Workbook

Sheet README
A1: SustainableTogether – Financial Verification Model (Proof of Concept)
A3: Purpose
A4: Early economic verification of the SustainableTogether photovoltaic product-as-a-service (PaaS) business model,
A5: as part of the FBC–EA–SE integration framework (paper: Toward Net-Positive Systems).
A6: The model tests whether the business model concept is economically viable BEFORE any architectural or engineering commitment.
A8: How to read this workbook
A9: Assumptions: all input parameters for both iterations (blue = inputs you can change).
A10: Iteration 1: conventional one-to-one conversion of the PV sales business into a lease model. RESULT: FAILS economic verification.
A11: Iteration 2: business model adjusted after financial AND Future-Fit verification (circular procurement, C2C design,
A12: flexibility aggregation, longer service life). RESULT: PASSES economic verification.
A13: Summary: key results and verification verdicts.
A15: Scope and disclaimer
... A17: Not investment advice. Companion files: SustainableTogether_FBMC_Analysis.docx, SustainableTogether_FFBB_Assessment.xlsx.

Sheet Assumptions
A1: Parameter | B1: Unit | C1: Iteration 1 | D1: Iteration 2 | E1: Rationale / link to verification loop
A2: Planning horizon | B2: years | C2: 20 | D2: 20 | E2: Fleet model horizon
A3: Fleet build-up period | B3: years | C3: 10 | D3: 10 | E3: New installations in years 1–10 only
A4: New systems per year | B4: # | C4: 200 | D4: 200 | E4: From FBC: ~200 new customers per year (canvas, Benefits)
A5: System size | B5: kWp / kWh | C5: 8 / 10 | D5: 8 / 10 | E5: Residential reference system with storage
A6: CAPEX per system | B6: EUR | C6: 16500 | D6: 12500 | E6: It.2: 30% refurbished module pool, wholesale procurement, demountable C2C mounting (FFBB BE04/BE19 actions)
A7: Customer acquisition cost | B7: EUR/system | C7: 600 | D7: 400 | E7: It.2: community channel and word-of-mouth (FBC Channels)
A8: Lease fee | B8: EUR/month | C8: 119 | D8: 149 | E8: It.2 incl. full service guarantee; still below comparable market offers (~150–180 EUR/mo)
A9: Grid / flexibility revenue | B9: EUR/system/yr | C9: 60 | D9: 140 | E9: It.2: aggregation of storage into virtual power plant (FBC value co-creation: stabilize the grid)
A10: O&M cost | B10: EUR/system/yr | C10: 345 | D10: 320 | E10: It.2: demountable design eases service and repair
A11: Sustainability opex | B11: EUR/system/yr | C11: 0 | D11: 90 | E11: It.2: electric service vans, take-back reserve, living-wage clause, supplier audits (FFBB actions)
A12: SG&A fixed | B12: EUR/yr | C12: 250000 | D12: 250000 | E12: Core team
A13: SG&A variable | B13: EUR/system/yr | C13: 60 | D13: 60 | E13: Billing, support, software
A14: System service life | B14: years | C14: 20 | D14: 24 | E14: It.2: design for longevity and second life (FFBB BE19)
A15: WACC (discount rate) | B15: % | C15: 0.06 | D15: 0.06 | E15: Illustrative cost of capital
A16: Tax rate | B16: % | C16: 0.3 | D16: 0.3 | E16: Simplified corporate tax
A17: Terminal value haircut | B17: % | C17: 0.8 | D17: 0.8 | E17: Conservative factor on remaining lease margins at year 20

Sheet Iteration 1
A1: All figures in EUR unless stated. Years across columns.
A3: Year | B3: 1 | C3: 2 | D3: 3 | E3: 4 | F3: 5 | G3: 6 | H3: 7 | I3: 8 | J3: 9 | K3: 10 | L3: 11 | M3: 12 | N3: 13 | O3: 14 | P3: 15 | Q3: 16 | R3: 17 | S3: 18 | T3: 19 | U3: 20
A4: New systems | B4: =IF(B3<=Assumptions!$C$3,Assumptions!$C$4,0) -> 200 | C4: =IF(C3<=Assumptions!$C$3,Assumptions!$C$4,0) -> 200 | D4: =IF(D3<=Assumptions!$C$3,Assumptions!$C$4,0) -> 200 | E4: =IF(E3<=Assumptions!$C$3,Assumptions!$C$4,0) -> 200 | F4: =IF(F3<=Assumptions!$C$3,Assumptions!$C$4,0) -> 200 | G4: =IF(G3<=Assumptions!$C$3,Assumptions!$C$4,0) -> 200 | H4: =IF(H3<=Assumptions!$C$3,Assumptions!$C$4,0) -> 200 | I4: =IF(I3<=Assumptions!$C$3,Assumptions!$C$4,0) -> 200 | ... U4: =IF(U3<=Assumptions!$C$3,Assumptions!$C$4,0) -> 0
A5: Cumulative fleet | B5: =Assumptions!$C$4*MIN(B3,Assumptions!$C$3) -> 200 | C5: =Assumptions!$C$4*MIN(C3,Assumptions!$C$3) -> 400 | D5: =Assumptions!$C$4*MIN(D3,Assumptions!$C$3) -> 600 | E5: =Assumptions!$C$4*MIN(E3,Assumptions!$C$3) -> 800 | F5: =Assumptions!$C$4*MIN(F3,Assumptions!$C$3) -> 1000 | G5: =Assumptions!$C$4*MIN(G3,Assumptions!$C$3) -> 1200 | H5: =Assumptions!$C$4*MIN(H3,Assumptions!$C$3) -> 1400 | I5: =Assumptions!$C$4*MIN(I3,Assumptions!$C$3) -> 1600 | ... U5: =Assumptions!$C$4*MIN(U3,Assumptions!$C$3) -> 2000
A6: Lease revenue | B6: =B5*Assumptions!$C$8*12 -> 285600 | C6: =C5*Assumptions!$C$8*12 -> 571200 | D6: =D5*Assumptions!$C$8*12 -> 856800 | E6: =E5*Assumptions!$C$8*12 -> 1142400 | F6: =F5*Assumptions!$C$8*12 -> 1428000 | G6: =G5*Assumptions!$C$8*12 -> 1713600 | H6: =H5*Assumptions!$C$8*12 -> 1999200 | I6: =I5*Assumptions!$C$8*12 -> 2284800 | ... U6: =U5*Assumptions!$C$8*12 -> 2856000
A7: Grid/flex revenue | B7: =B5*Assumptions!$C$9 -> 12000 | C7: =C5*Assumptions!$C$9 -> 24000 | D7: =D5*Assumptions!$C$9 -> 36000 | E7: =E5*Assumptions!$C$9 -> 48000 | F7: =F5*Assumptions!$C$9 -> 60000 | G7: =G5*Assumptions!$C$9 -> 72000 | H7: =H5*Assumptions!$C$9 -> 84000 | I7: =I5*Assumptions!$C$9 -> 96000 | ... U7: =U5*Assumptions!$C$9 -> 120000
A8: Total revenue | B8: =B6+B7 -> 297600 | C8: =C6+C7 -> 595200 | D8: =D6+D7 -> 892800 | E8: =E6+E7 -> 1190400 | F8: =F6+F7 -> 1488000 | G8: =G6+G7 -> 1785600 | H8: =H6+H7 -> 2083200 | I8: =I6+I7 -> 2380800 | ... U8: =U6+U7 -> 2976000
A9: O&M cost | B9: =-B5*Assumptions!$C$10 -> -69000 | C9: =-C5*Assumptions!$C$10 -> -138000 | D9: =-D5*Assumptions!$C$10 -> -207000 | E9: =-E5*Assumptions!$C$10 -> -276000 | F9: =-F5*Assumptions!$C$10 -> -345000 | G9: =-G5*Assumptions!$C$10 -> -414000 | H9: =-H5*Assumptions!$C$10 -> -483000 | I9: =-I5*Assumptions!$C$10 -> -552000 | ... U9: =-U5*Assumptions!$C$10 -> -690000
A10: Sustainability opex | B10: =-B5*Assumptions!$C$11 -> 0 | C10: =-C5*Assumptions!$C$11 -> 0 | D10: =-D5*Assumptions!$C$11 -> 0 | E10: =-E5*Assumptions!$C$11 -> 0 | F10: =-F5*Assumptions!$C$11 -> 0 | G10: =-G5*Assumptions!$C$11 -> 0 | H10: =-H5*Assumptions!$C$11 -> 0 | I10: =-I5*Assumptions!$C$11 -> 0 | ... U10: =-U5*Assumptions!$C$11 -> 0
A11: SG&A | B11: =-(Assumptions!$C$12+Assumptions!$C$13*B5) -> -262000 | C11: =-(Assumptions!$C$12+Assumptions!$C$13*C5) -> -274000 | D11: =-(Assumptions!$C$12+Assumptions!$C$13*D5) -> -286000 | E11: =-(Assumptions!$C$12+Assumptions!$C$13*E5) -> -298000 | F11: =-(Assumptions!$C$12+Assumptions!$C$13*F5) -> -310000 | G11: =-(Assumptions!$C$12+Assumptions!$C$13*G5) -> -322000 | H11: =-(Assumptions!$C$12+Assumptions!$C$13*H5) -> -334000 | I11: =-(Assumptions!$C$12+Assumptions!$C$13*I5) -> -346000 | ... U11: =-(Assumptions!$C$12+Assumptions!$C$13*U5) -> -370000
A12: EBITDA | B12: =B8+B9+B10+B11 -> -33400 | C12: =C8+C9+C10+C11 -> 183200 | D12: =D8+D9+D10+D11 -> 399800 | E12: =E8+E9+E10+E11 -> 616400 | F12: =F8+F9+F10+F11 -> 833000 | G12: =G8+G9+G10+G11 -> 1049600 | H12: =H8+H9+H10+H11 -> 1266200 | I12: =I8+I9+I10+I11 -> 1482800 | ... U12: =U8+U9+U10+U11 -> 1916000
A13: Depreciation | B13: =-Assumptions!$C$6*B5/Assumptions!$C$14 -> -165000 | C13: =-Assumptions!$C$6*C5/Assumptions!$C$14 -> -330000 | D13: =-Assumptions!$C$6*D5/Assumptions!$C$14 -> -495000 | E13: =-Assumptions!$C$6*E5/Assumptions!$C$14 -> -660000 | F13: =-Assumptions!$C$6*F5/Assumptions!$C$14 -> -825000 | G13: =-Assumptions!$C$6*G5/Assumptions!$C$14 -> -990000 | H13: =-Assumptions!$C$6*H5/Assumptions!$C$14 -> -1155000 | I13: =-Assumptions!$C$6*I5/Assumptions!$C$14 -> -1320000 | ... U13: =-Assumptions!$C$6*U5/Assumptions!$C$14 -> -1650000
A14: EBT | B14: =B12+B13 -> -198400 | C14: =C12+C13 -> -146800 | D14: =D12+D13 -> -95200 | E14: =E12+E13 -> -43600 | F14: =F12+F13 -> 8000 | G14: =G12+G13 -> 59600 | H14: =H12+H13 -> 111200 | I14: =I12+I13 -> 162800 | ... U14: =U12+U13 -> 266000
A15: Tax | B15: =-MAX(0,B14)*Assumptions!$C$16 -> 0 | C15: =-MAX(0,C14)*Assumptions!$C$16 -> 0 | D15: =-MAX(0,D14)*Assumptions!$C$16 -> 0 | E15: =-MAX(0,E14)*Assumptions!$C$16 -> 0 | F15: =-MAX(0,F14)*Assumptions!$C$16 -> -2400 | G15: =-MAX(0,G14)*Assumptions!$C$16 -> -17880 | H15: =-MAX(0,H14)*Assumptions!$C$16 -> -33360 | I15: =-MAX(0,I14)*Assumptions!$C$16 -> -48840 | ... U15: =-MAX(0,U14)*Assumptions!$C$16 -> -79800
A16: CAPEX | B16: =-B4*Assumptions!$C$6 -> -3300000 | C16: =-C4*Assumptions!$C$6 -> -3300000 | D16: =-D4*Assumptions!$C$6 -> -3300000 | E16: =-E4*Assumptions!$C$6 -> -3300000 | F16: =-F4*Assumptions!$C$6 -> -3300000 | G16: =-G4*Assumptions!$C$6 -> -3300000 | H16: =-H4*Assumptions!$C$6 -> -3300000 | I16: =-I4*Assumptions!$C$6 -> -3300000 | ... U16: =-U4*Assumptions!$C$6 -> 0
A17: Customer acquisition | B17: =-B4*Assumptions!$C$7 -> -120000 | C17: =-C4*Assumptions!$C$7 -> -120000 | D17: =-D4*Assumptions!$C$7 -> -120000 | E17: =-E4*Assumptions!$C$7 -> -120000 | F17: =-F4*Assumptions!$C$7 -> -120000 | G17: =-G4*Assumptions!$C$7 -> -120000 | H17: =-H4*Assumptions!$C$7 -> -120000 | I17: =-I4*Assumptions!$C$7 -> -120000 | ... U17: =-U4*Assumptions!$C$7 -> 0
A18: Free cash flow | B18: =B12+B15+B16+B17 -> -3453400 | C18: =C12+C15+C16+C17 -> -3236800 | D18: =D12+D15+D16+D17 -> -3020200 | E18: =E12+E15+E16+E17 -> -2803600 | F18: =F12+F15+F16+F17 -> -2589400 | G18: =G12+G15+G16+G17 -> -2388280 | H18: =H12+H15+H16+H17 -> -2187160 | I18: =I12+I15+I16+I17 -> -1986040 | ... U18: =U12+U15+U16+U17 -> 1836200
A19: Terminal value | B19: =IF(B3=20,TVcalc!$B$16,0) -> 0 | C19: =IF(C3=20,TVcalc!$B$16,0) -> 0 | D19: =IF(D3=20,TVcalc!$B$16,0) -> 0 | E19: =IF(E3=20,TVcalc!$B$16,0) -> 0 | F19: =IF(F3=20,TVcalc!$B$16,0) -> 0 | G19: =IF(G3=20,TVcalc!$B$16,0) -> 0 | H19: =IF(H3=20,TVcalc!$B$16,0) -> 0 | I19: =IF(I3=20,TVcalc!$B$16,0) -> 0 | ... U19: =IF(U3=20,TVcalc!$B$16,0) -> 7624068.6
A20: Net cash flow | B20: =B18+B19 -> -3453400 | C20: =C18+C19 -> -3236800 | D20: =D18+D19 -> -3020200 | E20: =E18+E19 -> -2803600 | F20: =F18+F19 -> -2589400 | G20: =G18+G19 -> -2388280 | H20: =H18+H19 -> -2187160 | I20: =I18+I19 -> -1986040 | ... U20: =U18+U19 -> 9460268.6
A21: Discounted CF | B21: =B20/(1+Assumptions!$C$15)^B3 -> -3257924.5 | C21: =C20/(1+Assumptions!$C$15)^C3 -> -2880740.5 | D21: =D20/(1+Assumptions!$C$15)^D3 -> -2535818.2 | E21: =E20/(1+Assumptions!$C$15)^E3 -> -2220713.8 | F21: =F20/(1+Assumptions!$C$15)^F3 -> -1934950.3 | G21: =G20/(1+Assumptions!$C$15)^G3 -> -1683643.2 | H21: =H20/(1+Assumptions!$C$15)^H3 -> -1454586.3 | I21: =I20/(1+Assumptions!$C$15)^I3 -> -1246066.1 | ... U21: =U20/(1+Assumptions!$C$15)^U3 -> 2949756.5
A23: Results
A24: NPV @ WACC (EUR) | B24: =SUM(B21:U21) -> -9231621.7
A25: IRR | B25: =IRR(B20:U20,0.05) -> 0.0031166311
A26: Margin per system (EUR/yr) | B26: =Assumptions!$C$8*12+Assumptions!$C$9-Assumptions!$C$10-Assumptions!$C$11-Assumptions!$C$13 -> 1083
A27: Simple payback per system (yrs) | B27: =Assumptions!$C$6/B26 -> 15.235457
A28: Verification verdict | B28: =IF(AND(B24>0,B25>Assumptions!$C$15),"PASS – proceed to EA/SE transformation","FAIL – revise business model") -> FAIL – revise business model

Sheet Iteration 2
A1: All figures in EUR unless stated. Years across columns.
A3: Year | B3: 1 | C3: 2 | D3: 3 | E3: 4 | F3: 5 | G3: 6 | H3: 7 | I3: 8 | J3: 9 | K3: 10 | L3: 11 | M3: 12 | N3: 13 | O3: 14 | P3: 15 | Q3: 16 | R3: 17 | S3: 18 | T3: 19 | U3: 20
A4: New systems | B4: =IF(B3<=Assumptions!$D$3,Assumptions!$D$4,0) -> 200 | C4: =IF(C3<=Assumptions!$D$3,Assumptions!$D$4,0) -> 200 | D4: =IF(D3<=Assumptions!$D$3,Assumptions!$D$4,0) -> 200 | E4: =IF(E3<=Assumptions!$D$3,Assumptions!$D$4,0) -> 200 | F4: =IF(F3<=Assumptions!$D$3,Assumptions!$D$4,0) -> 200 | G4: =IF(G3<=Assumptions!$D$3,Assumptions!$D$4,0) -> 200 | H4: =IF(H3<=Assumptions!$D$3,Assumptions!$D$4,0) -> 200 | I4: =IF(I3<=Assumptions!$D$3,Assumptions!$D$4,0) -> 200 | ... U4: =IF(U3<=Assumptions!$D$3,Assumptions!$D$4,0) -> 0
A5: Cumulative fleet | B5: =Assumptions!$D$4*MIN(B3,Assumptions!$D$3) -> 200 | C5: =Assumptions!$D$4*MIN(C3,Assumptions!$D$3) -> 400 | D5: =Assumptions!$D$4*MIN(D3,Assumptions!$D$3) -> 600 | E5: =Assumptions!$D$4*MIN(E3,Assumptions!$D$3) -> 800 | F5: =Assumptions!$D$4*MIN(F3,Assumptions!$D$3) -> 1000 | G5: =Assumptions!$D$4*MIN(G3,Assumptions!$D$3) -> 1200 | H5: =Assumptions!$D$4*MIN(H3,Assumptions!$D$3) -> 1400 | I5: =Assumptions!$D$4*MIN(I3,Assumptions!$D$3) -> 1600 | ... U5: =Assumptions!$D$4*MIN(U3,Assumptions!$D$3) -> 2000
A6: Lease revenue | B6: =B5*Assumptions!$D$8*12 -> 357600 | C6: =C5*Assumptions!$D$8*12 -> 715200 | D6: =D5*Assumptions!$D$8*12 -> 1072800 | E6: =E5*Assumptions!$D$8*12 -> 1430400 | F6: =F5*Assumptions!$D$8*12 -> 1788000 | G6: =G5*Assumptions!$D$8*12 -> 2145600 | H6: =H5*Assumptions!$D$8*12 -> 2503200 | I6: =I5*Assumptions!$D$8*12 -> 2860800 | ... U6: =U5*Assumptions!$D$8*12 -> 3576000
A7: Grid/flex revenue | B7: =B5*Assumptions!$D$9 -> 28000 | C7: =C5*Assumptions!$D$9 -> 56000 | D7: =D5*Assumptions!$D$9 -> 84000 | E7: =E5*Assumptions!$D$9 -> 112000 | F7: =F5*Assumptions!$D$9 -> 140000 | G7: =G5*Assumptions!$D$9 -> 168000 | H7: =H5*Assumptions!$D$9 -> 196000 | I7: =I5*Assumptions!$D$9 -> 224000 | ... U7: =U5*Assumptions!$D$9 -> 280000
A8: Total revenue | B8: =B6+B7 -> 385600 | C8: =C6+C7 -> 771200 | D8: =D6+D7 -> 1156800 | E8: =E6+E7 -> 1542400 | F8: =F6+F7 -> 1928000 | G8: =G6+G7 -> 2313600 | H8: =H6+H7 -> 2699200 | I8: =I6+I7 -> 3084800 | ... U8: =U6+U7 -> 3856000
A9: O&M cost | B9: =-B5*Assumptions!$D$10 -> -64000 | C9: =-C5*Assumptions!$D$10 -> -128000 | D9: =-D5*Assumptions!$D$10 -> -192000 | E9: =-E5*Assumptions!$D$10 -> -256000 | F9: =-F5*Assumptions!$D$10 -> -320000 | G9: =-G5*Assumptions!$D$10 -> -384000 | H9: =-H5*Assumptions!$D$10 -> -448000 | I9: =-I5*Assumptions!$D$10 -> -512000 | ... U9: =-U5*Assumptions!$D$10 -> -640000
A10: Sustainability opex | B10: =-B5*Assumptions!$D$11 -> -18000 | C10: =-C5*Assumptions!$D$11 -> -36000 | D10: =-D5*Assumptions!$D$11 -> -54000 | E10: =-E5*Assumptions!$D$11 -> -72000 | F10: =-F5*Assumptions!$D$11 -> -90000 | G10: =-G5*Assumptions!$D$11 -> -108000 | H10: =-H5*Assumptions!$D$11 -> -126000 | I10: =-I5*Assumptions!$D$11 -> -144000 | ... U10: =-U5*Assumptions!$D$11 -> -180000
A11: SG&A | B11: =-(Assumptions!$D$12+Assumptions!$D$13*B5) -> -262000 | C11: =-(Assumptions!$D$12+Assumptions!$D$13*C5) -> -274000 | D11: =-(Assumptions!$D$12+Assumptions!$D$13*D5) -> -286000 | E11: =-(Assumptions!$D$12+Assumptions!$D$13*E5) -> -298000 | F11: =-(Assumptions!$D$12+Assumptions!$D$13*F5) -> -310000 | G11: =-(Assumptions!$D$12+Assumptions!$D$13*G5) -> -322000 | H11: =-(Assumptions!$D$12+Assumptions!$D$13*H5) -> -334000 | I11: =-(Assumptions!$D$12+Assumptions!$D$13*I5) -> -346000 | ... U11: =-(Assumptions!$D$12+Assumptions!$D$13*U5) -> -370000
A12: EBITDA | B12: =B8+B9+B10+B11 -> 41600 | C12: =C8+C9+C10+C11 -> 333200 | D12: =D8+D9+D10+D11 -> 624800 | E12: =E8+E9+E10+E11 -> 916400 | F12: =F8+F9+F10+F11 -> 1208000 | G12: =G8+G9+G10+G11 -> 1499600 | H12: =H8+H9+H10+H11 -> 1791200 | I12: =I8+I9+I10+I11 -> 2082800 | ... U12: =U8+U9+U10+U11 -> 2666000
A13: Depreciation | B13: =-Assumptions!$D$6*B5/Assumptions!$D$14 -> -104166.67 | C13: =-Assumptions!$D$6*C5/Assumptions!$D$14 -> -208333.33 | D13: =-Assumptions!$D$6*D5/Assumptions!$D$14 -> -312500 | E13: =-Assumptions!$D$6*E5/Assumptions!$D$14 -> -416666.67 | F13: =-Assumptions!$D$6*F5/Assumptions!$D$14 -> -520833.33 | G13: =-Assumptions!$D$6*G5/Assumptions!$D$14 -> -625000 | H13: =-Assumptions!$D$6*H5/Assumptions!$D$14 -> -729166.67 | I13: =-Assumptions!$D$6*I5/Assumptions!$D$14 -> -833333.33 | ... U13: =-Assumptions!$D$6*U5/Assumptions!$D$14 -> -1041666.7
A14: EBT | B14: =B12+B13 -> -62566.667 | C14: =C12+C13 -> 124866.67 | D14: =D12+D13 -> 312300 | E14: =E12+E13 -> 499733.33 | F14: =F12+F13 -> 687166.67 | G14: =G12+G13 -> 874600 | H14: =H12+H13 -> 1062033.3 | I14: =I12+I13 -> 1249466.7 | ... U14: =U12+U13 -> 1624333.3
A15: Tax | B15: =-MAX(0,B14)*Assumptions!$D$16 -> 0 | C15: =-MAX(0,C14)*Assumptions!$D$16 -> -37460 | D15: =-MAX(0,D14)*Assumptions!$D$16 -> -93690 | E15: =-MAX(0,E14)*Assumptions!$D$16 -> -149920 | F15: =-MAX(0,F14)*Assumptions!$D$16 -> -206150 | G15: =-MAX(0,G14)*Assumptions!$D$16 -> -262380 | H15: =-MAX(0,H14)*Assumptions!$D$16 -> -318610 | I15: =-MAX(0,I14)*Assumptions!$D$16 -> -374840 | ... U15: =-MAX(0,U14)*Assumptions!$D$16 -> -487300
A16: CAPEX | B16: =-B4*Assumptions!$D$6 -> -2500000 | C16: =-C4*Assumptions!$D$6 -> -2500000 | D16: =-D4*Assumptions!$D$6 -> -2500000 | E16: =-E4*Assumptions!$D$6 -> -2500000 | F16: =-F4*Assumptions!$D$6 -> -2500000 | G16: =-G4*Assumptions!$D$6 -> -2500000 | H16: =-H4*Assumptions!$D$6 -> -2500000 | I16: =-I4*Assumptions!$D$6 -> -2500000 | ... U16: =-U4*Assumptions!$D$6 -> 0
A17: Customer acquisition | B17: =-B4*Assumptions!$D$7 -> -80000 | C17: =-C4*Assumptions!$D$7 -> -80000 | D17: =-D4*Assumptions!$D$7 -> -80000 | E17: =-E4*Assumptions!$D$7 -> -80000 | F17: =-F4*Assumptions!$D$7 -> -80000 | G17: =-G4*Assumptions!$D$7 -> -80000 | H17: =-H4*Assumptions!$D$7 -> -80000 | I17: =-I4*Assumptions!$D$7 -> -80000 | ... U17: =-U4*Assumptions!$D$7 -> 0
A18: Free cash flow | B18: =B12+B15+B16+B17 -> -2538400 | C18: =C12+C15+C16+C17 -> -2284260 | D18: =D12+D15+D16+D17 -> -2048890 | E18: =E12+E15+E16+E17 -> -1813520 | F18: =F12+F15+F16+F17 -> -1578150 | G18: =G12+G15+G16+G17 -> -1342780 | H18: =H12+H15+H16+H17 -> -1107410 | I18: =I12+I15+I16+I17 -> -872040 | ... U18: =U12+U15+U16+U17 -> 2178700
A19: Terminal value | B19: =IF(B3=20,TVcalc2!$B$16,0) -> 0 | C19: =IF(C3=20,TVcalc2!$B$16,0) -> 0 | D19: =IF(D3=20,TVcalc2!$B$16,0) -> 0 | E19: =IF(E3=20,TVcalc2!$B$16,0) -> 0 | F19: =IF(F3=20,TVcalc2!$B$16,0) -> 0 | G19: =IF(G3=20,TVcalc2!$B$16,0) -> 0 | H19: =IF(H3=20,TVcalc2!$B$16,0) -> 0 | I19: =IF(I3=20,TVcalc2!$B$16,0) -> 0 | ... U19: =IF(U3=20,TVcalc2!$B$16,0) -> 16213433
A20: Net cash flow | B20: =B18+B19 -> -2538400 | C20: =C18+C19 -> -2284260 | D20: =D18+D19 -> -2048890 | E20: =E18+E19 -> -1813520 | F20: =F18+F19 -> -1578150 | G20: =G18+G19 -> -1342780 | H20: =H18+H19 -> -1107410 | I20: =I18+I19 -> -872040 | ... U20: =U18+U19 -> 18392133
A21: Discounted CF | B21: =B20/(1+Assumptions!$D$15)^B3 -> -2394717 | C21: =C20/(1+Assumptions!$D$15)^C3 -> -2032983.3 | D21: =D20/(1+Assumptions!$D$15)^D3 -> -1720287.6 | E21: =E20/(1+Assumptions!$D$15)^E3 -> -1436477.7 | F21: =F20/(1+Assumptions!$D$15)^F3 -> -1179285.5 | G21: =G20/(1+Assumptions!$D$15)^G3 -> -946606.91 | H21: =H20/(1+Assumptions!$D$15)^H3 -> -736490.9 | I21: =I20/(1+Assumptions!$D$15)^I3 -> -547128.68 | ... U21: =U20/(1+Assumptions!$D$15)^U3 -> 5734754
A23: Results
A24: NPV @ WACC (EUR) | B24: =SUM(B21:U21) -> 2414615.5
A25: IRR | B25: =IRR(B20:U20,0.05) -> 0.075565143
A26: Margin per system (EUR/yr) | B26: =Assumptions!$D$8*12+Assumptions!$D$9-Assumptions!$D$10-Assumptions!$D$11-Assumptions!$D$13 -> 1458
A27: Simple payback per system (yrs) | B27: =Assumptions!$D$6/B26 -> 8.5733882
A28: Verification verdict | B28: =IF(AND(B24>0,B25>Assumptions!$D$15),"PASS – proceed to EA/SE transformation","FAIL – revise business model") -> PASS – proceed to EA/SE transformation

Sheet TVcalc
A1: Terminal value at year 20: PV of remaining lease margins per installation cohort (haircut applied)
A3: Cohort (install yr) | B3: Remaining life @ yr 20 | C3: Annuity factor | D3: TV contribution
A4: 1 | B4: =MAX(0,Assumptions!$C$14-(20-A4)) -> 1 | C4: =IF(B4=0,0,(1-(1+Assumptions!$C$15)^-B4)/Assumptions!$C$15) -> 0.94339623 | D4: =Assumptions!$C$4*('Iteration 1'!$B$26)*Assumptions!$C$17*C4 -> 163471.7
A5: 2 | B5: =MAX(0,Assumptions!$C$14-(20-A5)) -> 2 | C5: =IF(B5=0,0,(1-(1+Assumptions!$C$15)^-B5)/Assumptions!$C$15) -> 1.8333927 | D5: =Assumptions!$C$4*('Iteration 1'!$B$26)*Assumptions!$C$17*C5 -> 317690.28
A6: 3 | B6: =MAX(0,Assumptions!$C$14-(20-A6)) -> 3 | C6: =IF(B6=0,0,(1-(1+Assumptions!$C$15)^-B6)/Assumptions!$C$15) -> 2.6730119 | D6: =Assumptions!$C$4*('Iteration 1'!$B$26)*Assumptions!$C$17*C6 -> 463179.51
A7: 4 | B7: =MAX(0,Assumptions!$C$14-(20-A7)) -> 4 | C7: =IF(B7=0,0,(1-(1+Assumptions!$C$15)^-B7)/Assumptions!$C$15) -> 3.4651056 | D7: =Assumptions!$C$4*('Iteration 1'!$B$26)*Assumptions!$C$17*C7 -> 600433.5
A8: 5 | B8: =MAX(0,Assumptions!$C$14-(20-A8)) -> 5 | C8: =IF(B8=0,0,(1-(1+Assumptions!$C$15)^-B8)/Assumptions!$C$15) -> 4.2123638 | D8: =Assumptions!$C$4*('Iteration 1'!$B$26)*Assumptions!$C$17*C8 -> 729918.4
A9: 6 | B9: =MAX(0,Assumptions!$C$14-(20-A9)) -> 6 | C9: =IF(B9=0,0,(1-(1+Assumptions!$C$15)^-B9)/Assumptions!$C$15) -> 4.9173243 | D9: =Assumptions!$C$4*('Iteration 1'!$B$26)*Assumptions!$C$17*C9 -> 852073.96
A10: 7 | B10: =MAX(0,Assumptions!$C$14-(20-A10)) -> 7 | C10: =IF(B10=0,0,(1-(1+Assumptions!$C$15)^-B10)/Assumptions!$C$15) -> 5.5823814 | D10: =Assumptions!$C$4*('Iteration 1'!$B$26)*Assumptions!$C$17*C10 -> 967315.06
A11: 8 | B11: =MAX(0,Assumptions!$C$14-(20-A11)) -> 8 | C11: =IF(B11=0,0,(1-(1+Assumptions!$C$15)^-B11)/Assumptions!$C$15) -> 6.2097938 | D11: =Assumptions!$C$4*('Iteration 1'!$B$26)*Assumptions!$C$17*C11 -> 1076033.1
A12: 9 | B12: =MAX(0,Assumptions!$C$14-(20-A12)) -> 9 | C12: =IF(B12=0,0,(1-(1+Assumptions!$C$15)^-B12)/Assumptions!$C$15) -> 6.8016923 | D12: =Assumptions!$C$4*('Iteration 1'!$B$26)*Assumptions!$C$17*C12 -> 1178597.2
A13: 10 | B13: =MAX(0,Assumptions!$C$14-(20-A13)) -> 10 | C13: =IF(B13=0,0,(1-(1+Assumptions!$C$15)^-B13)/Assumptions!$C$15) -> 7.3600871 | D13: =Assumptions!$C$4*('Iteration 1'!$B$26)*Assumptions!$C$17*C13 -> 1275355.9
A15: Total TV
A16: (used in model) | B16: =SUM(D4:D13) -> 7624068.6

Sheet TVcalc2
A1: Terminal value at year 20: PV of remaining lease margins per installation cohort (haircut applied)
A3: Cohort (install yr) | B3: Remaining life @ yr 20 | C3: Annuity factor | D3: TV contribution
A4: 1 | B4: =MAX(0,Assumptions!$D$14-(20-A4)) -> 5 | C4: =IF(B4=0,0,(1-(1+Assumptions!$D$15)^-B4)/Assumptions!$D$15) -> 4.2123638 | D4: =Assumptions!$D$4*('Iteration 2'!$B$26)*Assumptions!$D$17*C4 -> 982660.22
A5: 2 | B5: =MAX(0,Assumptions!$D$14-(20-A5)) -> 6 | C5: =IF(B5=0,0,(1-(1+Assumptions!$D$15)^-B5)/Assumptions!$D$15) -> 4.9173243 | D5: =Assumptions!$D$4*('Iteration 2'!$B$26)*Assumptions!$D$17*C5 -> 1147113.4
A6: 3 | B6: =MAX(0,Assumptions!$D$14-(20-A6)) -> 7 | C6: =IF(B6=0,0,(1-(1+Assumptions!$D$15)^-B6)/Assumptions!$D$15) -> 5.5823814 | D6: =Assumptions!$D$4*('Iteration 2'!$B$26)*Assumptions!$D$17*C6 -> 1302257.9
A7: 4 | B7: =MAX(0,Assumptions!$D$14-(20-A7)) -> 8 | C7: =IF(B7=0,0,(1-(1+Assumptions!$D$15)^-B7)/Assumptions!$D$15) -> 6.2097938 | D7: =Assumptions!$D$4*('Iteration 2'!$B$26)*Assumptions!$D$17*C7 -> 1448620.7
A8: 5 | B8: =MAX(0,Assumptions!$D$14-(20-A8)) -> 9 | C8: =IF(B8=0,0,(1-(1+Assumptions!$D$15)^-B8)/Assumptions!$D$15) -> 6.8016923 | D8: =Assumptions!$D$4*('Iteration 2'!$B$26)*Assumptions!$D$17*C8 -> 1586698.8
A9: 6 | B9: =MAX(0,Assumptions!$D$14-(20-A9)) -> 10 | C9: =IF(B9=0,0,(1-(1+Assumptions!$D$15)^-B9)/Assumptions!$D$15) -> 7.3600871 | D9: =Assumptions!$D$4*('Iteration 2'!$B$26)*Assumptions!$D$17*C9 -> 1716961.1
A10: 7 | B10: =MAX(0,Assumptions!$D$14-(20-A10)) -> 11 | C10: =IF(B10=0,0,(1-(1+Assumptions!$D$15)^-B10)/Assumptions!$D$15) -> 7.8868746 | D10: =Assumptions!$D$4*('Iteration 2'!$B$26)*Assumptions!$D$17*C10 -> 1839850.1
A11: 8 | B11: =MAX(0,Assumptions!$D$14-(20-A11)) -> 12 | C11: =IF(B11=0,0,(1-(1+Assumptions!$D$15)^-B11)/Assumptions!$D$15) -> 8.3838439 | D11: =Assumptions!$D$4*('Iteration 2'!$B$26)*Assumptions!$D$17*C11 -> 1955783.1
A12: 9 | B12: =MAX(0,Assumptions!$D$14-(20-A12)) -> 13 | C12: =IF(B12=0,0,(1-(1+Assumptions!$D$15)^-B12)/Assumptions!$D$15) -> 8.852683 | D12: =Assumptions!$D$4*('Iteration 2'!$B$26)*Assumptions!$D$17*C12 -> 2065153.9
A13: 10 | B13: =MAX(0,Assumptions!$D$14-(20-A13)) -> 14 | C13: =IF(B13=0,0,(1-(1+Assumptions!$D$15)^-B13)/Assumptions!$D$15) -> 9.2949839 | D13: =Assumptions!$D$4*('Iteration 2'!$B$26)*Assumptions!$D$17*C13 -> 2168333.9
A15: Total TV
A16: (used in model) | B16: =SUM(D4:D13) -> 16213433

Sheet Summary
A1: Verification Summary – SustainableTogether PV Product-as-a-Service
A3: Indicator | B3: Iteration 1 (initial concept) | C3: Iteration 2 (adjusted concept)
A4: NPV @ 6% WACC (EUR) | B4: ='Iteration 1'!B24 -> -9231621.7 | C4: ='Iteration 2'!B24 -> 2414615.5
A5: IRR | B5: ='Iteration 1'!B25 -> 0.0031166311 | C5: ='Iteration 2'!B25 -> 0.075565143
A6: Margin per system (EUR/yr) | B6: ='Iteration 1'!B26 -> 1083 | C6: ='Iteration 2'!B26 -> 1458
A7: Simple payback (yrs) | B7: ='Iteration 1'!B27 -> 15.235457 | C7: ='Iteration 2'!B27 -> 8.5733882
A8: Economic verdict | B8: ='Iteration 1'!B28 -> FAIL – revise business model | C8: ='Iteration 2'!B28 -> PASS – proceed to EA/SE transformation
A10: Future-Fit verdict (see SustainableTogether_FFBB_Assessment.xlsx) | B10: FAIL: 2 of 23 Break-Even Goals below 50% fitness | C10: PASS: no goal below 50%, avg. fitness 88%
A12: Key Iteration 2 adjustments (driven by both verifications):
A13: • 30% refurbished module pool + audited wholesale procurement (CAPEX −24%, FFBB BE03/BE04)
A14: • Cradle-to-cradle demountable design, 24-yr service life + second life (FFBB BE19, lower O&M)
A15: • Storage aggregated into virtual power plant: flexibility revenue 140 EUR/system/yr (grid stabilization)
A16: • Lease repositioned at 149 EUR/month incl. full service guarantee (honest comms, FFBB BE15)
A17: • Sustainability opex 90 EUR/system/yr: e-vans, take-back reserve, living-wage clause, audits (BE06/BE07/BE11)
