Workbook

Sheet README
B1: FBMC ⇄ CLD Concept Registry — Single Source of Truth
B2: Version 0.1 (generic template) · SustainableTogether / INCOSE Sustainability WG · 2026-07-02
B4: 1. Purpose
B5: This workbook is the Concept Registry defined in 'FBMC-CLD-Semantic-Alignment.docx' and the draw.io ontology (page 3). Every concept that appears in the Flourishing Business Model Canvas, the Causal Loop Diagram, the future Vensim SD model, and the Excel financial model exists here exactly once, with a stable ID. The canvas and the CLD are projections of this registry — they are never edited independently.
B7: 2. Sheets
B8: Concepts — one row per MeasurableAttribute (the bridge concept: a measurable, time-varying attribute of exactly one FBMC element). Currently pre-filled with the 21 GENERIC concepts covering every FBMC block.
B9: CausalLinks — one row per causal link between two concepts, with polarity (+/-) and delay flag. From/To names are looked up automatically from Concepts.
B10: Loops — one row per feedback loop, as an ordered list of LinkIDs. Loop type R/B is DERIVED by formula from the number of negative links (odd = B). Never type R/B by hand.
B11: ChangeLog — every change to any sheet is recorded here first. This is what keeps FBMC and CLD synchronized.
B12: Lists — dropdown sources for data validation. Extend the lists here if a new FBMC block name or status value is ever needed.
B14: 3. How to APPEND a new concept (instantiation workflow)
A15: 1 | B15: Identify the FBMC element the new concept belongs to. If there is no canvas element, STOP — either add the element to the canvas first, or the concept does not belong in the model (invariant I1).
A16: 2 | B16: Ask: which measurable attribute of that element varies over time? Name it as a single-concept, direction-neutral noun phrase (no 'gain', 'reduction', 'pressure and X').
A17: 3 | B17: Add a row in Concepts with the next free ID (prefix: GEN- for generic, PV- for the SustainaSun instantiation). IDs are NEVER reused, even after retirement.
A18: 4 | B18: Fill: Definition, FBMC_Block (dropdown), FBMC_Element (the concrete canvas entry), Unit (mandatory before the SD stage), Dimension, SDType (dropdown; see derivation rules below), InCLDBoundary. If excluded from the CLD, give an ExclusionRationale (invariant I2).
A19: 5 | B19: Record the addition in ChangeLog (type 'add') BEFORE publishing any artifact that uses it.
A20: 6 | B20: Only then add CausalLinks that use the new concept, and update Loops if a feedback loop changes. Check the DerivedType column — if a loop's R/B changed, that is a finding, not an error.
B22: 4. How to RENAME / SPLIT / MERGE / RETIRE
B23: Rename: change CanonicalName and CLDVariableName in place (same ID), log 'rename' in ChangeLog with old and new name in the description. Keep old artifact names in the Name_v1/Name_v2 columns for traceability.
B24: Split: retire the old row (Status = retired, keep the row), create two new IDs, log 'split' referencing all three IDs.
B25: Merge: retire both old rows, create one new ID, log 'merge'. Re-point all CausalLinks that referenced the retired IDs.
B26: Retire: set Status = retired and InCLDBoundary = N with rationale. Never delete rows; never reuse IDs.
B28: 5. Derivation rules (FBMC element type → SDType)
B29: Resource / Biophysical Stock / engaged Stakeholder population / slow Relationship → Stock. Activity / Channel operation / Value Co-Creation / Co-Destruction → Flow. Ecosystem Service / Need satisfaction / perception / quality / Partnership strength → Auxiliary. Governance choice / contract term / policy → Parameter. Goal+Indicator → Output (must appear in the CLD, invariant I6).
B31: 6. Invariants — check before publishing any FBMC / CLD version
B32: I1 every CLD variable realizes exactly one Concept; every Concept anchors to exactly one FBMC element. I2 every FBMC element has ≥1 concept in the CLD or an exclusion rationale. I3 loop type is derived, never asserted. I4 single-concept, direction-neutral names. I5 actual ≠ perceived (separate concepts). I6 every Goal/Indicator concept appears in the CLD. I7 all changes go through ChangeLog first.
B34: 7. Cell colour code
B35: Yellow background = manual input required when instantiating (e.g. Unit, FBMC_Element, NegLinkCount). Black = formulas / fixed content — do not overwrite formula cells in CausalLinks (FromName/ToName) and Loops (DerivedType).

Sheet Lists
A1: FBMC_Block | B1: Dimension | C1: SDType | D1: YN | E1: Status | F1: ChangeType | G1: Polarity
A2: Actors (Who) | B2: Econ | C2: Stock | D2: Y | E2: draft | F2: add | G2: +
A3: Needs (Who) | B3: Soc | C3: Flow | D3: N | E3: reviewed | F3: rename | G3: -
A4: Stakeholders (Who) | B4: Eco | C4: Auxiliary | E4: approved | F4: split
A5: Relationships (People) | B5: Econ+Soc | C5: Parameter | E5: retired | F5: merge
A6: Channels (People) | B6: Econ+Eco | C6: Output | F6: retire
A7: Value Co-Creations (Value) | B7: Soc+Eco | F7: link-change
A8: Value Co-Destructions (Value) | B8: Econ+Soc+Eco | F8: loop-change
A9: Products/Services (Value) | F9: gate-approval
A10: Activities (Process)
A11: Resources (Process)
A12: Partnerships (Process)
A13: Governance (Process)
A14: Biophysical Stocks (Environment)
A15: Ecosystem Services (Environment)
A16: Costs (Outcomes)
A17: Benefits (Outcomes)
A18: Goals (Outcomes)
A19: Context: Environment
A20: Context: Society
A21: Context: Economy

Sheet Concepts
A1: ID | B1: CanonicalName | C1: Definition | D1: FBMC_Block | E1: FBMC_Element (instance) | F1: Unit | G1: Dimension | H1: SDType | I1: InCLDBoundary | J1: ExclusionRationale | K1: CLDVariableName | L1: Name_v1 (paper 1) | M1: Name_v2 (paper 2) | N1: Status | O1: Version | P1: Notes
A2: GEN-001 | B2: remaining addressable actor pool | C2: Number of actors who could take a stakeholder role but have not yet engaged | D2: Actors (Who) | F2: actors | G2: Econ+Soc | H2: Stock | I2: Y | K2: remaining addressable actor pool | N2: draft | O2: 0.1
A3: GEN-002 | B3: need satisfaction increase | C3: Degree to which the fundamental needs of engaged stakeholders are met | D3: Needs (Who) | F3: dmnl (0-1) | G3: Soc | H3: Auxiliary | I3: Y | K3: need satisfaction level | N3: draft | O3: 0.1
A4: GEN-003 | B4: engaged stakeholder base | C4: Number of actors currently holding an active stakeholder role | D4: Stakeholders (Who) | F4: actors | G4: Econ+Soc | H4: Stock | I4: Y | K4: engaged stakeholder base | N4: draft | O4: 0.1
A5: GEN-004 | B5: relationship strength and trust | C5: Accumulated quality of the firm-stakeholder connection | D5: Relationships (People) | F5: dmnl (0-1) | G5: Soc | H5: Stock | I5: Y | K5: relationship strength and trust | N5: draft | O5: 0.1
A6: GEN-005 | B6: engagement rate | C6: Rate at which new actors become engaged stakeholders via channels | D6: Channels (People) | F6: actors/year | G6: Econ+Soc | H6: Flow | I6: Y | K6: engagement rate | N6: draft | O6: 0.1
A7: GEN-006 | B7: value co-creation rate | C7: Rate at which positive value is created with and for stakeholders | D7: Value Co-Creations (Value) | F7: value/year | G7: Econ+Soc+Eco | H7: Flow | I7: Y | K7: value co-creation rate | N7: draft | O7: 0.1
A8: GEN-007 | B8: value co-destruction rate | C8: Rate at which harm / negative value is generated for stakeholders | D8: Value Co-Destructions (Value) | F8: value/year | G8: Econ+Soc+Eco | H8: Flow | I8: Y | K8: value co-destruction rate | N8: draft | O8: 0.1
A9: GEN-008 | B9: offering delivery quality | C9: Quality and availability of the products/services carrying the value propositions | D9: Products/Services (Value) | F9: dmnl (0-1) | G9: Econ | H9: Auxiliary | I9: Y | K9: offering delivery quality | N9: draft | O9: 0.1
A10: GEN-009 | B10: activity throughput | C10: Volume of value-creating processes performed per unit time | D10: Activities (Process) | F10: units/year | G10: Econ | H10: Flow | I10: Y | K10: activity throughput | N10: draft | O10: 0.1
A11: GEN-010 | B11: resource and capability stock | C11: Accumulated resources, capabilities and capital available to activities | D11: Resources (Process) | F11: resource units | G11: Econ | H11: Stock | I11: Y | K11: resource and capability stock | N11: draft | O11: 0.1
A12: GEN-011 | B12: activity capacity | C12: Maximum activity throughput the current resource stock supports | D12: Resources (Process) | F12: units/year | G12: Econ | H12: Auxiliary | I12: Y | K12: activity capacity | N12: draft | O12: 0.1
A13: GEN-012 | B13: partnership strength | C13: Strength and coverage of formal agreements with partner organizations | D13: Partnerships (Process) | F13: dmnl (0-1) | G13: Econ+Soc | H13: Auxiliary | I13: Y | K13: partnership strength | N13: draft | O13: 0.1
... A22: GEN-021 | B22: societal legitimacy | C22: Legitimacy and licence to operate granted by society | D22: Context: Society | F22: dmnl (0-1) | G22: Soc | H22: Auxiliary | I22: Y | K22: societal legitimacy | N22: draft | O22: 0.1
A23: PV-001 | B23: remaining addressable household market | C23: Households, tenants and building owners in the target region who could lease a PV system but have not yet | D23: Actors (Who) | E23: EU households / building owners (potential lessees) | F23: households | G23: Econ+Soc | H23: Stock | I23: Y | K23: remaining addressable household market | L23: market potential | M23: remaining total addressable market | N23: draft | O23: 0.2 | P23: instantiates GEN-001; circular PV leasing model
A24: PV-002 | B24: customer satisfaction | C24: Degree to which lessees' needs for affordable, reliable clean energy are met | D24: Needs (Who) | E24: Lessees' need for affordable reliable clean energy | F24: dmnl (0-1) | G24: Soc | H24: Auxiliary | I24: Y | K24: customer satisfaction | L24: customer satisfaction | M24: customer satisfaction | N24: draft | O24: 0.2 | P24: instantiates GEN-002; circular PV leasing model
A25: PV-003 | B25: active lease customer base | C25: Number of households/organizations currently holding an active PV lease contract | D25: Stakeholders (Who) | E25: Lease customers (households, building owners) | F25: households | G25: Econ+Soc | H25: Stock | I25: Y | K25: active lease customer base | L25: active customer base | M25: leased PV-System customers | N25: draft | O25: 0.2 | P25: instantiates GEN-003; circular PV leasing model
A26: PV-004 | B26: customer trust | C26: Accumulated quality of the SustainaSun-lessee relationship | D26: Relationships (People) | E26: SustainaSun - lessee relationship | F26: dmnl (0-1) | G26: Soc | H26: Stock | I26: Y | K26: customer trust | L26: trust and reputation | M26: reputational gain and trust | N26: draft | O26: 0.2 | P26: instantiates GEN-004; circular PV leasing model
A27: PV-005 | B27: customer acquisition rate | C27: Rate at which new customers sign PV lease contracts via referrals, channels and campaigns | D27: Channels (People) | E27: Referral / sales channels | F27: households/year | G27: Econ+Soc | H27: Flow | I27: Y | K27: customer acquisition rate | L27: new customer acquisition | M27: leads and customer acquisition | N27: draft | O27: 0.2 | P27: instantiates GEN-005; circular PV leasing model
A28: PV-006 | B28: energy service delivery rate | C28: Rate at which clean-energy service value is delivered to lessees and community | D28: Value Co-Creations (Value) | E28: Leased clean-energy service | F28: MWh/year | G28: Econ+Soc+Eco | H28: Flow | I28: Y | K28: energy service delivery rate | N28: draft | O28: 0.2 | P28: instantiates GEN-006; circular PV leasing model
A29: PV-007 | B29: end-of-life waste generation rate | C29: Rate at which unmanaged PV end-of-life waste and related harms are generated | D29: Value Co-Destructions (Value) | E29: Unmanaged PV waste stream | F29: t/year | G29: Econ+Soc+Eco | H29: Flow | I29: Y | K29: end-of-life waste generation rate | L29: waste generation | M29: waste from non-circular PV materials | N29: draft | O29: 0.2 | P29: instantiates GEN-007; circular PV leasing model
A30: PV-008 | B30: service quality | C30: Quality and speed of installation, repair and upgrade services carrying the lease offer | D30: Products/Services (Value) | E30: PV leasing service (install, repair, upgrade) | F30: dmnl (0-1) | G30: Econ | H30: Auxiliary | I30: Y | K30: service quality | L30: service quality | M30: fast repair and good service | N30: draft | O30: 0.2 | P30: instantiates GEN-008; circular PV leasing model
A31: PV-009 | B31: lease operations throughput | C31: Installations, repairs and upgrades completed per unit time | D31: Activities (Process) | E31: Install / maintain / upgrade operations | F31: systems/year | G31: Econ | H31: Flow | I31: Y | K31: lease operations throughput | L31: installation growth; service completion | M31: new PV system leases installed per year; completed mounting, repair and upgrade services | N31: draft | O31: 0.2 | P31: instantiates GEN-009; circular PV leasing model
A32: PV-010 | B32: operational resource base | C32: Accumulated capital, crews, equipment and reserves available to lease operations | D32: Resources (Process) | E32: Capital + crews + equipment | F32: resource units | G32: Econ | H32: Stock | I32: Y | K32: operational resource base | L32: financial reserves | N32: draft | O32: 0.2 | P32: instantiates GEN-010; circular PV leasing model
A33: PV-011 | B33: operations capacity | C33: Maximum installations/repairs per year the current resource base supports | D33: Resources (Process) | E33: Installation & maintenance capacity | F33: systems/year | G33: Econ | H33: Auxiliary | I33: Y | K33: operations capacity | L33: installation capacity; service capacity | M33: planning and mounting capacity | N33: draft | O33: 0.2 | P33: instantiates GEN-011; circular PV leasing model
A34: PV-012 | B34: financier confidence | C34: Confidence of financing partners in the leasing model's returns | D34: Partnerships (Process) | E34: Financiers / green lenders partnership | F34: dmnl (0-1) | G34: Econ+Soc | H34: Auxiliary | I34: Y | K34: financier confidence | L34: investor confidence | M34: financier confidence and ROI confidence | N34: draft | O34: 0.2 | P34: instantiates GEN-012; circular PV leasing model
A35: PV-013 | B35: corrective management response | C35: Intensity of corrective decisions on lease pricing and capacity allocation | D35: Governance (Process) | E35: SustainaSun governance (pricing, capacity allocation) | F35: dmnl (0-1) | G35: Econ+Soc+Eco | H35: Auxiliary | I35: Y | K35: corrective management response | N35: draft | O35: 0.2 | P35: instantiates GEN-013; circular PV leasing model
A36: PV-014 | B36: circular material bank | C36: Stock of recoverable PV materials (modules, components) under SustainaSun stewardship | D36: Biophysical Stocks (Environment) | E36: PV material stock (Si, glass, Al, Ag, components) | F36: t | G36: Eco | H36: Stock | I36: Y | K36: circular material bank | L36: recovered component stock | M36: material resource bank | N36: draft | O36: 0.2 | P36: instantiates GEN-014; circular PV leasing model
A37: PV-015 | B37: virgin material consumption rate | C37: Rate at which new PV deployments draw virgin materials and impose supply-chain impacts | D37: Biophysical Stocks (Environment) | E37: Virgin material draw of new PV systems | F37: t/year | G37: Eco | H37: Flow | I37: Y | K37: virgin material consumption rate | N37: draft | O37: 0.2 | P37: instantiates GEN-015; circular PV leasing model
A38: PV-016 | B38: material recovery rate | C38: Rate at which end-of-lease take-back and reverse logistics return materials to the bank | D38: Biophysical Stocks (Environment) | E38: Take-back & recycling operations | F38: t/year | G38: Eco | H38: Flow | I38: Y | K38: material recovery rate | L38: component recovery | M38: recovered materials through reverse logistics | N38: draft | O38: 0.2 | P38: instantiates GEN-016; circular PV leasing model
A39: PV-017 | B39: reverse logistics capability | C39: Capability of the take-back/recycling network the circular model depends on | D39: Ecosystem Services (Environment) | E39: Reverse logistics / recycler network | F39: service units | G39: Eco | H39: Auxiliary | I39: Y | K39: reverse logistics capability | L39: reverse logistics capability | M39: reverse logistics capability for material take-back | N39: draft | O39: 0.2 | P39: instantiates GEN-017; circular PV leasing model; G5 note: structural analog of ecosystem-service capacity in the leasing model; review anchoring
A40: PV-018 | B40: incurred lifecycle costs | C40: Negative outcomes incurred per dimension: operating/maintenance cost, waste externalities | D40: Costs (Outcomes) | E40: Cost structure (O&M, financing, EOL) | F40: EUR + soc/eco units | G40: Econ+Soc+Eco | H40: Auxiliary | I40: Y | K40: incurred lifecycle costs | L40: maintenance cost pressure; operating cash pressure | M40: operating cost pressure; repair and service cost pressure | N40: draft | O40: 0.2 | P40: instantiates GEN-018; circular PV leasing model
A41: PV-019 | B41: realized tri-profit benefits | C41: Positive outcomes realized per dimension: lease margin, energy access, avoided emissions | D41: Benefits (Outcomes) | E41: Benefit streams (lease margin, energy access, avoided CO2) | F41: EUR + soc/eco units | G41: Econ+Soc+Eco | H41: Stock | I41: Y | K41: realized tri-profit benefits | L41: cumulative environmental benefit | M41: financial predictability and net financial benefit | N41: draft | O41: 0.2 | P41: instantiates GEN-019; circular PV leasing model
A42: PV-020 | B42: viability goal gap | C42: Gap between agreed viability targets (affordability, IRR, circularity) and actual outcomes | D42: Goals (Outcomes) | E42: SustainaSun goals (affordability, IRR >= 8%, >=95% recovery) | F42: dmnl (0-1) | G42: Econ+Soc+Eco | H42: Output | I42: Y | K42: viability goal gap | N42: draft | O42: 0.2 | P42: instantiates GEN-020; circular PV leasing model
A43: PV-021 | B43: environmental reputation | C43: Legitimacy and licence to operate granted by society for circular performance | D43: Context: Society | E43: Public/regulator perception of SustainaSun | F43: dmnl (0-1) | G43: Soc | H43: Auxiliary | I43: Y | K43: environmental reputation | L43: environmental reputation | M43: circular economy and environmental reputation | N43: draft | O43: 0.2 | P43: instantiates GEN-021; circular PV leasing model

Sheet CausalLinks
A1: LinkID | B1: FromID | C1: ToID | D1: FromName (auto) | E1: ToName (auto) | F1: Polarity | G1: Delay | H1: Rationale | I1: Status
A2: L01 | B2: GEN-005 | C2: GEN-003 | D2: =IFERROR(VLOOKUP(B2,Concepts!$A:$B,2,FALSE()),"") | E2: =IFERROR(VLOOKUP(C2,Concepts!$A:$B,2,FALSE()),"") | F2: + | G2: N | H2: More engagement grows the stakeholder base | I2: draft
A3: L02 | B3: GEN-003 | C3: GEN-001 | D3: =IFERROR(VLOOKUP(B3,Concepts!$A:$B,2,FALSE()),"") | E3: =IFERROR(VLOOKUP(C3,Concepts!$A:$B,2,FALSE()),"") | F3: - | G3: N | H3: Engaged actors leave the addressable pool | I3: draft
A4: L03 | B4: GEN-001 | C4: GEN-005 | D4: =IFERROR(VLOOKUP(B4,Concepts!$A:$B,2,FALSE()),"") | E4: =IFERROR(VLOOKUP(C4,Concepts!$A:$B,2,FALSE()),"") | F4: + | G4: N | H4: A larger pool enables more engagement | I4: draft
A5: L04 | B5: GEN-004 | C5: GEN-005 | D5: =IFERROR(VLOOKUP(B5,Concepts!$A:$B,2,FALSE()),"") | E5: =IFERROR(VLOOKUP(C5,Concepts!$A:$B,2,FALSE()),"") | F5: + | G5: N | H5: Stronger relationships attract engagement | I5: draft
A6: L05 | B6: GEN-002 | C6: GEN-004 | D6: =IFERROR(VLOOKUP(B6,Concepts!$A:$B,2,FALSE()),"") | E6: =IFERROR(VLOOKUP(C6,Concepts!$A:$B,2,FALSE()),"") | F6: + | G6: Y | H6: Satisfied needs build trust over time | I6: draft
A7: L06 | B7: GEN-006 | C7: GEN-002 | D7: =IFERROR(VLOOKUP(B7,Concepts!$A:$B,2,FALSE()),"") | E7: =IFERROR(VLOOKUP(C7,Concepts!$A:$B,2,FALSE()),"") | F7: + | G7: N | H7: Co-created value satisfies needs | I7: draft
A8: L07 | B8: GEN-007 | C8: GEN-002 | D8: =IFERROR(VLOOKUP(B8,Concepts!$A:$B,2,FALSE()),"") | E8: =IFERROR(VLOOKUP(C8,Concepts!$A:$B,2,FALSE()),"") | F8: - | G8: N | H8: Co-destroyed value impedes needs | I8: draft
A9: L08 | B9: GEN-008 | C9: GEN-002 | D9: =IFERROR(VLOOKUP(B9,Concepts!$A:$B,2,FALSE()),"") | E9: =IFERROR(VLOOKUP(C9,Concepts!$A:$B,2,FALSE()),"") | F9: + | G9: N | H9: Better delivery quality raises satisfaction | I9: draft
A10: L09 | B10: GEN-003 | C10: GEN-009 | D10: =IFERROR(VLOOKUP(B10,Concepts!$A:$B,2,FALSE()),"") | E10: =IFERROR(VLOOKUP(C10,Concepts!$A:$B,2,FALSE()),"") | F10: + | G10: N | H10: More stakeholders demand more activity | I10: draft
A11: L10 | B11: GEN-009 | C11: GEN-006 | D11: =IFERROR(VLOOKUP(B11,Concepts!$A:$B,2,FALSE()),"") | E11: =IFERROR(VLOOKUP(C11,Concepts!$A:$B,2,FALSE()),"") | F11: + | G11: N | H11: Activities create value | I11: draft
A12: L11 | B12: GEN-009 | C12: GEN-007 | D12: =IFERROR(VLOOKUP(B12,Concepts!$A:$B,2,FALSE()),"") | E12: =IFERROR(VLOOKUP(C12,Concepts!$A:$B,2,FALSE()),"") | F12: + | G12: N | H12: Activities also generate unintended harm | I12: draft
A13: L12 | B13: GEN-009 | C13: GEN-008 | D13: =IFERROR(VLOOKUP(B13,Concepts!$A:$B,2,FALSE()),"") | E13: =IFERROR(VLOOKUP(C13,Concepts!$A:$B,2,FALSE()),"") | F13: - | G13: N | H13: Load beyond capacity erodes quality | I13: draft
... A35: L34 | B35: GEN-021 | C35: GEN-005 | D35: =IFERROR(VLOOKUP(B35,Concepts!$A:$B,2,FALSE()),"") | E35: =IFERROR(VLOOKUP(C35,Concepts!$A:$B,2,FALSE()),"") | F35: + | G35: N | H35: Legitimacy attracts engagement | I35: draft

Sheet Loops
A1: LoopID | B1: LoopName | C1: Ordered LinkIDs | D1: NegLinkCount (manual) | E1: DerivedType (formula) | F1: Archetype | G1: Narrative
A2: R1 | B2: Value engagement engine | C2: L09,L10,L06,L05,L04,L01 | D2: 0 | E2: =IF(ISODD(D2),"B","R") | F2: Growth engine | G2: Base drives activity, value co-creation, satisfaction, trust and new engagement.
A3: B1 | B3: Actor pool saturation | C3: L02,L03,L01 | D3: 1 | E3: =IF(ISODD(D3),"B","R") | F3: Limits to growth (market) | G3: Engagement depletes the remaining addressable pool.
A4: R2 | B4: Capability reinvestment | C4: L15,L14,L13,L08,L05,L04,L01 | D4: 0 | E4: =IF(ISODD(D4),"B","R") | F4: Investment engine | G4: Exchanges replenish resources, capacity and quality, feeding satisfaction.
A5: B2 | B5: Service overload | C5: L09,L12,L08,L05,L04,L01 | D5: 1 | E5: =IF(ISODD(D5),"B","R") | F5: Growth & underinvestment (with R2) | G5: Throughput beyond capacity erodes quality and slows growth.
A6: B3 | B6: Co-destruction drag | C6: L09,L11,L07,L05,L04,L01 | D6: 1 | E6: =IF(ISODD(D6),"B","R") | F6: Externality backlash | G6: Activity side-effects impede needs and suppress engagement.
A7: B4 | B7: Ecological source limit | C7: L18,L19,L20,L21,L13,L08,L05,L04,L01,L09 | D7: 1 | E7: =IF(ISODD(D7),"B","R") | F7: Limits to growth (biophysical) | G7: Extraction depletes the stocks whose services enable capacity.
A8: R3 | B8: Regenerative reinvestment | C8: L23,L22,L20,L21,L13,L08,L05,L04,L01,L15 | D8: 0 | E8: =IF(ISODD(D8),"B","R") | F8: Regeneration engine | G8: Resources fund regeneration, rebuilding services and capacity.
A9: B5 | B9: Governance goal-seeking | C9: L28,L30,L31,L13,L08,L05,L04,L01,L09,L10,L25 | D9: 1 | E9: =IF(ISODD(D9),"B","R") | F9: Goal-seeking control | G9: The goal gap triggers governance that restores benefits.
A10: R4 | B10: Legitimacy engine | C10: L32,L34,L01,L09,L10,L25 | D10: 0 | E10: =IF(ISODD(D10),"B","R") | F10: Reputation engine | G10: Benefits earn legitimacy which attracts engagement.
B12: NegLinkCount = number of '-' polarities among the listed LinkIDs (count them in CausalLinks). DerivedType then computes R/B — never type R/B directly (invariant I3).

Sheet ChangeLog
A1: Date | B1: RegistryVersion | C1: ChangeType | D1: ConceptIDs / LinkIDs / LoopIDs | E1: Description & rationale | F1: Author | G1: AffectedArtifacts
A2: 2026-07-02 | B2: 0.1 | C2: add | D2: GEN-001..GEN-021, L01..L34, R1..R4, B1..B5 | E2: Initial generic registry created from the FBMC-CLD alignment ontology (complete-canvas template, no use case) | F2: Hamza / Claude | G2: drawio p.4, Word doc §7-8
A3: 2026-07-02 | B3: 0.1 | C3: add | D3: (Lists) | E3: Added ChangeType 'gate-approval' so human gate sign-offs are recorded distinctly from content changes (verifier finding #2) | F3: Claude (approved workflow, P1 session) | G3: registry Lists sheet
A4: 2026-07-02 | B4: 0.2 | C4: add | D4: PV-001..PV-021 | E4: P2 instantiation: 21 PV- rows for the SustainaSun CIRCULAR PV LEASING model (scope decision by Hamza at gate, 2026-07-02). Canonical names reconciled from v1 paper and v2 CLD (legacy names in Name_v1/Name_v2); structure remains defined over GEN links (instance rows are naming projections, marker: instantiates GEN-xxx). | F4: Hamza / Claude | G4: Concepts sheet; future CLD v3
A5: 2026-07-02 | B5: 0.2 | C5: gate-approval | D5: PV-001..PV-021 | E5: Gate: P2 scope question answered - circular PV leasing canvas selected over utility PPA. G5 expert review of names/definitions still pending. | F5: Hamza | G5: registry v0.2
