Workbook

Sheet README
B2: SustainaSun — Regenerative PV Business Model
B3: Parametric Financial Model — Reference Architecture v0.1
B5: Question this model answers
B6: Can a regenerative PV business model be profitable — and under what conditions?
B8: Verdict (Regenerative scenario, base-case assumptions)
B9: Regenerative equity IRR (target ≥ 8%) | C9: =KPIs!D5 -> 0.096126531
B10: Regenerative NPV at 5% discount (€) | C10: =KPIs!D8 -> 445545.77
B11: Verdict | C11: =IF(KPIs!D5>=0.08,"PROFITABLE","BELOW TARGET") -> PROFITABLE
B13: How to use this model
B14: 1. Open the Assumptions sheet. Every blue cell is editable. Change any value to test a different assumption.
B15: 2. Three scenario columns are pre-loaded: Conventional (baseline), Regenerative (today), Future (2030 outlook).
B16: 3. Cashflow sheets (CF_Conv, CF_Regen, CF_Future) compute a full 30-year project finance cashflow from those assumptions.
B17: 4. The KPIs sheet shows side-by-side outputs: equity IRR, project IRR, NPV at 5%/8%/10%, LCOE, LVOE, payback, DSCR.
B18: 5. The Sensitivity sheet shows how the Regenerative case equity IRR responds to ±20% perturbations of each key driver.
B19: 6. When you change an assumption, all dependent values recalculate automatically.
B22: Sheet structure
B23: README | C23: This sheet — purpose, verdict, instructions, colour legend.
B24: Assumptions | C24: All inputs. Blue = editable hardcoded value. Three scenario columns + notes.
B25: CF_Conv | C25: 30-year cashflow for the Conventional baseline scenario (energy only, no regenerative streams).
B26: CF_Regen | C26: 30-year cashflow for the Regenerative scenario — agrivoltaic + low-carbon premium + community equity tranche.
B27: CF_Future | C27: 30-year cashflow for the Future scenario — adds biodiversity credits and DPP licensing at 2030 prices.
B28: KPIs | C28: Side-by-side outputs for all three scenarios. The verdict on this sheet.
B29: Sensitivity | C29: One-way sensitivity on Regenerative equity IRR. Identifies the most impactful variables.
B31: Colour legend
B32: Blue text | C32: Hardcoded input value — editable by user
B33: Black text | C33: Formula or computed value — do not overwrite
B34: Green text | C34: Cross-sheet link — points to another sheet
B35: Yellow background | C35: Key assumption needing attention or stress-testing
B38: License & Project
B39: MIT License. Part of SustainableTogether (INCOSE Sustainability Working Group).
B40: Repository: https://github.com/TheNightFox-1/SustainableTogether

Sheet Assumptions
A1: Assumptions — all editable inputs (blue cells)
A3: Parameter | B3: Unit | C3: Conventional | D3: Regenerative | E3: Future | F3: Notes / Source
A4: PROJECT PARAMETERS
A5: Installed capacity | B5: kWp | C5: 5000 | D5: 5000 | E5: 5000 | F5: Reference utility/community-scale project. Change to scale model.
A6: Specific yield (Year 1) | B6: kWh/kWp/yr | C6: 1226 | D6: 1180 | E6: 1180 | F6: EU mid-latitude. Agrivoltaic mounting -3-5% vs. conventional. Source: Fraunhofer ISE.
A7: Module degradation | B7: %/yr | C7: 0.005 | D7: 0.005 | E7: 0.005 | F7: TOPCon/HJT performance warranty. Source: IEA-PVPS Task 13.
A8: Project life | B8: years | C8: 30 | D8: 30 | E8: 30 | F8: Design life of c-Si modules.
A9: Land area | B9: ha | C9: 7 | D9: 8 | E9: 8 | F9: Agrivoltaic projects use ~10-20% more land (lower density).
A11: CAPEX (€/Wp)
A12: Modules | B12: €/Wp | C12: 0.1 | D12: 0.12 | E12: 0.12 | F12: Low-carbon traceable modules +20-30% over spot. Source: Aiko / Meyer Burger 2025 indicative.
A13: Inverters + BoS | B13: €/Wp | C13: 0.09 | D13: 0.09 | E13: 0.09 | F13: EU 2026 market.
A14: Mounting (disassemblable for regen) | B14: €/Wp | C14: 0.07 | D14: 0.08 | E14: 0.08 | F14: +10-20% for bolted/demountable design.
A15: Civil + EPC | B15: €/Wp | C15: 0.18 | D15: 0.2 | E15: 0.2 | F15: Low-disturbance protocol for regen.
A16: Grid connection | B16: €/Wp | C16: 0.07 | D16: 0.07 | E16: 0.07 | F16: Site-dependent; assumed equal across scenarios.
A17: Development + permitting | B17: €/Wp | C17: 0.04 | D17: 0.06 | E17: 0.06 | F17: Regen includes community engagement upfront (€50-100k fixed).
A18: Contingency | B18: % of CAPEX | C18: 0.03 | D18: 0.04 | E18: 0.04 | F18: Higher for regen due to first-of-kind elements.
A20: REVENUE — ENERGY
A21: PPA price Year 1 | B21: €/MWh | C21: 67 | D21: 64 | E21: 66 | F21: EU corporate PPA Q1 2026 range €55-70. Source: Pexapark, LevelTen.
A22: PPA escalator | B22: %/yr | C22: 0.02 | D22: 0.02 | E22: 0.02 | F22: Inflation-indexed structure.
A23: PPA tenor | B23: years | C23: 15 | D23: 20 | E23: 22 | F23: Longer tenor for regen-positioned offtake.
A24: Merchant tail price (real) | B24: €/MWh | C24: 50 | D24: 50 | E24: 55 | F24: Years after PPA tenor. High uncertainty.
A26: REVENUE — REGENERATIVE PREMIUMS
A27: Low-carbon attribute premium | B27: €/MWh | C27: 0 | D27: 3 | E27: 4 | F27: Verified low-gCO2/kWh module sourcing. FR CRE + voluntary corporate PPAs.
A28: Agrivoltaic premium / co-revenue | B28: €/MWh | C28: 0 | D28: 1.5 | E28: 2 | F28: FR agrivoltaic decree; DE EEG §37; IT DM. None for conv.
A29: Biodiversity credit revenue | B29: €/MWh | C29: 0 | D29: 0 | E29: 0.8 | F29: Not bankable in EU today; modelled in Future only.
A30: DPP / data licensing | B30: €/MWh | C30: 0 | D30: 0 | E30: 0.5 | F30: Forward-looking, post-ESPR PV scope.
A31: Community grant revenue | B31: €/yr | C31: 0 | D31: 8000 | E31: 12000 | F31: Energy-poverty/social-tariff programmes. Programme-dependent.
A33: REVENUE — END OF LIFE (YEAR 30)
A34: Material recovery gross revenue | B34: €/kWp | C34: 0 | D34: 12 | E34: 20 | F34: Glass + Al + Si + Ag. Source: IRENA EOL 2022. Future: improved recovery.
A35: Decommissioning cost | B35: €/kWp | C35: 15 | D35: 18 | E35: 18 | F35: Higher for regen due to careful disassembly; offset by recovery rev.
A37: OPERATING COSTS
A38: O&M | B38: €/kWp/yr | C38: 11 | D38: 13 | E38: 13 | F38: Regen includes ecological monitoring partnership.
A39: O&M escalation | B39: %/yr | C39: 0.02 | D39: 0.02 | E39: 0.02 | F39: Inflation-indexed.
A40: Land lease (net of agri uplift) | B40: €/ha/yr | C40: 2500 | D40: 1800 | E40: 1500 | F40: Regen: farmer accepts lower lease in exchange for soil stewardship.
A41: Insurance | B41: % of CAPEX/yr | C41: 0.005 | D41: 0.005 | E41: 0.005 | F41: Industry standard.
A42: CSRD + DPP compliance (SPV allocation) | B42: €/yr | C42: 5000 | D42: 8000 | E42: 8000 | F42: SPV-level allocation of parent-company CSRD effort. Reduce per project as portfolio scales.
A43: Community governance | B43: €/yr | C43: 0 | D43: 6000 | E43: 6000 | F43: Cooperative secretariat, AGM, reporting to members.
A44: EOL reserve contribution | B44: €/MWh | C44: 0 | D44: 2 | E44: 2 | F44: Ring-fenced fund for Year 30 decommissioning + recycling.
A46: CAPITAL STRUCTURE
A47: Senior debt share | B47: % of CAPEX | C47: 0.6 | D47: 0.6 | E47: 0.65 | F47: Project finance norm. Regen lower due to community tranche.
A48: Cost of senior debt | B48: % nominal | C48: 0.055 | D48: 0.045 | E48: 0.045 | F48: Green bond aligned for regen. Source: EIB / commercial spreads 2026.
A49: Debt tenor | B49: years | C49: 18 | D49: 20 | E49: 22 | F49: Sculpted to DSCR; longer for green-aligned.
A50: Community equity share | B50: % of CAPEX | C50: 0 | D50: 0.15 | E50: 0.2 | F50: Cooperative tranche. 0 for conv.
A51: Cost of community equity | B51: % return expected | C51: 0 | D51: 0.06 | E51: 0.06 | F51: Below commercial; cooperative-member return.
A52: Commercial equity share | B52: % of CAPEX | C52: 0.4 | D52: 0.25 | E52: 0.15 | F52: Residual. Conv: 40%. Regen: 25%. Future: 15%.
A53: Cost of commercial equity (hurdle) | B53: % return target | C53: 0.1 | D53: 0.1 | E53: 0.1 | F53: Sponsor IRR target.
A54: Depreciation life | B54: years | C54: 25 | D54: 25 | E54: 25 | F54: Straight-line, fiscal.
A55: Corporate tax rate | B55: % | C55: 0.25 | D55: 0.25 | E55: 0.25 | F55: EU average. Adjust for jurisdiction.
A57: DISCOUNT RATES (FOR NPV / LCOE)
A58: Discount rate — low | B58: % | C58: 0.05 | D58: 0.05 | E58: 0.05 | F58: Sovereign / EU taxonomy reference.
A59: Discount rate — base | B59: % | C59: 0.08 | D59: 0.08 | E59: 0.08 | F59: Conventional project IRR target.
A60: Discount rate — high | B60: % | C60: 0.1 | D60: 0.1 | E60: 0.1 | F60: Stress / sponsor view.
A62: CALCULATED TOTALS (formula)
A63: Total CAPEX (€/Wp) | C63: =(C12+C13+C14+C15+C16+C17)*(1+C18) -> 0.5665 | D63: =(D12+D13+D14+D15+D16+D17)*(1+D18) -> 0.6448 | E63: =(E12+E13+E14+E15+E16+E17)*(1+E18) -> 0.6448
A64: Total CAPEX (€) | C64: =C63*1000*C5 -> 2832500 | D64: =D63*1000*D5 -> 3224000 | E64: =E63*1000*E5 -> 3224000
A65: Year 1 generation (MWh) | C65: =C5*C6/1000 -> 6130 | D65: =D5*D6/1000 -> 5900 | E65: =E5*E6/1000 -> 5900
A66: Senior debt drawn (€) | C66: =C47*C64 -> 1699500 | D66: =D47*D64 -> 1934400 | E66: =E47*E64 -> 2095600
A67: Community equity (€) | C67: =C50*C64 -> 0 | D67: =D50*D64 -> 483600 | E67: =E50*E64 -> 644800
A68: Commercial equity (€) | C68: =C52*C64 -> 1133000 | D68: =D52*D64 -> 806000 | E68: =E52*E64 -> 483600
A69: Blended WACC (informational) | C69: =C47*C48*(1-C55)+C50*C51+C52*C53 -> 0.06475 | D69: =D47*D48*(1-D55)+D50*D51+D52*D53 -> 0.05425 | E69: =E47*E48*(1-E55)+E50*E51+E52*E53 -> 0.0489375

Sheet CF_Conv
A1: Cashflow — Conventional scenario
A2: All values link to Assumptions sheet column C. Edit Assumptions to change scenario.
A4: Line item | B4: Unit | C4: Y0 | D4: Y1 | E4: Y2 | F4: Y3 | G4: Y4 | H4: Y5 | I4: Y6 | J4: Y7 | K4: Y8 | L4: Y9 | M4: Y10 | N4: Y11 | O4: Y12 | P4: Y13 | Q4: Y14 | R4: Y15 | S4: Y16 | T4: Y17 | U4: Y18 | V4: Y19 | W4: Y20 | X4: Y21 | Y4: Y22 | Z4: Y23 | AA4: Y24 | AB4: Y25 | AC4: Y26 | AD4: Y27 | AE4: Y28 | AF4: Y29 | AG4: Y30
A5: GENERATION
A6: Generation | B6: MWh | C6: =0 -> 0 | D6: =Assumptions!$C$65*(1-Assumptions!$C$7)^(1-1) -> 6130 | E6: =Assumptions!$C$65*(1-Assumptions!$C$7)^(2-1) -> 6099.35 | F6: =Assumptions!$C$65*(1-Assumptions!$C$7)^(3-1) -> 6068.8533 | G6: =Assumptions!$C$65*(1-Assumptions!$C$7)^(4-1) -> 6038.509 | H6: =Assumptions!$C$65*(1-Assumptions!$C$7)^(5-1) -> 6008.3164 | I6: =Assumptions!$C$65*(1-Assumptions!$C$7)^(6-1) -> 5978.2749 | J6: =Assumptions!$C$65*(1-Assumptions!$C$7)^(7-1) -> 5948.3835 | K6: =Assumptions!$C$65*(1-Assumptions!$C$7)^(8-1) -> 5918.6416 | L6: =Assumptions!$C$65*(1-Assumptions!$C$7)^(9-1) -> 5889.0484 | M6: =Assumptions!$C$65*(1-Assumptions!$C$7)^(10-1) -> 5859.6031 | N6: =Assumptions!$C$65*(1-Assumptions!$C$7)^(11-1) -> 5830.3051 | O6: =Assumptions!$C$65*(1-Assumptions!$C$7)^(12-1) -> 5801.1536 | P6: =Assumptions!$C$65*(1-Assumptions!$C$7)^(13-1) -> 5772.1478 | Q6: =Assumptions!$C$65*(1-Assumptions!$C$7)^(14-1) -> 5743.2871 | R6: =Assumptions!$C$65*(1-Assumptions!$C$7)^(15-1) -> 5714.5706 | S6: =Assumptions!$C$65*(1-Assumptions!$C$7)^(16-1) -> 5685.9978 | T6: =Assumptions!$C$65*(1-Assumptions!$C$7)^(17-1) -> 5657.5678 | U6: =Assumptions!$C$65*(1-Assumptions!$C$7)^(18-1) -> 5629.28 | V6: =Assumptions!$C$65*(1-Assumptions!$C$7)^(19-1) -> 5601.1336 | W6: =Assumptions!$C$65*(1-Assumptions!$C$7)^(20-1) -> 5573.1279 | X6: =Assumptions!$C$65*(1-Assumptions!$C$7)^(21-1) -> 5545.2622 | Y6: =Assumptions!$C$65*(1-Assumptions!$C$7)^(22-1) -> 5517.5359 | Z6: =Assumptions!$C$65*(1-Assumptions!$C$7)^(23-1) -> 5489.9483 | AA6: =Assumptions!$C$65*(1-Assumptions!$C$7)^(24-1) -> 5462.4985 | AB6: =Assumptions!$C$65*(1-Assumptions!$C$7)^(25-1) -> 5435.186 | AC6: =Assumptions!$C$65*(1-Assumptions!$C$7)^(26-1) -> 5408.0101 | AD6: =Assumptions!$C$65*(1-Assumptions!$C$7)^(27-1) -> 5380.97 | AE6: =Assumptions!$C$65*(1-Assumptions!$C$7)^(28-1) -> 5354.0652 | AF6: =Assumptions!$C$65*(1-Assumptions!$C$7)^(29-1) -> 5327.2949 | AG6: =Assumptions!$C$65*(1-Assumptions!$C$7)^(30-1) -> 5300.6584
A8: REVENUE
A9: PPA energy revenue | B9: € | C9: =0 -> 0 | D9: =IF(1<=Assumptions!$C$23,D6*Assumptions!$C$21*(1+Assumptions!$C$22)^(1-1),D6*Assumptions!$C$24) -> 410710 | E9: =IF(2<=Assumptions!$C$23,E6*Assumptions!$C$21*(1+Assumptions!$C$22)^(2-1),E6*Assumptions!$C$24) -> 416829.58 | F9: =IF(3<=Assumptions!$C$23,F6*Assumptions!$C$21*(1+Assumptions!$C$22)^(3-1),F6*Assumptions!$C$24) -> 423040.34 | G9: =IF(4<=Assumptions!$C$23,G6*Assumptions!$C$21*(1+Assumptions!$C$22)^(4-1),G6*Assumptions!$C$24) -> 429343.64 | H9: =IF(5<=Assumptions!$C$23,H6*Assumptions!$C$21*(1+Assumptions!$C$22)^(5-1),H6*Assumptions!$C$24) -> 435740.86 | I9: =IF(6<=Assumptions!$C$23,I6*Assumptions!$C$21*(1+Assumptions!$C$22)^(6-1),I6*Assumptions!$C$24) -> 442233.4 | J9: =IF(7<=Assumptions!$C$23,J6*Assumptions!$C$21*(1+Assumptions!$C$22)^(7-1),J6*Assumptions!$C$24) -> 448822.68 | K9: =IF(8<=Assumptions!$C$23,K6*Assumptions!$C$21*(1+Assumptions!$C$22)^(8-1),K6*Assumptions!$C$24) -> 455510.14 | L9: =IF(9<=Assumptions!$C$23,L6*Assumptions!$C$21*(1+Assumptions!$C$22)^(9-1),L6*Assumptions!$C$24) -> 462297.24 | M9: =IF(10<=Assumptions!$C$23,M6*Assumptions!$C$21*(1+Assumptions!$C$22)^(10-1),M6*Assumptions!$C$24) -> 469185.47 | N9: =IF(11<=Assumptions!$C$23,N6*Assumptions!$C$21*(1+Assumptions!$C$22)^(11-1),N6*Assumptions!$C$24) -> 476176.33 | O9: =IF(12<=Assumptions!$C$23,O6*Assumptions!$C$21*(1+Assumptions!$C$22)^(12-1),O6*Assumptions!$C$24) -> 483271.36 | P9: =IF(13<=Assumptions!$C$23,P6*Assumptions!$C$21*(1+Assumptions!$C$22)^(13-1),P6*Assumptions!$C$24) -> 490472.1 | Q9: =IF(14<=Assumptions!$C$23,Q6*Assumptions!$C$21*(1+Assumptions!$C$22)^(14-1),Q6*Assumptions!$C$24) -> 497780.13 | R9: =IF(15<=Assumptions!$C$23,R6*Assumptions!$C$21*(1+Assumptions!$C$22)^(15-1),R6*Assumptions!$C$24) -> 505197.06 | S9: =IF(16<=Assumptions!$C$23,S6*Assumptions!$C$21*(1+Assumptions!$C$22)^(16-1),S6*Assumptions!$C$24) -> 284299.89 | T9: =IF(17<=Assumptions!$C$23,T6*Assumptions!$C$21*(1+Assumptions!$C$22)^(17-1),T6*Assumptions!$C$24) -> 282878.39 | U9: =IF(18<=Assumptions!$C$23,U6*Assumptions!$C$21*(1+Assumptions!$C$22)^(18-1),U6*Assumptions!$C$24) -> 281464 | V9: =IF(19<=Assumptions!$C$23,V6*Assumptions!$C$21*(1+Assumptions!$C$22)^(19-1),V6*Assumptions!$C$24) -> 280056.68 | W9: =IF(20<=Assumptions!$C$23,W6*Assumptions!$C$21*(1+Assumptions!$C$22)^(20-1),W6*Assumptions!$C$24) -> 278656.39 | X9: =IF(21<=Assumptions!$C$23,X6*Assumptions!$C$21*(1+Assumptions!$C$22)^(21-1),X6*Assumptions!$C$24) -> 277263.11 | Y9: =IF(22<=Assumptions!$C$23,Y6*Assumptions!$C$21*(1+Assumptions!$C$22)^(22-1),Y6*Assumptions!$C$24) -> 275876.8 | Z9: =IF(23<=Assumptions!$C$23,Z6*Assumptions!$C$21*(1+Assumptions!$C$22)^(23-1),Z6*Assumptions!$C$24) -> 274497.41 | AA9: =IF(24<=Assumptions!$C$23,AA6*Assumptions!$C$21*(1+Assumptions!$C$22)^(24-1),AA6*Assumptions!$C$24) -> 273124.93 | AB9: =IF(25<=Assumptions!$C$23,AB6*Assumptions!$C$21*(1+Assumptions!$C$22)^(25-1),AB6*Assumptions!$C$24) -> 271759.3 | AC9: =IF(26<=Assumptions!$C$23,AC6*Assumptions!$C$21*(1+Assumptions!$C$22)^(26-1),AC6*Assumptions!$C$24) -> 270400.5 | AD9: =IF(27<=Assumptions!$C$23,AD6*Assumptions!$C$21*(1+Assumptions!$C$22)^(27-1),AD6*Assumptions!$C$24) -> 269048.5 | AE9: =IF(28<=Assumptions!$C$23,AE6*Assumptions!$C$21*(1+Assumptions!$C$22)^(28-1),AE6*Assumptions!$C$24) -> 267703.26 | AF9: =IF(29<=Assumptions!$C$23,AF6*Assumptions!$C$21*(1+Assumptions!$C$22)^(29-1),AF6*Assumptions!$C$24) -> 266364.74 | AG9: =IF(30<=Assumptions!$C$23,AG6*Assumptions!$C$21*(1+Assumptions!$C$22)^(30-1),AG6*Assumptions!$C$24) -> 265032.92
A10: Low-carbon attribute premium | B10: € | C10: =0 -> 0 | D10: =IF(1<=Assumptions!$C$23,D6*Assumptions!$C$27,0) -> 0 | E10: =IF(2<=Assumptions!$C$23,E6*Assumptions!$C$27,0) -> 0 | F10: =IF(3<=Assumptions!$C$23,F6*Assumptions!$C$27,0) -> 0 | G10: =IF(4<=Assumptions!$C$23,G6*Assumptions!$C$27,0) -> 0 | H10: =IF(5<=Assumptions!$C$23,H6*Assumptions!$C$27,0) -> 0 | I10: =IF(6<=Assumptions!$C$23,I6*Assumptions!$C$27,0) -> 0 | J10: =IF(7<=Assumptions!$C$23,J6*Assumptions!$C$27,0) -> 0 | K10: =IF(8<=Assumptions!$C$23,K6*Assumptions!$C$27,0) -> 0 | L10: =IF(9<=Assumptions!$C$23,L6*Assumptions!$C$27,0) -> 0 | M10: =IF(10<=Assumptions!$C$23,M6*Assumptions!$C$27,0) -> 0 | N10: =IF(11<=Assumptions!$C$23,N6*Assumptions!$C$27,0) -> 0 | O10: =IF(12<=Assumptions!$C$23,O6*Assumptions!$C$27,0) -> 0 | P10: =IF(13<=Assumptions!$C$23,P6*Assumptions!$C$27,0) -> 0 | Q10: =IF(14<=Assumptions!$C$23,Q6*Assumptions!$C$27,0) -> 0 | R10: =IF(15<=Assumptions!$C$23,R6*Assumptions!$C$27,0) -> 0 | S10: =IF(16<=Assumptions!$C$23,S6*Assumptions!$C$27,0) -> 0 | T10: =IF(17<=Assumptions!$C$23,T6*Assumptions!$C$27,0) -> 0 | U10: =IF(18<=Assumptions!$C$23,U6*Assumptions!$C$27,0) -> 0 | V10: =IF(19<=Assumptions!$C$23,V6*Assumptions!$C$27,0) -> 0 | W10: =IF(20<=Assumptions!$C$23,W6*Assumptions!$C$27,0) -> 0 | X10: =IF(21<=Assumptions!$C$23,X6*Assumptions!$C$27,0) -> 0 | Y10: =IF(22<=Assumptions!$C$23,Y6*Assumptions!$C$27,0) -> 0 | Z10: =IF(23<=Assumptions!$C$23,Z6*Assumptions!$C$27,0) -> 0 | AA10: =IF(24<=Assumptions!$C$23,AA6*Assumptions!$C$27,0) -> 0 | AB10: =IF(25<=Assumptions!$C$23,AB6*Assumptions!$C$27,0) -> 0 | AC10: =IF(26<=Assumptions!$C$23,AC6*Assumptions!$C$27,0) -> 0 | AD10: =IF(27<=Assumptions!$C$23,AD6*Assumptions!$C$27,0) -> 0 | AE10: =IF(28<=Assumptions!$C$23,AE6*Assumptions!$C$27,0) -> 0 | AF10: =IF(29<=Assumptions!$C$23,AF6*Assumptions!$C$27,0) -> 0 | AG10: =IF(30<=Assumptions!$C$23,AG6*Assumptions!$C$27,0) -> 0
A11: Agrivoltaic co-revenue / premium | B11: € | C11: =0 -> 0 | D11: =D6*Assumptions!$C$28 -> 0 | E11: =E6*Assumptions!$C$28 -> 0 | F11: =F6*Assumptions!$C$28 -> 0 | G11: =G6*Assumptions!$C$28 -> 0 | H11: =H6*Assumptions!$C$28 -> 0 | I11: =I6*Assumptions!$C$28 -> 0 | J11: =J6*Assumptions!$C$28 -> 0 | K11: =K6*Assumptions!$C$28 -> 0 | ... AG11: =AG6*Assumptions!$C$28 -> 0
A12: Biodiversity credit revenue | B12: € | C12: =0 -> 0 | D12: =D6*Assumptions!$C$29 -> 0 | E12: =E6*Assumptions!$C$29 -> 0 | F12: =F6*Assumptions!$C$29 -> 0 | G12: =G6*Assumptions!$C$29 -> 0 | H12: =H6*Assumptions!$C$29 -> 0 | I12: =I6*Assumptions!$C$29 -> 0 | J12: =J6*Assumptions!$C$29 -> 0 | K12: =K6*Assumptions!$C$29 -> 0 | ... AG12: =AG6*Assumptions!$C$29 -> 0
A13: DPP / data licensing | B13: € | C13: =0 -> 0 | D13: =D6*Assumptions!$C$30 -> 0 | E13: =E6*Assumptions!$C$30 -> 0 | F13: =F6*Assumptions!$C$30 -> 0 | G13: =G6*Assumptions!$C$30 -> 0 | H13: =H6*Assumptions!$C$30 -> 0 | I13: =I6*Assumptions!$C$30 -> 0 | J13: =J6*Assumptions!$C$30 -> 0 | K13: =K6*Assumptions!$C$30 -> 0 | ... AG13: =AG6*Assumptions!$C$30 -> 0
A14: Community / energy-access grant | B14: € | C14: =0 -> 0 | D14: =Assumptions!$C$31 -> 0 | E14: =Assumptions!$C$31 -> 0 | F14: =Assumptions!$C$31 -> 0 | G14: =Assumptions!$C$31 -> 0 | H14: =Assumptions!$C$31 -> 0 | I14: =Assumptions!$C$31 -> 0 | J14: =Assumptions!$C$31 -> 0 | K14: =Assumptions!$C$31 -> 0 | ... AG14: =Assumptions!$C$31 -> 0
A15: EOL material recovery (Year 30) | B15: € | C15: =0 -> 0 | D15: =0 -> 0 | E15: =0 -> 0 | F15: =0 -> 0 | G15: =0 -> 0 | H15: =0 -> 0 | I15: =0 -> 0 | J15: =0 -> 0 | ... AF15: =0 -> 0 | AG15: =Assumptions!$C$34*Assumptions!$C$5 -> 0
A16: Total revenue | B16: € | C16: =SUM(C9:C15) -> 0 | D16: =SUM(D9:D15) -> 410710 | E16: =SUM(E9:E15) -> 416829.58 | F16: =SUM(F9:F15) -> 423040.34 | G16: =SUM(G9:G15) -> 429343.64 | H16: =SUM(H9:H15) -> 435740.86 | I16: =SUM(I9:I15) -> 442233.4 | J16: =SUM(J9:J15) -> 448822.68 | ... AG16: =SUM(AG9:AG15) -> 265032.92
A18: OPERATING COSTS
A19: O&M | B19: € | C19: =0 -> 0 | D19: =-Assumptions!$C$38*Assumptions!$C$5*(1+Assumptions!$C$39)^(1-1) -> -55000 | E19: =-Assumptions!$C$38*Assumptions!$C$5*(1+Assumptions!$C$39)^(2-1) -> -56100 | F19: =-Assumptions!$C$38*Assumptions!$C$5*(1+Assumptions!$C$39)^(3-1) -> -57222 | G19: =-Assumptions!$C$38*Assumptions!$C$5*(1+Assumptions!$C$39)^(4-1) -> -58366.44 | H19: =-Assumptions!$C$38*Assumptions!$C$5*(1+Assumptions!$C$39)^(5-1) -> -59533.769 | I19: =-Assumptions!$C$38*Assumptions!$C$5*(1+Assumptions!$C$39)^(6-1) -> -60724.444 | J19: =-Assumptions!$C$38*Assumptions!$C$5*(1+Assumptions!$C$39)^(7-1) -> -61938.933 | K19: =-Assumptions!$C$38*Assumptions!$C$5*(1+Assumptions!$C$39)^(8-1) -> -63177.712 | L19: =-Assumptions!$C$38*Assumptions!$C$5*(1+Assumptions!$C$39)^(9-1) -> -64441.266 | M19: =-Assumptions!$C$38*Assumptions!$C$5*(1+Assumptions!$C$39)^(10-1) -> -65730.091 | N19: =-Assumptions!$C$38*Assumptions!$C$5*(1+Assumptions!$C$39)^(11-1) -> -67044.693 | O19: =-Assumptions!$C$38*Assumptions!$C$5*(1+Assumptions!$C$39)^(12-1) -> -68385.587 | P19: =-Assumptions!$C$38*Assumptions!$C$5*(1+Assumptions!$C$39)^(13-1) -> -69753.299 | Q19: =-Assumptions!$C$38*Assumptions!$C$5*(1+Assumptions!$C$39)^(14-1) -> -71148.365 | R19: =-Assumptions!$C$38*Assumptions!$C$5*(1+Assumptions!$C$39)^(15-1) -> -72571.332 | S19: =-Assumptions!$C$38*Assumptions!$C$5*(1+Assumptions!$C$39)^(16-1) -> -74022.759 | T19: =-Assumptions!$C$38*Assumptions!$C$5*(1+Assumptions!$C$39)^(17-1) -> -75503.214 | U19: =-Assumptions!$C$38*Assumptions!$C$5*(1+Assumptions!$C$39)^(18-1) -> -77013.278 | V19: =-Assumptions!$C$38*Assumptions!$C$5*(1+Assumptions!$C$39)^(19-1) -> -78553.544 | W19: =-Assumptions!$C$38*Assumptions!$C$5*(1+Assumptions!$C$39)^(20-1) -> -80124.614 | X19: =-Assumptions!$C$38*Assumptions!$C$5*(1+Assumptions!$C$39)^(21-1) -> -81727.107 | Y19: =-Assumptions!$C$38*Assumptions!$C$5*(1+Assumptions!$C$39)^(22-1) -> -83361.649 | Z19: =-Assumptions!$C$38*Assumptions!$C$5*(1+Assumptions!$C$39)^(23-1) -> -85028.882 | AA19: =-Assumptions!$C$38*Assumptions!$C$5*(1+Assumptions!$C$39)^(24-1) -> -86729.46 | AB19: =-Assumptions!$C$38*Assumptions!$C$5*(1+Assumptions!$C$39)^(25-1) -> -88464.049 | AC19: =-Assumptions!$C$38*Assumptions!$C$5*(1+Assumptions!$C$39)^(26-1) -> -90233.33 | AD19: =-Assumptions!$C$38*Assumptions!$C$5*(1+Assumptions!$C$39)^(27-1) -> -92037.996 | AE19: =-Assumptions!$C$38*Assumptions!$C$5*(1+Assumptions!$C$39)^(28-1) -> -93878.756 | AF19: =-Assumptions!$C$38*Assumptions!$C$5*(1+Assumptions!$C$39)^(29-1) -> -95756.331 | AG19: =-Assumptions!$C$38*Assumptions!$C$5*(1+Assumptions!$C$39)^(30-1) -> -97671.458
A20: Land lease (net of agri uplift) | B20: € | C20: =0 -> 0 | D20: =-Assumptions!$C$40*Assumptions!$C$9*(1+Assumptions!$C$39)^(1-1) -> -17500 | E20: =-Assumptions!$C$40*Assumptions!$C$9*(1+Assumptions!$C$39)^(2-1) -> -17850 | F20: =-Assumptions!$C$40*Assumptions!$C$9*(1+Assumptions!$C$39)^(3-1) -> -18207 | G20: =-Assumptions!$C$40*Assumptions!$C$9*(1+Assumptions!$C$39)^(4-1) -> -18571.14 | H20: =-Assumptions!$C$40*Assumptions!$C$9*(1+Assumptions!$C$39)^(5-1) -> -18942.563 | I20: =-Assumptions!$C$40*Assumptions!$C$9*(1+Assumptions!$C$39)^(6-1) -> -19321.414 | J20: =-Assumptions!$C$40*Assumptions!$C$9*(1+Assumptions!$C$39)^(7-1) -> -19707.842 | K20: =-Assumptions!$C$40*Assumptions!$C$9*(1+Assumptions!$C$39)^(8-1) -> -20101.999 | L20: =-Assumptions!$C$40*Assumptions!$C$9*(1+Assumptions!$C$39)^(9-1) -> -20504.039 | M20: =-Assumptions!$C$40*Assumptions!$C$9*(1+Assumptions!$C$39)^(10-1) -> -20914.12 | N20: =-Assumptions!$C$40*Assumptions!$C$9*(1+Assumptions!$C$39)^(11-1) -> -21332.402 | O20: =-Assumptions!$C$40*Assumptions!$C$9*(1+Assumptions!$C$39)^(12-1) -> -21759.05 | P20: =-Assumptions!$C$40*Assumptions!$C$9*(1+Assumptions!$C$39)^(13-1) -> -22194.231 | Q20: =-Assumptions!$C$40*Assumptions!$C$9*(1+Assumptions!$C$39)^(14-1) -> -22638.116 | R20: =-Assumptions!$C$40*Assumptions!$C$9*(1+Assumptions!$C$39)^(15-1) -> -23090.878 | S20: =-Assumptions!$C$40*Assumptions!$C$9*(1+Assumptions!$C$39)^(16-1) -> -23552.696 | T20: =-Assumptions!$C$40*Assumptions!$C$9*(1+Assumptions!$C$39)^(17-1) -> -24023.75 | U20: =-Assumptions!$C$40*Assumptions!$C$9*(1+Assumptions!$C$39)^(18-1) -> -24504.225 | V20: =-Assumptions!$C$40*Assumptions!$C$9*(1+Assumptions!$C$39)^(19-1) -> -24994.309 | W20: =-Assumptions!$C$40*Assumptions!$C$9*(1+Assumptions!$C$39)^(20-1) -> -25494.196 | X20: =-Assumptions!$C$40*Assumptions!$C$9*(1+Assumptions!$C$39)^(21-1) -> -26004.079 | Y20: =-Assumptions!$C$40*Assumptions!$C$9*(1+Assumptions!$C$39)^(22-1) -> -26524.161 | Z20: =-Assumptions!$C$40*Assumptions!$C$9*(1+Assumptions!$C$39)^(23-1) -> -27054.644 | AA20: =-Assumptions!$C$40*Assumptions!$C$9*(1+Assumptions!$C$39)^(24-1) -> -27595.737 | AB20: =-Assumptions!$C$40*Assumptions!$C$9*(1+Assumptions!$C$39)^(25-1) -> -28147.652 | AC20: =-Assumptions!$C$40*Assumptions!$C$9*(1+Assumptions!$C$39)^(26-1) -> -28710.605 | AD20: =-Assumptions!$C$40*Assumptions!$C$9*(1+Assumptions!$C$39)^(27-1) -> -29284.817 | AE20: =-Assumptions!$C$40*Assumptions!$C$9*(1+Assumptions!$C$39)^(28-1) -> -29870.513 | AF20: =-Assumptions!$C$40*Assumptions!$C$9*(1+Assumptions!$C$39)^(29-1) -> -30467.924 | AG20: =-Assumptions!$C$40*Assumptions!$C$9*(1+Assumptions!$C$39)^(30-1) -> -31077.282
A21: Insurance | B21: € | C21: =0 -> 0 | D21: =-Assumptions!$C$41*Assumptions!$C$64 -> -14162.5 | E21: =-Assumptions!$C$41*Assumptions!$C$64 -> -14162.5 | F21: =-Assumptions!$C$41*Assumptions!$C$64 -> -14162.5 | G21: =-Assumptions!$C$41*Assumptions!$C$64 -> -14162.5 | H21: =-Assumptions!$C$41*Assumptions!$C$64 -> -14162.5 | I21: =-Assumptions!$C$41*Assumptions!$C$64 -> -14162.5 | J21: =-Assumptions!$C$41*Assumptions!$C$64 -> -14162.5 | K21: =-Assumptions!$C$41*Assumptions!$C$64 -> -14162.5 | ... AG21: =-Assumptions!$C$41*Assumptions!$C$64 -> -14162.5
A22: CSRD + DPP compliance | B22: € | C22: =0 -> 0 | D22: =-Assumptions!$C$42*(1+Assumptions!$C$39)^(1-1) -> -5000 | E22: =-Assumptions!$C$42*(1+Assumptions!$C$39)^(2-1) -> -5100 | F22: =-Assumptions!$C$42*(1+Assumptions!$C$39)^(3-1) -> -5202 | G22: =-Assumptions!$C$42*(1+Assumptions!$C$39)^(4-1) -> -5306.04 | H22: =-Assumptions!$C$42*(1+Assumptions!$C$39)^(5-1) -> -5412.1608 | I22: =-Assumptions!$C$42*(1+Assumptions!$C$39)^(6-1) -> -5520.404 | J22: =-Assumptions!$C$42*(1+Assumptions!$C$39)^(7-1) -> -5630.8121 | K22: =-Assumptions!$C$42*(1+Assumptions!$C$39)^(8-1) -> -5743.4283 | L22: =-Assumptions!$C$42*(1+Assumptions!$C$39)^(9-1) -> -5858.2969 | M22: =-Assumptions!$C$42*(1+Assumptions!$C$39)^(10-1) -> -5975.4628 | N22: =-Assumptions!$C$42*(1+Assumptions!$C$39)^(11-1) -> -6094.9721 | O22: =-Assumptions!$C$42*(1+Assumptions!$C$39)^(12-1) -> -6216.8715 | P22: =-Assumptions!$C$42*(1+Assumptions!$C$39)^(13-1) -> -6341.209 | Q22: =-Assumptions!$C$42*(1+Assumptions!$C$39)^(14-1) -> -6468.0332 | R22: =-Assumptions!$C$42*(1+Assumptions!$C$39)^(15-1) -> -6597.3938 | S22: =-Assumptions!$C$42*(1+Assumptions!$C$39)^(16-1) -> -6729.3417 | T22: =-Assumptions!$C$42*(1+Assumptions!$C$39)^(17-1) -> -6863.9285 | U22: =-Assumptions!$C$42*(1+Assumptions!$C$39)^(18-1) -> -7001.2071 | V22: =-Assumptions!$C$42*(1+Assumptions!$C$39)^(19-1) -> -7141.2312 | W22: =-Assumptions!$C$42*(1+Assumptions!$C$39)^(20-1) -> -7284.0559 | X22: =-Assumptions!$C$42*(1+Assumptions!$C$39)^(21-1) -> -7429.737 | Y22: =-Assumptions!$C$42*(1+Assumptions!$C$39)^(22-1) -> -7578.3317 | Z22: =-Assumptions!$C$42*(1+Assumptions!$C$39)^(23-1) -> -7729.8984 | AA22: =-Assumptions!$C$42*(1+Assumptions!$C$39)^(24-1) -> -7884.4963 | AB22: =-Assumptions!$C$42*(1+Assumptions!$C$39)^(25-1) -> -8042.1862 | AC22: =-Assumptions!$C$42*(1+Assumptions!$C$39)^(26-1) -> -8203.03 | AD22: =-Assumptions!$C$42*(1+Assumptions!$C$39)^(27-1) -> -8367.0906 | AE22: =-Assumptions!$C$42*(1+Assumptions!$C$39)^(28-1) -> -8534.4324 | AF22: =-Assumptions!$C$42*(1+Assumptions!$C$39)^(29-1) -> -8705.121 | AG22: =-Assumptions!$C$42*(1+Assumptions!$C$39)^(30-1) -> -8879.2235
A23: Community governance | B23: € | C23: =0 -> 0 | D23: =-Assumptions!$C$43*(1+Assumptions!$C$39)^(1-1) -> 0 | E23: =-Assumptions!$C$43*(1+Assumptions!$C$39)^(2-1) -> 0 | F23: =-Assumptions!$C$43*(1+Assumptions!$C$39)^(3-1) -> 0 | G23: =-Assumptions!$C$43*(1+Assumptions!$C$39)^(4-1) -> 0 | H23: =-Assumptions!$C$43*(1+Assumptions!$C$39)^(5-1) -> 0 | I23: =-Assumptions!$C$43*(1+Assumptions!$C$39)^(6-1) -> 0 | J23: =-Assumptions!$C$43*(1+Assumptions!$C$39)^(7-1) -> 0 | K23: =-Assumptions!$C$43*(1+Assumptions!$C$39)^(8-1) -> 0 | L23: =-Assumptions!$C$43*(1+Assumptions!$C$39)^(9-1) -> 0 | M23: =-Assumptions!$C$43*(1+Assumptions!$C$39)^(10-1) -> 0 | N23: =-Assumptions!$C$43*(1+Assumptions!$C$39)^(11-1) -> 0 | O23: =-Assumptions!$C$43*(1+Assumptions!$C$39)^(12-1) -> 0 | P23: =-Assumptions!$C$43*(1+Assumptions!$C$39)^(13-1) -> 0 | Q23: =-Assumptions!$C$43*(1+Assumptions!$C$39)^(14-1) -> 0 | R23: =-Assumptions!$C$43*(1+Assumptions!$C$39)^(15-1) -> 0 | S23: =-Assumptions!$C$43*(1+Assumptions!$C$39)^(16-1) -> 0 | T23: =-Assumptions!$C$43*(1+Assumptions!$C$39)^(17-1) -> 0 | U23: =-Assumptions!$C$43*(1+Assumptions!$C$39)^(18-1) -> 0 | V23: =-Assumptions!$C$43*(1+Assumptions!$C$39)^(19-1) -> 0 | W23: =-Assumptions!$C$43*(1+Assumptions!$C$39)^(20-1) -> 0 | X23: =-Assumptions!$C$43*(1+Assumptions!$C$39)^(21-1) -> 0 | Y23: =-Assumptions!$C$43*(1+Assumptions!$C$39)^(22-1) -> 0 | Z23: =-Assumptions!$C$43*(1+Assumptions!$C$39)^(23-1) -> 0 | AA23: =-Assumptions!$C$43*(1+Assumptions!$C$39)^(24-1) -> 0 | AB23: =-Assumptions!$C$43*(1+Assumptions!$C$39)^(25-1) -> 0 | AC23: =-Assumptions!$C$43*(1+Assumptions!$C$39)^(26-1) -> 0 | AD23: =-Assumptions!$C$43*(1+Assumptions!$C$39)^(27-1) -> 0 | AE23: =-Assumptions!$C$43*(1+Assumptions!$C$39)^(28-1) -> 0 | AF23: =-Assumptions!$C$43*(1+Assumptions!$C$39)^(29-1) -> 0 | AG23: =-Assumptions!$C$43*(1+Assumptions!$C$39)^(30-1) -> 0
A24: EOL reserve contribution | B24: € | C24: =0 -> 0 | D24: =-D6*Assumptions!$C$44 -> 0 | E24: =-E6*Assumptions!$C$44 -> 0 | F24: =-F6*Assumptions!$C$44 -> 0 | G24: =-G6*Assumptions!$C$44 -> 0 | H24: =-H6*Assumptions!$C$44 -> 0 | I24: =-I6*Assumptions!$C$44 -> 0 | J24: =-J6*Assumptions!$C$44 -> 0 | K24: =-K6*Assumptions!$C$44 -> 0 | ... AG24: =-AG6*Assumptions!$C$44 -> 0
A25: Decommissioning (Year 30) | B25: € | C25: =0 -> 0 | D25: =0 -> 0 | E25: =0 -> 0 | F25: =0 -> 0 | G25: =0 -> 0 | H25: =0 -> 0 | I25: =0 -> 0 | J25: =0 -> 0 | ... AF25: =0 -> 0 | AG25: =-Assumptions!$C$35*Assumptions!$C$5 -> -75000
A26: Total operating costs | B26: € | C26: =SUM(C19:C25) -> 0 | D26: =SUM(D19:D25) -> -91662.5 | E26: =SUM(E19:E25) -> -93212.5 | F26: =SUM(F19:F25) -> -94793.5 | G26: =SUM(G19:G25) -> -96406.12 | H26: =SUM(H19:H25) -> -98050.992 | I26: =SUM(I19:I25) -> -99728.762 | J26: =SUM(J19:J25) -> -101440.09 | ... AG26: =SUM(AG19:AG25) -> -226790.46
A28: EBITDA | B28: € | C28: =C16+C26 -> 0 | D28: =D16+D26 -> 319047.5 | E28: =E16+E26 -> 323617.08 | F28: =F16+F26 -> 328246.84 | G28: =G16+G26 -> 332937.52 | H28: =H16+H26 -> 337689.87 | I28: =I16+I26 -> 342504.64 | J28: =J16+J26 -> 347382.59 | ... AG28: =AG16+AG26 -> 38242.456
A30: DEPRECIATION, INTEREST, TAX
A31: Depreciation (straight-line) | B31: € | C31: =0 -> 0 | D31: =IF(1<=Assumptions!$C$54,-Assumptions!$C$64/Assumptions!$C$54,0) -> -113300 | E31: =IF(2<=Assumptions!$C$54,-Assumptions!$C$64/Assumptions!$C$54,0) -> -113300 | F31: =IF(3<=Assumptions!$C$54,-Assumptions!$C$64/Assumptions!$C$54,0) -> -113300 | G31: =IF(4<=Assumptions!$C$54,-Assumptions!$C$64/Assumptions!$C$54,0) -> -113300 | H31: =IF(5<=Assumptions!$C$54,-Assumptions!$C$64/Assumptions!$C$54,0) -> -113300 | I31: =IF(6<=Assumptions!$C$54,-Assumptions!$C$64/Assumptions!$C$54,0) -> -113300 | J31: =IF(7<=Assumptions!$C$54,-Assumptions!$C$64/Assumptions!$C$54,0) -> -113300 | K31: =IF(8<=Assumptions!$C$54,-Assumptions!$C$64/Assumptions!$C$54,0) -> -113300 | L31: =IF(9<=Assumptions!$C$54,-Assumptions!$C$64/Assumptions!$C$54,0) -> -113300 | M31: =IF(10<=Assumptions!$C$54,-Assumptions!$C$64/Assumptions!$C$54,0) -> -113300 | N31: =IF(11<=Assumptions!$C$54,-Assumptions!$C$64/Assumptions!$C$54,0) -> -113300 | O31: =IF(12<=Assumptions!$C$54,-Assumptions!$C$64/Assumptions!$C$54,0) -> -113300 | P31: =IF(13<=Assumptions!$C$54,-Assumptions!$C$64/Assumptions!$C$54,0) -> -113300 | Q31: =IF(14<=Assumptions!$C$54,-Assumptions!$C$64/Assumptions!$C$54,0) -> -113300 | R31: =IF(15<=Assumptions!$C$54,-Assumptions!$C$64/Assumptions!$C$54,0) -> -113300 | S31: =IF(16<=Assumptions!$C$54,-Assumptions!$C$64/Assumptions!$C$54,0) -> -113300 | T31: =IF(17<=Assumptions!$C$54,-Assumptions!$C$64/Assumptions!$C$54,0) -> -113300 | U31: =IF(18<=Assumptions!$C$54,-Assumptions!$C$64/Assumptions!$C$54,0) -> -113300 | V31: =IF(19<=Assumptions!$C$54,-Assumptions!$C$64/Assumptions!$C$54,0) -> -113300 | W31: =IF(20<=Assumptions!$C$54,-Assumptions!$C$64/Assumptions!$C$54,0) -> -113300 | X31: =IF(21<=Assumptions!$C$54,-Assumptions!$C$64/Assumptions!$C$54,0) -> -113300 | Y31: =IF(22<=Assumptions!$C$54,-Assumptions!$C$64/Assumptions!$C$54,0) -> -113300 | Z31: =IF(23<=Assumptions!$C$54,-Assumptions!$C$64/Assumptions!$C$54,0) -> -113300 | AA31: =IF(24<=Assumptions!$C$54,-Assumptions!$C$64/Assumptions!$C$54,0) -> -113300 | AB31: =IF(25<=Assumptions!$C$54,-Assumptions!$C$64/Assumptions!$C$54,0) -> -113300 | AC31: =IF(26<=Assumptions!$C$54,-Assumptions!$C$64/Assumptions!$C$54,0) -> 0 | AD31: =IF(27<=Assumptions!$C$54,-Assumptions!$C$64/Assumptions!$C$54,0) -> 0 | AE31: =IF(28<=Assumptions!$C$54,-Assumptions!$C$64/Assumptions!$C$54,0) -> 0 | AF31: =IF(29<=Assumptions!$C$54,-Assumptions!$C$64/Assumptions!$C$54,0) -> 0 | AG31: =IF(30<=Assumptions!$C$54,-Assumptions!$C$64/Assumptions!$C$54,0) -> 0
A32: Debt opening balance | B32: € | C32: =0 -> 0 | D32: =Assumptions!$C$66 -> 1699500 | E32: =D35 -> 1641853.1 | F32: =E35 -> 1581035.6 | G32: =F35 -> 1516873.2 | H32: =G35 -> 1449181.8 | I32: =H35 -> 1377767.4 | J32: =I35 -> 1302425.2 | K32: =J35 -> 1222939.2 | L32: =K35 -> 1139081.5 | ... AG32: =AF35 -> 0
A33: Interest expense | B33: € | C33: =0 -> 0 | D33: =-D32*Assumptions!$C$48 -> -93472.5 | E33: =-E32*Assumptions!$C$48 -> -90301.921 | F33: =-F32*Assumptions!$C$48 -> -86956.959 | G33: =-G32*Assumptions!$C$48 -> -83428.025 | H33: =-H32*Assumptions!$C$48 -> -79705 | I33: =-I32*Assumptions!$C$48 -> -75777.208 | J33: =-J32*Assumptions!$C$48 -> -71633.387 | K33: =-K32*Assumptions!$C$48 -> -67261.657 | ... AG33: =-AG32*Assumptions!$C$48 -> 0
A34: Principal repayment | B34: € | C34: =0 -> 0 | D34: =IF(AND(1<=Assumptions!$C$49,D32>0),-(PMT(Assumptions!$C$48,Assumptions!$C$49,-Assumptions!$C$66)-(-D33)),0) -> -57646.898 | E34: =IF(AND(2<=Assumptions!$C$49,E32>0),-(PMT(Assumptions!$C$48,Assumptions!$C$49,-Assumptions!$C$66)-(-E33)),0) -> -60817.477 | F34: =IF(AND(3<=Assumptions!$C$49,F32>0),-(PMT(Assumptions!$C$48,Assumptions!$C$49,-Assumptions!$C$66)-(-F33)),0) -> -64162.438 | G34: =IF(AND(4<=Assumptions!$C$49,G32>0),-(PMT(Assumptions!$C$48,Assumptions!$C$49,-Assumptions!$C$66)-(-G33)),0) -> -67691.372 | H34: =IF(AND(5<=Assumptions!$C$49,H32>0),-(PMT(Assumptions!$C$48,Assumptions!$C$49,-Assumptions!$C$66)-(-H33)),0) -> -71414.398 | I34: =IF(AND(6<=Assumptions!$C$49,I32>0),-(PMT(Assumptions!$C$48,Assumptions!$C$49,-Assumptions!$C$66)-(-I33)),0) -> -75342.19 | J34: =IF(AND(7<=Assumptions!$C$49,J32>0),-(PMT(Assumptions!$C$48,Assumptions!$C$49,-Assumptions!$C$66)-(-J33)),0) -> -79486.01 | K34: =IF(AND(8<=Assumptions!$C$49,K32>0),-(PMT(Assumptions!$C$48,Assumptions!$C$49,-Assumptions!$C$66)-(-K33)),0) -> -83857.741 | L34: =IF(AND(9<=Assumptions!$C$49,L32>0),-(PMT(Assumptions!$C$48,Assumptions!$C$49,-Assumptions!$C$66)-(-L33)),0) -> -88469.917 | M34: =IF(AND(10<=Assumptions!$C$49,M32>0),-(PMT(Assumptions!$C$48,Assumptions!$C$49,-Assumptions!$C$66)-(-M33)),0) -> -93335.762 | N34: =IF(AND(11<=Assumptions!$C$49,N32>0),-(PMT(Assumptions!$C$48,Assumptions!$C$49,-Assumptions!$C$66)-(-N33)),0) -> -98469.229 | O34: =IF(AND(12<=Assumptions!$C$49,O32>0),-(PMT(Assumptions!$C$48,Assumptions!$C$49,-Assumptions!$C$66)-(-O33)),0) -> -103885.04 | P34: =IF(AND(13<=Assumptions!$C$49,P32>0),-(PMT(Assumptions!$C$48,Assumptions!$C$49,-Assumptions!$C$66)-(-P33)),0) -> -109598.71 | Q34: =IF(AND(14<=Assumptions!$C$49,Q32>0),-(PMT(Assumptions!$C$48,Assumptions!$C$49,-Assumptions!$C$66)-(-Q33)),0) -> -115626.64 | R34: =IF(AND(15<=Assumptions!$C$49,R32>0),-(PMT(Assumptions!$C$48,Assumptions!$C$49,-Assumptions!$C$66)-(-R33)),0) -> -121986.11 | S34: =IF(AND(16<=Assumptions!$C$49,S32>0),-(PMT(Assumptions!$C$48,Assumptions!$C$49,-Assumptions!$C$66)-(-S33)),0) -> -128695.34 | T34: =IF(AND(17<=Assumptions!$C$49,T32>0),-(PMT(Assumptions!$C$48,Assumptions!$C$49,-Assumptions!$C$66)-(-T33)),0) -> -135773.59 | U34: =IF(AND(18<=Assumptions!$C$49,U32>0),-(PMT(Assumptions!$C$48,Assumptions!$C$49,-Assumptions!$C$66)-(-U33)),0) -> -143241.14 | V34: =IF(AND(19<=Assumptions!$C$49,V32>0),-(PMT(Assumptions!$C$48,Assumptions!$C$49,-Assumptions!$C$66)-(-V33)),0) -> 0 | W34: =IF(AND(20<=Assumptions!$C$49,W32>0),-(PMT(Assumptions!$C$48,Assumptions!$C$49,-Assumptions!$C$66)-(-W33)),0) -> 0 | X34: =IF(AND(21<=Assumptions!$C$49,X32>0),-(PMT(Assumptions!$C$48,Assumptions!$C$49,-Assumptions!$C$66)-(-X33)),0) -> 0 | Y34: =IF(AND(22<=Assumptions!$C$49,Y32>0),-(PMT(Assumptions!$C$48,Assumptions!$C$49,-Assumptions!$C$66)-(-Y33)),0) -> 0 | Z34: =IF(AND(23<=Assumptions!$C$49,Z32>0),-(PMT(Assumptions!$C$48,Assumptions!$C$49,-Assumptions!$C$66)-(-Z33)),0) -> 0 | AA34: =IF(AND(24<=Assumptions!$C$49,AA32>0),-(PMT(Assumptions!$C$48,Assumptions!$C$49,-Assumptions!$C$66)-(-AA33)),0) -> 0 | AB34: =IF(AND(25<=Assumptions!$C$49,AB32>0),-(PMT(Assumptions!$C$48,Assumptions!$C$49,-Assumptions!$C$66)-(-AB33)),0) -> 0 | AC34: =IF(AND(26<=Assumptions!$C$49,AC32>0),-(PMT(Assumptions!$C$48,Assumptions!$C$49,-Assumptions!$C$66)-(-AC33)),0) -> 0 | AD34: =IF(AND(27<=Assumptions!$C$49,AD32>0),-(PMT(Assumptions!$C$48,Assumptions!$C$49,-Assumptions!$C$66)-(-AD33)),0) -> 0 | AE34: =IF(AND(28<=Assumptions!$C$49,AE32>0),-(PMT(Assumptions!$C$48,Assumptions!$C$49,-Assumptions!$C$66)-(-AE33)),0) -> 0 | AF34: =IF(AND(29<=Assumptions!$C$49,AF32>0),-(PMT(Assumptions!$C$48,Assumptions!$C$49,-Assumptions!$C$66)-(-AF33)),0) -> 0 | AG34: =IF(AND(30<=Assumptions!$C$49,AG32>0),-(PMT(Assumptions!$C$48,Assumptions!$C$49,-Assumptions!$C$66)-(-AG33)),0) -> 0
A35: Debt closing balance | B35: € | C35: =0 -> 0 | D35: =D32+D34 -> 1641853.1 | E35: =E32+E34 -> 1581035.6 | F35: =F32+F34 -> 1516873.2 | G35: =G32+G34 -> 1449181.8 | H35: =H32+H34 -> 1377767.4 | I35: =I32+I34 -> 1302425.2 | J35: =J32+J34 -> 1222939.2 | K35: =K32+K34 -> 1139081.5 | ... AG35: =AG32+AG34 -> 0
A37: EBT (Earnings before tax) | B37: € | C37: =0 -> 0 | D37: =D28+D31+D33 -> 112275 | E37: =E28+E31+E33 -> 120015.16 | F37: =F28+F31+F33 -> 127989.88 | G37: =G28+G31+G33 -> 136209.5 | H37: =H28+H31+H33 -> 144684.87 | I37: =I28+I31+I33 -> 153427.43 | J37: =J28+J31+J33 -> 162449.2 | K37: =K28+K31+K33 -> 171762.84 | ... AG37: =AG28+AG31+AG33 -> 38242.456
A38: Tax (only on positive EBT) | B38: € | C38: =0 -> 0 | D38: =-MAX(0,D37)*Assumptions!$C$55 -> -28068.75 | E38: =-MAX(0,E37)*Assumptions!$C$55 -> -30003.79 | F38: =-MAX(0,F37)*Assumptions!$C$55 -> -31997.47 | G38: =-MAX(0,G37)*Assumptions!$C$55 -> -34052.374 | H38: =-MAX(0,H37)*Assumptions!$C$55 -> -36171.217 | I38: =-MAX(0,I37)*Assumptions!$C$55 -> -38356.857 | J38: =-MAX(0,J37)*Assumptions!$C$55 -> -40612.301 | K38: =-MAX(0,K37)*Assumptions!$C$55 -> -42940.71 | ... AG38: =-MAX(0,AG37)*Assumptions!$C$55 -> -9560.614
A39: Net income | B39: € | C39: =0 -> 0 | D39: =D37+D38 -> 84206.25 | E39: =E37+E38 -> 90011.369 | F39: =F37+F38 -> 95992.41 | G39: =G37+G38 -> 102157.12 | H39: =H37+H38 -> 108513.65 | I39: =I37+I38 -> 115070.57 | J39: =J37+J38 -> 121836.9 | K39: =K37+K38 -> 128822.13 | ... AG39: =AG37+AG38 -> 28681.842
A41: CASHFLOW SUMMARY
A42: CFADS (after-tax, pre-debt) | B42: € | C42: =0 -> 0 | D42: =D28+D38 -> 290978.75 | E42: =E28+E38 -> 293613.29 | F42: =F28+F38 -> 296249.37 | G42: =G28+G38 -> 298885.15 | H42: =H28+H38 -> 301518.65 | I42: =I28+I38 -> 304147.78 | J42: =J28+J38 -> 306770.29 | K42: =K28+K38 -> 309383.79 | ... AG42: =AG28+AG38 -> 28681.842
A43: DSCR (CFADS / debt service) | B43: x | C43: =0 -> 0 | D43: =IFERROR(IF((D33+D34)=0,0,D42/(-(D33+D34))),0) -> 1.9254891 | E43: =IFERROR(IF((E33+E34)=0,0,E42/(-(E33+E34))),0) -> 1.9429226 | F43: =IFERROR(IF((F33+F34)=0,0,F42/(-(F33+F34))),0) -> 1.9603663 | G43: =IFERROR(IF((G33+G34)=0,0,G42/(-(G33+G34))),0) -> 1.977808 | H43: =IFERROR(IF((H33+H34)=0,0,H42/(-(H33+H34))),0) -> 1.9952346 | I43: =IFERROR(IF((I33+I34)=0,0,I42/(-(I33+I34))),0) -> 2.0126323 | J43: =IFERROR(IF((J33+J34)=0,0,J42/(-(J33+J34))),0) -> 2.0299862 | K43: =IFERROR(IF((K33+K34)=0,0,K42/(-(K33+K34))),0) -> 2.0472804 | ... AG43: =IFERROR(IF((AG33+AG34)=0,0,AG42/(-(AG33+AG34))),0) -> 0
A45: CAPEX | B45: € | C45: =-Assumptions!$C$64 -> -2832500 | D45: =0 -> 0 | E45: =0 -> 0 | F45: =0 -> 0 | G45: =0 -> 0 | H45: =0 -> 0 | I45: =0 -> 0 | J45: =0 -> 0 | K45: =0 -> 0 | ... AG45: =0 -> 0
A46: Project FCF (unlevered, post-tax) | B46: € | C46: =C45 -> -2832500 | D46: =D28-MAX(0,D28+D31)*Assumptions!$C$55 -> 267610.62 | E46: =E28-MAX(0,E28+E31)*Assumptions!$C$55 -> 271037.81 | F46: =F28-MAX(0,F28+F31)*Assumptions!$C$55 -> 274510.13 | G46: =G28-MAX(0,G28+G31)*Assumptions!$C$55 -> 278028.14 | H46: =H28-MAX(0,H28+H31)*Assumptions!$C$55 -> 281592.4 | I46: =I28-MAX(0,I28+I31)*Assumptions!$C$55 -> 285203.48 | J46: =J28-MAX(0,J28+J31)*Assumptions!$C$55 -> 288861.94 | K46: =K28-MAX(0,K28+K31)*Assumptions!$C$55 -> 292568.37 | ... AG46: =AG28-MAX(0,AG28+AG31)*Assumptions!$C$55 -> 28681.842
A47: Equity FCF (levered, post-tax) | B47: € | C47: =-(Assumptions!$C$67+Assumptions!$C$68) -> -1133000 | D47: =D39-D31+D34 -> 139859.35 | E47: =E39-E31+E34 -> 142493.89 | F47: =F39-F31+F34 -> 145129.97 | G47: =G39-G31+G34 -> 147765.75 | H47: =H39-H31+H34 -> 150399.25 | I47: =I39-I31+I34 -> 153028.38 | J47: =J39-J31+J34 -> 155650.89 | K47: =K39-K31+K34 -> 158264.39 | ... AG47: =AG39-AG31+AG34 -> 28681.842
A48: Cumulative project FCF | B48: € | C48: =C46 -> -2832500 | D48: =C48+D46 -> -2564889.4 | E48: =D48+E46 -> -2293851.6 | F48: =E48+F46 -> -2019341.4 | G48: =F48+G46 -> -1741313.3 | H48: =G48+H46 -> -1459720.9 | I48: =H48+I46 -> -1174517.4 | J48: =I48+J46 -> -885655.47 | K48: =J48+K46 -> -593087.1 | ... AG48: =AF48+AG46 -> 3366477
A49: Cumulative discounted FCF (@ disc_mid) | B49: € | C49: =C46 -> -2832500 | D49: =C49+D46/(1+Assumptions!$C$59)^1 -> -2584712.4 | E49: =D49+E46/(1+Assumptions!$C$59)^2 -> -2352341.1 | F49: =E49+F46/(1+Assumptions!$C$59)^3 -> -2134426.2 | G49: =F49+G46/(1+Assumptions!$C$59)^4 -> -1930067.2 | H49: =G49+H46/(1+Assumptions!$C$59)^5 -> -1738420.1 | I49: =H49+I46/(1+Assumptions!$C$59)^6 -> -1558693.5 | J49: =I49+J46/(1+Assumptions!$C$59)^7 -> -1390145.4 | K49: =J49+K46/(1+Assumptions!$C$59)^8 -> -1232079.8 | L49: =K49+L46/(1+Assumptions!$C$59)^9 -> -1083844.3 | M49: =L49+M46/(1+Assumptions!$C$59)^10 -> -944827.25 | N49: =M49+N46/(1+Assumptions!$C$59)^11 -> -814454.87 | O49: =N49+O46/(1+Assumptions!$C$59)^12 -> -692189.3 | P49: =O49+P46/(1+Assumptions!$C$59)^13 -> -577526.14 | Q49: =P49+Q46/(1+Assumptions!$C$59)^14 -> -469992.43 | R49: =Q49+R46/(1+Assumptions!$C$59)^15 -> -369144.65 | S49: =R49+S46/(1+Assumptions!$C$59)^16 -> -324573.14 | T49: =S49+T46/(1+Assumptions!$C$59)^17 -> -284014.21 | U49: =T49+U46/(1+Assumptions!$C$59)^18 -> -247124.48 | V49: =U49+V46/(1+Assumptions!$C$59)^19 -> -213589.07 | W49: =V49+W46/(1+Assumptions!$C$59)^20 -> -183119.3 | X49: =W49+X46/(1+Assumptions!$C$59)^21 -> -155450.57 | Y49: =X49+Y46/(1+Assumptions!$C$59)^22 -> -130340.38 | Z49: =Y49+Z46/(1+Assumptions!$C$59)^23 -> -107566.48 | AA49: =Z49+AA46/(1+Assumptions!$C$59)^24 -> -86925.281 | AB49: =AA49+AB46/(1+Assumptions!$C$59)^25 -> -68230.29 | AC49: =AB49+AC46/(1+Assumptions!$C$59)^26 -> -55140.288 | AD49: =AC49+AD46/(1+Assumptions!$C$59)^27 -> -43385.612 | AE49: =AD49+AE46/(1+Assumptions!$C$59)^28 -> -32844.094 | AF49: =AE49+AF46/(1+Assumptions!$C$59)^29 -> -23404.14 | AG49: =AF49+AG46/(1+Assumptions!$C$59)^30 -> -20553.815

Sheet CF_Regen
A1: Cashflow — Regenerative scenario
A2: All values link to Assumptions sheet column D. Edit Assumptions to change scenario.
A4: Line item | B4: Unit | C4: Y0 | D4: Y1 | E4: Y2 | F4: Y3 | G4: Y4 | H4: Y5 | I4: Y6 | J4: Y7 | K4: Y8 | L4: Y9 | M4: Y10 | N4: Y11 | O4: Y12 | P4: Y13 | Q4: Y14 | R4: Y15 | S4: Y16 | T4: Y17 | U4: Y18 | V4: Y19 | W4: Y20 | X4: Y21 | Y4: Y22 | Z4: Y23 | AA4: Y24 | AB4: Y25 | AC4: Y26 | AD4: Y27 | AE4: Y28 | AF4: Y29 | AG4: Y30
A5: GENERATION
A6: Generation | B6: MWh | C6: =0 -> 0 | D6: =Assumptions!$D$65*(1-Assumptions!$D$7)^(1-1) -> 5900 | E6: =Assumptions!$D$65*(1-Assumptions!$D$7)^(2-1) -> 5870.5 | F6: =Assumptions!$D$65*(1-Assumptions!$D$7)^(3-1) -> 5841.1475 | G6: =Assumptions!$D$65*(1-Assumptions!$D$7)^(4-1) -> 5811.9418 | H6: =Assumptions!$D$65*(1-Assumptions!$D$7)^(5-1) -> 5782.8821 | I6: =Assumptions!$D$65*(1-Assumptions!$D$7)^(6-1) -> 5753.9676 | J6: =Assumptions!$D$65*(1-Assumptions!$D$7)^(7-1) -> 5725.1978 | K6: =Assumptions!$D$65*(1-Assumptions!$D$7)^(8-1) -> 5696.5718 | L6: =Assumptions!$D$65*(1-Assumptions!$D$7)^(9-1) -> 5668.089 | M6: =Assumptions!$D$65*(1-Assumptions!$D$7)^(10-1) -> 5639.7485 | N6: =Assumptions!$D$65*(1-Assumptions!$D$7)^(11-1) -> 5611.5498 | O6: =Assumptions!$D$65*(1-Assumptions!$D$7)^(12-1) -> 5583.492 | P6: =Assumptions!$D$65*(1-Assumptions!$D$7)^(13-1) -> 5555.5746 | Q6: =Assumptions!$D$65*(1-Assumptions!$D$7)^(14-1) -> 5527.7967 | R6: =Assumptions!$D$65*(1-Assumptions!$D$7)^(15-1) -> 5500.1577 | S6: =Assumptions!$D$65*(1-Assumptions!$D$7)^(16-1) -> 5472.6569 | T6: =Assumptions!$D$65*(1-Assumptions!$D$7)^(17-1) -> 5445.2936 | U6: =Assumptions!$D$65*(1-Assumptions!$D$7)^(18-1) -> 5418.0672 | V6: =Assumptions!$D$65*(1-Assumptions!$D$7)^(19-1) -> 5390.9768 | W6: =Assumptions!$D$65*(1-Assumptions!$D$7)^(20-1) -> 5364.0219 | X6: =Assumptions!$D$65*(1-Assumptions!$D$7)^(21-1) -> 5337.2018 | Y6: =Assumptions!$D$65*(1-Assumptions!$D$7)^(22-1) -> 5310.5158 | Z6: =Assumptions!$D$65*(1-Assumptions!$D$7)^(23-1) -> 5283.9632 | AA6: =Assumptions!$D$65*(1-Assumptions!$D$7)^(24-1) -> 5257.5434 | AB6: =Assumptions!$D$65*(1-Assumptions!$D$7)^(25-1) -> 5231.2557 | AC6: =Assumptions!$D$65*(1-Assumptions!$D$7)^(26-1) -> 5205.0994 | AD6: =Assumptions!$D$65*(1-Assumptions!$D$7)^(27-1) -> 5179.0739 | AE6: =Assumptions!$D$65*(1-Assumptions!$D$7)^(28-1) -> 5153.1786 | AF6: =Assumptions!$D$65*(1-Assumptions!$D$7)^(29-1) -> 5127.4127 | AG6: =Assumptions!$D$65*(1-Assumptions!$D$7)^(30-1) -> 5101.7756
A8: REVENUE
A9: PPA energy revenue | B9: € | C9: =0 -> 0 | D9: =IF(1<=Assumptions!$D$23,D6*Assumptions!$D$21*(1+Assumptions!$D$22)^(1-1),D6*Assumptions!$D$24) -> 377600 | E9: =IF(2<=Assumptions!$D$23,E6*Assumptions!$D$21*(1+Assumptions!$D$22)^(2-1),E6*Assumptions!$D$24) -> 383226.24 | F9: =IF(3<=Assumptions!$D$23,F6*Assumptions!$D$21*(1+Assumptions!$D$22)^(3-1),F6*Assumptions!$D$24) -> 388936.31 | G9: =IF(4<=Assumptions!$D$23,G6*Assumptions!$D$21*(1+Assumptions!$D$22)^(4-1),G6*Assumptions!$D$24) -> 394731.46 | H9: =IF(5<=Assumptions!$D$23,H6*Assumptions!$D$21*(1+Assumptions!$D$22)^(5-1),H6*Assumptions!$D$24) -> 400612.96 | I9: =IF(6<=Assumptions!$D$23,I6*Assumptions!$D$21*(1+Assumptions!$D$22)^(6-1),I6*Assumptions!$D$24) -> 406582.09 | J9: =IF(7<=Assumptions!$D$23,J6*Assumptions!$D$21*(1+Assumptions!$D$22)^(7-1),J6*Assumptions!$D$24) -> 412640.17 | K9: =IF(8<=Assumptions!$D$23,K6*Assumptions!$D$21*(1+Assumptions!$D$22)^(8-1),K6*Assumptions!$D$24) -> 418788.51 | L9: =IF(9<=Assumptions!$D$23,L6*Assumptions!$D$21*(1+Assumptions!$D$22)^(9-1),L6*Assumptions!$D$24) -> 425028.45 | M9: =IF(10<=Assumptions!$D$23,M6*Assumptions!$D$21*(1+Assumptions!$D$22)^(10-1),M6*Assumptions!$D$24) -> 431361.38 | N9: =IF(11<=Assumptions!$D$23,N6*Assumptions!$D$21*(1+Assumptions!$D$22)^(11-1),N6*Assumptions!$D$24) -> 437788.66 | O9: =IF(12<=Assumptions!$D$23,O6*Assumptions!$D$21*(1+Assumptions!$D$22)^(12-1),O6*Assumptions!$D$24) -> 444311.71 | P9: =IF(13<=Assumptions!$D$23,P6*Assumptions!$D$21*(1+Assumptions!$D$22)^(13-1),P6*Assumptions!$D$24) -> 450931.96 | Q9: =IF(14<=Assumptions!$D$23,Q6*Assumptions!$D$21*(1+Assumptions!$D$22)^(14-1),Q6*Assumptions!$D$24) -> 457650.84 | R9: =IF(15<=Assumptions!$D$23,R6*Assumptions!$D$21*(1+Assumptions!$D$22)^(15-1),R6*Assumptions!$D$24) -> 464469.84 | S9: =IF(16<=Assumptions!$D$23,S6*Assumptions!$D$21*(1+Assumptions!$D$22)^(16-1),S6*Assumptions!$D$24) -> 471390.44 | T9: =IF(17<=Assumptions!$D$23,T6*Assumptions!$D$21*(1+Assumptions!$D$22)^(17-1),T6*Assumptions!$D$24) -> 478414.16 | U9: =IF(18<=Assumptions!$D$23,U6*Assumptions!$D$21*(1+Assumptions!$D$22)^(18-1),U6*Assumptions!$D$24) -> 485542.53 | V9: =IF(19<=Assumptions!$D$23,V6*Assumptions!$D$21*(1+Assumptions!$D$22)^(19-1),V6*Assumptions!$D$24) -> 492777.12 | W9: =IF(20<=Assumptions!$D$23,W6*Assumptions!$D$21*(1+Assumptions!$D$22)^(20-1),W6*Assumptions!$D$24) -> 500119.49 | X9: =IF(21<=Assumptions!$D$23,X6*Assumptions!$D$21*(1+Assumptions!$D$22)^(21-1),X6*Assumptions!$D$24) -> 266860.09 | Y9: =IF(22<=Assumptions!$D$23,Y6*Assumptions!$D$21*(1+Assumptions!$D$22)^(22-1),Y6*Assumptions!$D$24) -> 265525.79 | Z9: =IF(23<=Assumptions!$D$23,Z6*Assumptions!$D$21*(1+Assumptions!$D$22)^(23-1),Z6*Assumptions!$D$24) -> 264198.16 | AA9: =IF(24<=Assumptions!$D$23,AA6*Assumptions!$D$21*(1+Assumptions!$D$22)^(24-1),AA6*Assumptions!$D$24) -> 262877.17 | AB9: =IF(25<=Assumptions!$D$23,AB6*Assumptions!$D$21*(1+Assumptions!$D$22)^(25-1),AB6*Assumptions!$D$24) -> 261562.79 | AC9: =IF(26<=Assumptions!$D$23,AC6*Assumptions!$D$21*(1+Assumptions!$D$22)^(26-1),AC6*Assumptions!$D$24) -> 260254.97 | AD9: =IF(27<=Assumptions!$D$23,AD6*Assumptions!$D$21*(1+Assumptions!$D$22)^(27-1),AD6*Assumptions!$D$24) -> 258953.7 | AE9: =IF(28<=Assumptions!$D$23,AE6*Assumptions!$D$21*(1+Assumptions!$D$22)^(28-1),AE6*Assumptions!$D$24) -> 257658.93 | AF9: =IF(29<=Assumptions!$D$23,AF6*Assumptions!$D$21*(1+Assumptions!$D$22)^(29-1),AF6*Assumptions!$D$24) -> 256370.63 | AG9: =IF(30<=Assumptions!$D$23,AG6*Assumptions!$D$21*(1+Assumptions!$D$22)^(30-1),AG6*Assumptions!$D$24) -> 255088.78
A10: Low-carbon attribute premium | B10: € | C10: =0 -> 0 | D10: =IF(1<=Assumptions!$D$23,D6*Assumptions!$D$27,0) -> 17700 | E10: =IF(2<=Assumptions!$D$23,E6*Assumptions!$D$27,0) -> 17611.5 | F10: =IF(3<=Assumptions!$D$23,F6*Assumptions!$D$27,0) -> 17523.443 | G10: =IF(4<=Assumptions!$D$23,G6*Assumptions!$D$27,0) -> 17435.825 | H10: =IF(5<=Assumptions!$D$23,H6*Assumptions!$D$27,0) -> 17348.646 | I10: =IF(6<=Assumptions!$D$23,I6*Assumptions!$D$27,0) -> 17261.903 | J10: =IF(7<=Assumptions!$D$23,J6*Assumptions!$D$27,0) -> 17175.593 | K10: =IF(8<=Assumptions!$D$23,K6*Assumptions!$D$27,0) -> 17089.715 | L10: =IF(9<=Assumptions!$D$23,L6*Assumptions!$D$27,0) -> 17004.267 | M10: =IF(10<=Assumptions!$D$23,M6*Assumptions!$D$27,0) -> 16919.246 | N10: =IF(11<=Assumptions!$D$23,N6*Assumptions!$D$27,0) -> 16834.649 | O10: =IF(12<=Assumptions!$D$23,O6*Assumptions!$D$27,0) -> 16750.476 | P10: =IF(13<=Assumptions!$D$23,P6*Assumptions!$D$27,0) -> 16666.724 | Q10: =IF(14<=Assumptions!$D$23,Q6*Assumptions!$D$27,0) -> 16583.39 | R10: =IF(15<=Assumptions!$D$23,R6*Assumptions!$D$27,0) -> 16500.473 | S10: =IF(16<=Assumptions!$D$23,S6*Assumptions!$D$27,0) -> 16417.971 | T10: =IF(17<=Assumptions!$D$23,T6*Assumptions!$D$27,0) -> 16335.881 | U10: =IF(18<=Assumptions!$D$23,U6*Assumptions!$D$27,0) -> 16254.201 | V10: =IF(19<=Assumptions!$D$23,V6*Assumptions!$D$27,0) -> 16172.93 | W10: =IF(20<=Assumptions!$D$23,W6*Assumptions!$D$27,0) -> 16092.066 | X10: =IF(21<=Assumptions!$D$23,X6*Assumptions!$D$27,0) -> 0 | Y10: =IF(22<=Assumptions!$D$23,Y6*Assumptions!$D$27,0) -> 0 | Z10: =IF(23<=Assumptions!$D$23,Z6*Assumptions!$D$27,0) -> 0 | AA10: =IF(24<=Assumptions!$D$23,AA6*Assumptions!$D$27,0) -> 0 | AB10: =IF(25<=Assumptions!$D$23,AB6*Assumptions!$D$27,0) -> 0 | AC10: =IF(26<=Assumptions!$D$23,AC6*Assumptions!$D$27,0) -> 0 | AD10: =IF(27<=Assumptions!$D$23,AD6*Assumptions!$D$27,0) -> 0 | AE10: =IF(28<=Assumptions!$D$23,AE6*Assumptions!$D$27,0) -> 0 | AF10: =IF(29<=Assumptions!$D$23,AF6*Assumptions!$D$27,0) -> 0 | AG10: =IF(30<=Assumptions!$D$23,AG6*Assumptions!$D$27,0) -> 0
A11: Agrivoltaic co-revenue / premium | B11: € | C11: =0 -> 0 | D11: =D6*Assumptions!$D$28 -> 8850 | E11: =E6*Assumptions!$D$28 -> 8805.75 | F11: =F6*Assumptions!$D$28 -> 8761.7213 | G11: =G6*Assumptions!$D$28 -> 8717.9126 | H11: =H6*Assumptions!$D$28 -> 8674.3231 | I11: =I6*Assumptions!$D$28 -> 8630.9515 | J11: =J6*Assumptions!$D$28 -> 8587.7967 | K11: =K6*Assumptions!$D$28 -> 8544.8577 | ... AG11: =AG6*Assumptions!$D$28 -> 7652.6634
A12: Biodiversity credit revenue | B12: € | C12: =0 -> 0 | D12: =D6*Assumptions!$D$29 -> 0 | E12: =E6*Assumptions!$D$29 -> 0 | F12: =F6*Assumptions!$D$29 -> 0 | G12: =G6*Assumptions!$D$29 -> 0 | H12: =H6*Assumptions!$D$29 -> 0 | I12: =I6*Assumptions!$D$29 -> 0 | J12: =J6*Assumptions!$D$29 -> 0 | K12: =K6*Assumptions!$D$29 -> 0 | ... AG12: =AG6*Assumptions!$D$29 -> 0
A13: DPP / data licensing | B13: € | C13: =0 -> 0 | D13: =D6*Assumptions!$D$30 -> 0 | E13: =E6*Assumptions!$D$30 -> 0 | F13: =F6*Assumptions!$D$30 -> 0 | G13: =G6*Assumptions!$D$30 -> 0 | H13: =H6*Assumptions!$D$30 -> 0 | I13: =I6*Assumptions!$D$30 -> 0 | J13: =J6*Assumptions!$D$30 -> 0 | K13: =K6*Assumptions!$D$30 -> 0 | ... AG13: =AG6*Assumptions!$D$30 -> 0
A14: Community / energy-access grant | B14: € | C14: =0 -> 0 | D14: =Assumptions!$D$31 -> 8000 | E14: =Assumptions!$D$31 -> 8000 | F14: =Assumptions!$D$31 -> 8000 | G14: =Assumptions!$D$31 -> 8000 | H14: =Assumptions!$D$31 -> 8000 | I14: =Assumptions!$D$31 -> 8000 | J14: =Assumptions!$D$31 -> 8000 | K14: =Assumptions!$D$31 -> 8000 | ... AG14: =Assumptions!$D$31 -> 8000
A15: EOL material recovery (Year 30) | B15: € | C15: =0 -> 0 | D15: =0 -> 0 | E15: =0 -> 0 | F15: =0 -> 0 | G15: =0 -> 0 | H15: =0 -> 0 | I15: =0 -> 0 | J15: =0 -> 0 | ... AF15: =0 -> 0 | AG15: =Assumptions!$D$34*Assumptions!$D$5 -> 60000
A16: Total revenue | B16: € | C16: =SUM(C9:C15) -> 0 | D16: =SUM(D9:D15) -> 412150 | E16: =SUM(E9:E15) -> 417643.49 | F16: =SUM(F9:F15) -> 423221.47 | G16: =SUM(G9:G15) -> 428885.2 | H16: =SUM(H9:H15) -> 434635.93 | I16: =SUM(I9:I15) -> 440474.95 | J16: =SUM(J9:J15) -> 446403.56 | ... AG16: =SUM(AG9:AG15) -> 330741.44
A18: OPERATING COSTS
A19: O&M | B19: € | C19: =0 -> 0 | D19: =-Assumptions!$D$38*Assumptions!$D$5*(1+Assumptions!$D$39)^(1-1) -> -65000 | E19: =-Assumptions!$D$38*Assumptions!$D$5*(1+Assumptions!$D$39)^(2-1) -> -66300 | F19: =-Assumptions!$D$38*Assumptions!$D$5*(1+Assumptions!$D$39)^(3-1) -> -67626 | G19: =-Assumptions!$D$38*Assumptions!$D$5*(1+Assumptions!$D$39)^(4-1) -> -68978.52 | H19: =-Assumptions!$D$38*Assumptions!$D$5*(1+Assumptions!$D$39)^(5-1) -> -70358.09 | I19: =-Assumptions!$D$38*Assumptions!$D$5*(1+Assumptions!$D$39)^(6-1) -> -71765.252 | J19: =-Assumptions!$D$38*Assumptions!$D$5*(1+Assumptions!$D$39)^(7-1) -> -73200.557 | K19: =-Assumptions!$D$38*Assumptions!$D$5*(1+Assumptions!$D$39)^(8-1) -> -74664.568 | L19: =-Assumptions!$D$38*Assumptions!$D$5*(1+Assumptions!$D$39)^(9-1) -> -76157.86 | M19: =-Assumptions!$D$38*Assumptions!$D$5*(1+Assumptions!$D$39)^(10-1) -> -77681.017 | N19: =-Assumptions!$D$38*Assumptions!$D$5*(1+Assumptions!$D$39)^(11-1) -> -79234.637 | O19: =-Assumptions!$D$38*Assumptions!$D$5*(1+Assumptions!$D$39)^(12-1) -> -80819.33 | P19: =-Assumptions!$D$38*Assumptions!$D$5*(1+Assumptions!$D$39)^(13-1) -> -82435.717 | Q19: =-Assumptions!$D$38*Assumptions!$D$5*(1+Assumptions!$D$39)^(14-1) -> -84084.431 | R19: =-Assumptions!$D$38*Assumptions!$D$5*(1+Assumptions!$D$39)^(15-1) -> -85766.12 | S19: =-Assumptions!$D$38*Assumptions!$D$5*(1+Assumptions!$D$39)^(16-1) -> -87481.442 | T19: =-Assumptions!$D$38*Assumptions!$D$5*(1+Assumptions!$D$39)^(17-1) -> -89231.071 | U19: =-Assumptions!$D$38*Assumptions!$D$5*(1+Assumptions!$D$39)^(18-1) -> -91015.692 | V19: =-Assumptions!$D$38*Assumptions!$D$5*(1+Assumptions!$D$39)^(19-1) -> -92836.006 | W19: =-Assumptions!$D$38*Assumptions!$D$5*(1+Assumptions!$D$39)^(20-1) -> -94692.726 | X19: =-Assumptions!$D$38*Assumptions!$D$5*(1+Assumptions!$D$39)^(21-1) -> -96586.581 | Y19: =-Assumptions!$D$38*Assumptions!$D$5*(1+Assumptions!$D$39)^(22-1) -> -98518.312 | Z19: =-Assumptions!$D$38*Assumptions!$D$5*(1+Assumptions!$D$39)^(23-1) -> -100488.68 | AA19: =-Assumptions!$D$38*Assumptions!$D$5*(1+Assumptions!$D$39)^(24-1) -> -102498.45 | AB19: =-Assumptions!$D$38*Assumptions!$D$5*(1+Assumptions!$D$39)^(25-1) -> -104548.42 | AC19: =-Assumptions!$D$38*Assumptions!$D$5*(1+Assumptions!$D$39)^(26-1) -> -106639.39 | AD19: =-Assumptions!$D$38*Assumptions!$D$5*(1+Assumptions!$D$39)^(27-1) -> -108772.18 | AE19: =-Assumptions!$D$38*Assumptions!$D$5*(1+Assumptions!$D$39)^(28-1) -> -110947.62 | AF19: =-Assumptions!$D$38*Assumptions!$D$5*(1+Assumptions!$D$39)^(29-1) -> -113166.57 | AG19: =-Assumptions!$D$38*Assumptions!$D$5*(1+Assumptions!$D$39)^(30-1) -> -115429.9
A20: Land lease (net of agri uplift) | B20: € | C20: =0 -> 0 | D20: =-Assumptions!$D$40*Assumptions!$D$9*(1+Assumptions!$D$39)^(1-1) -> -14400 | E20: =-Assumptions!$D$40*Assumptions!$D$9*(1+Assumptions!$D$39)^(2-1) -> -14688 | F20: =-Assumptions!$D$40*Assumptions!$D$9*(1+Assumptions!$D$39)^(3-1) -> -14981.76 | G20: =-Assumptions!$D$40*Assumptions!$D$9*(1+Assumptions!$D$39)^(4-1) -> -15281.395 | H20: =-Assumptions!$D$40*Assumptions!$D$9*(1+Assumptions!$D$39)^(5-1) -> -15587.023 | I20: =-Assumptions!$D$40*Assumptions!$D$9*(1+Assumptions!$D$39)^(6-1) -> -15898.764 | J20: =-Assumptions!$D$40*Assumptions!$D$9*(1+Assumptions!$D$39)^(7-1) -> -16216.739 | K20: =-Assumptions!$D$40*Assumptions!$D$9*(1+Assumptions!$D$39)^(8-1) -> -16541.074 | L20: =-Assumptions!$D$40*Assumptions!$D$9*(1+Assumptions!$D$39)^(9-1) -> -16871.895 | M20: =-Assumptions!$D$40*Assumptions!$D$9*(1+Assumptions!$D$39)^(10-1) -> -17209.333 | N20: =-Assumptions!$D$40*Assumptions!$D$9*(1+Assumptions!$D$39)^(11-1) -> -17553.52 | O20: =-Assumptions!$D$40*Assumptions!$D$9*(1+Assumptions!$D$39)^(12-1) -> -17904.59 | P20: =-Assumptions!$D$40*Assumptions!$D$9*(1+Assumptions!$D$39)^(13-1) -> -18262.682 | Q20: =-Assumptions!$D$40*Assumptions!$D$9*(1+Assumptions!$D$39)^(14-1) -> -18627.935 | R20: =-Assumptions!$D$40*Assumptions!$D$9*(1+Assumptions!$D$39)^(15-1) -> -19000.494 | S20: =-Assumptions!$D$40*Assumptions!$D$9*(1+Assumptions!$D$39)^(16-1) -> -19380.504 | T20: =-Assumptions!$D$40*Assumptions!$D$9*(1+Assumptions!$D$39)^(17-1) -> -19768.114 | U20: =-Assumptions!$D$40*Assumptions!$D$9*(1+Assumptions!$D$39)^(18-1) -> -20163.476 | V20: =-Assumptions!$D$40*Assumptions!$D$9*(1+Assumptions!$D$39)^(19-1) -> -20566.746 | W20: =-Assumptions!$D$40*Assumptions!$D$9*(1+Assumptions!$D$39)^(20-1) -> -20978.081 | X20: =-Assumptions!$D$40*Assumptions!$D$9*(1+Assumptions!$D$39)^(21-1) -> -21397.643 | Y20: =-Assumptions!$D$40*Assumptions!$D$9*(1+Assumptions!$D$39)^(22-1) -> -21825.595 | Z20: =-Assumptions!$D$40*Assumptions!$D$9*(1+Assumptions!$D$39)^(23-1) -> -22262.107 | AA20: =-Assumptions!$D$40*Assumptions!$D$9*(1+Assumptions!$D$39)^(24-1) -> -22707.349 | AB20: =-Assumptions!$D$40*Assumptions!$D$9*(1+Assumptions!$D$39)^(25-1) -> -23161.496 | AC20: =-Assumptions!$D$40*Assumptions!$D$9*(1+Assumptions!$D$39)^(26-1) -> -23624.726 | AD20: =-Assumptions!$D$40*Assumptions!$D$9*(1+Assumptions!$D$39)^(27-1) -> -24097.221 | AE20: =-Assumptions!$D$40*Assumptions!$D$9*(1+Assumptions!$D$39)^(28-1) -> -24579.165 | AF20: =-Assumptions!$D$40*Assumptions!$D$9*(1+Assumptions!$D$39)^(29-1) -> -25070.749 | AG20: =-Assumptions!$D$40*Assumptions!$D$9*(1+Assumptions!$D$39)^(30-1) -> -25572.164
A21: Insurance | B21: € | C21: =0 -> 0 | D21: =-Assumptions!$D$41*Assumptions!$D$64 -> -16120 | E21: =-Assumptions!$D$41*Assumptions!$D$64 -> -16120 | F21: =-Assumptions!$D$41*Assumptions!$D$64 -> -16120 | G21: =-Assumptions!$D$41*Assumptions!$D$64 -> -16120 | H21: =-Assumptions!$D$41*Assumptions!$D$64 -> -16120 | I21: =-Assumptions!$D$41*Assumptions!$D$64 -> -16120 | J21: =-Assumptions!$D$41*Assumptions!$D$64 -> -16120 | K21: =-Assumptions!$D$41*Assumptions!$D$64 -> -16120 | ... AG21: =-Assumptions!$D$41*Assumptions!$D$64 -> -16120
A22: CSRD + DPP compliance | B22: € | C22: =0 -> 0 | D22: =-Assumptions!$D$42*(1+Assumptions!$D$39)^(1-1) -> -8000 | E22: =-Assumptions!$D$42*(1+Assumptions!$D$39)^(2-1) -> -8160 | F22: =-Assumptions!$D$42*(1+Assumptions!$D$39)^(3-1) -> -8323.2 | G22: =-Assumptions!$D$42*(1+Assumptions!$D$39)^(4-1) -> -8489.664 | H22: =-Assumptions!$D$42*(1+Assumptions!$D$39)^(5-1) -> -8659.4573 | I22: =-Assumptions!$D$42*(1+Assumptions!$D$39)^(6-1) -> -8832.6464 | J22: =-Assumptions!$D$42*(1+Assumptions!$D$39)^(7-1) -> -9009.2994 | K22: =-Assumptions!$D$42*(1+Assumptions!$D$39)^(8-1) -> -9189.4853 | L22: =-Assumptions!$D$42*(1+Assumptions!$D$39)^(9-1) -> -9373.275 | M22: =-Assumptions!$D$42*(1+Assumptions!$D$39)^(10-1) -> -9560.7405 | N22: =-Assumptions!$D$42*(1+Assumptions!$D$39)^(11-1) -> -9751.9554 | O22: =-Assumptions!$D$42*(1+Assumptions!$D$39)^(12-1) -> -9946.9945 | P22: =-Assumptions!$D$42*(1+Assumptions!$D$39)^(13-1) -> -10145.934 | Q22: =-Assumptions!$D$42*(1+Assumptions!$D$39)^(14-1) -> -10348.853 | R22: =-Assumptions!$D$42*(1+Assumptions!$D$39)^(15-1) -> -10555.83 | S22: =-Assumptions!$D$42*(1+Assumptions!$D$39)^(16-1) -> -10766.947 | T22: =-Assumptions!$D$42*(1+Assumptions!$D$39)^(17-1) -> -10982.286 | U22: =-Assumptions!$D$42*(1+Assumptions!$D$39)^(18-1) -> -11201.931 | V22: =-Assumptions!$D$42*(1+Assumptions!$D$39)^(19-1) -> -11425.97 | W22: =-Assumptions!$D$42*(1+Assumptions!$D$39)^(20-1) -> -11654.489 | X22: =-Assumptions!$D$42*(1+Assumptions!$D$39)^(21-1) -> -11887.579 | Y22: =-Assumptions!$D$42*(1+Assumptions!$D$39)^(22-1) -> -12125.331 | Z22: =-Assumptions!$D$42*(1+Assumptions!$D$39)^(23-1) -> -12367.837 | AA22: =-Assumptions!$D$42*(1+Assumptions!$D$39)^(24-1) -> -12615.194 | AB22: =-Assumptions!$D$42*(1+Assumptions!$D$39)^(25-1) -> -12867.498 | AC22: =-Assumptions!$D$42*(1+Assumptions!$D$39)^(26-1) -> -13124.848 | AD22: =-Assumptions!$D$42*(1+Assumptions!$D$39)^(27-1) -> -13387.345 | AE22: =-Assumptions!$D$42*(1+Assumptions!$D$39)^(28-1) -> -13655.092 | AF22: =-Assumptions!$D$42*(1+Assumptions!$D$39)^(29-1) -> -13928.194 | AG22: =-Assumptions!$D$42*(1+Assumptions!$D$39)^(30-1) -> -14206.758
A23: Community governance | B23: € | C23: =0 -> 0 | D23: =-Assumptions!$D$43*(1+Assumptions!$D$39)^(1-1) -> -6000 | E23: =-Assumptions!$D$43*(1+Assumptions!$D$39)^(2-1) -> -6120 | F23: =-Assumptions!$D$43*(1+Assumptions!$D$39)^(3-1) -> -6242.4 | G23: =-Assumptions!$D$43*(1+Assumptions!$D$39)^(4-1) -> -6367.248 | H23: =-Assumptions!$D$43*(1+Assumptions!$D$39)^(5-1) -> -6494.593 | I23: =-Assumptions!$D$43*(1+Assumptions!$D$39)^(6-1) -> -6624.4848 | J23: =-Assumptions!$D$43*(1+Assumptions!$D$39)^(7-1) -> -6756.9745 | K23: =-Assumptions!$D$43*(1+Assumptions!$D$39)^(8-1) -> -6892.114 | L23: =-Assumptions!$D$43*(1+Assumptions!$D$39)^(9-1) -> -7029.9563 | M23: =-Assumptions!$D$43*(1+Assumptions!$D$39)^(10-1) -> -7170.5554 | N23: =-Assumptions!$D$43*(1+Assumptions!$D$39)^(11-1) -> -7313.9665 | O23: =-Assumptions!$D$43*(1+Assumptions!$D$39)^(12-1) -> -7460.2459 | P23: =-Assumptions!$D$43*(1+Assumptions!$D$39)^(13-1) -> -7609.4508 | Q23: =-Assumptions!$D$43*(1+Assumptions!$D$39)^(14-1) -> -7761.6398 | R23: =-Assumptions!$D$43*(1+Assumptions!$D$39)^(15-1) -> -7916.8726 | S23: =-Assumptions!$D$43*(1+Assumptions!$D$39)^(16-1) -> -8075.21 | T23: =-Assumptions!$D$43*(1+Assumptions!$D$39)^(17-1) -> -8236.7142 | U23: =-Assumptions!$D$43*(1+Assumptions!$D$39)^(18-1) -> -8401.4485 | V23: =-Assumptions!$D$43*(1+Assumptions!$D$39)^(19-1) -> -8569.4775 | W23: =-Assumptions!$D$43*(1+Assumptions!$D$39)^(20-1) -> -8740.867 | X23: =-Assumptions!$D$43*(1+Assumptions!$D$39)^(21-1) -> -8915.6844 | Y23: =-Assumptions!$D$43*(1+Assumptions!$D$39)^(22-1) -> -9093.9981 | Z23: =-Assumptions!$D$43*(1+Assumptions!$D$39)^(23-1) -> -9275.878 | AA23: =-Assumptions!$D$43*(1+Assumptions!$D$39)^(24-1) -> -9461.3956 | AB23: =-Assumptions!$D$43*(1+Assumptions!$D$39)^(25-1) -> -9650.6235 | AC23: =-Assumptions!$D$43*(1+Assumptions!$D$39)^(26-1) -> -9843.636 | AD23: =-Assumptions!$D$43*(1+Assumptions!$D$39)^(27-1) -> -10040.509 | AE23: =-Assumptions!$D$43*(1+Assumptions!$D$39)^(28-1) -> -10241.319 | AF23: =-Assumptions!$D$43*(1+Assumptions!$D$39)^(29-1) -> -10446.145 | AG23: =-Assumptions!$D$43*(1+Assumptions!$D$39)^(30-1) -> -10655.068
A24: EOL reserve contribution | B24: € | C24: =0 -> 0 | D24: =-D6*Assumptions!$D$44 -> -11800 | E24: =-E6*Assumptions!$D$44 -> -11741 | F24: =-F6*Assumptions!$D$44 -> -11682.295 | G24: =-G6*Assumptions!$D$44 -> -11623.884 | H24: =-H6*Assumptions!$D$44 -> -11565.764 | I24: =-I6*Assumptions!$D$44 -> -11507.935 | J24: =-J6*Assumptions!$D$44 -> -11450.396 | K24: =-K6*Assumptions!$D$44 -> -11393.144 | ... AG24: =-AG6*Assumptions!$D$44 -> -10203.551
A25: Decommissioning (Year 30) | B25: € | C25: =0 -> 0 | D25: =0 -> 0 | E25: =0 -> 0 | F25: =0 -> 0 | G25: =0 -> 0 | H25: =0 -> 0 | I25: =0 -> 0 | J25: =0 -> 0 | ... AF25: =0 -> 0 | AG25: =-Assumptions!$D$35*Assumptions!$D$5 -> -90000
A26: Total operating costs | B26: € | C26: =SUM(C19:C25) -> 0 | D26: =SUM(D19:D25) -> -121320 | E26: =SUM(E19:E25) -> -123129 | F26: =SUM(F19:F25) -> -124975.65 | G26: =SUM(G19:G25) -> -126860.71 | H26: =SUM(H19:H25) -> -128784.93 | I26: =SUM(I19:I25) -> -130749.08 | J26: =SUM(J19:J25) -> -132753.97 | ... AG26: =SUM(AG19:AG25) -> -282187.45
A28: EBITDA | B28: € | C28: =C16+C26 -> 0 | D28: =D16+D26 -> 290830 | E28: =E16+E26 -> 294514.49 | F28: =F16+F26 -> 298245.82 | G28: =G16+G26 -> 302024.49 | H28: =H16+H26 -> 305851 | I28: =I16+I26 -> 309725.87 | J28: =J16+J26 -> 313649.59 | ... AG28: =AG16+AG26 -> 48553.999
A30: DEPRECIATION, INTEREST, TAX
A31: Depreciation (straight-line) | B31: € | C31: =0 -> 0 | D31: =IF(1<=Assumptions!$D$54,-Assumptions!$D$64/Assumptions!$D$54,0) -> -128960 | E31: =IF(2<=Assumptions!$D$54,-Assumptions!$D$64/Assumptions!$D$54,0) -> -128960 | F31: =IF(3<=Assumptions!$D$54,-Assumptions!$D$64/Assumptions!$D$54,0) -> -128960 | G31: =IF(4<=Assumptions!$D$54,-Assumptions!$D$64/Assumptions!$D$54,0) -> -128960 | H31: =IF(5<=Assumptions!$D$54,-Assumptions!$D$64/Assumptions!$D$54,0) -> -128960 | I31: =IF(6<=Assumptions!$D$54,-Assumptions!$D$64/Assumptions!$D$54,0) -> -128960 | J31: =IF(7<=Assumptions!$D$54,-Assumptions!$D$64/Assumptions!$D$54,0) -> -128960 | K31: =IF(8<=Assumptions!$D$54,-Assumptions!$D$64/Assumptions!$D$54,0) -> -128960 | L31: =IF(9<=Assumptions!$D$54,-Assumptions!$D$64/Assumptions!$D$54,0) -> -128960 | M31: =IF(10<=Assumptions!$D$54,-Assumptions!$D$64/Assumptions!$D$54,0) -> -128960 | N31: =IF(11<=Assumptions!$D$54,-Assumptions!$D$64/Assumptions!$D$54,0) -> -128960 | O31: =IF(12<=Assumptions!$D$54,-Assumptions!$D$64/Assumptions!$D$54,0) -> -128960 | P31: =IF(13<=Assumptions!$D$54,-Assumptions!$D$64/Assumptions!$D$54,0) -> -128960 | Q31: =IF(14<=Assumptions!$D$54,-Assumptions!$D$64/Assumptions!$D$54,0) -> -128960 | R31: =IF(15<=Assumptions!$D$54,-Assumptions!$D$64/Assumptions!$D$54,0) -> -128960 | S31: =IF(16<=Assumptions!$D$54,-Assumptions!$D$64/Assumptions!$D$54,0) -> -128960 | T31: =IF(17<=Assumptions!$D$54,-Assumptions!$D$64/Assumptions!$D$54,0) -> -128960 | U31: =IF(18<=Assumptions!$D$54,-Assumptions!$D$64/Assumptions!$D$54,0) -> -128960 | V31: =IF(19<=Assumptions!$D$54,-Assumptions!$D$64/Assumptions!$D$54,0) -> -128960 | W31: =IF(20<=Assumptions!$D$54,-Assumptions!$D$64/Assumptions!$D$54,0) -> -128960 | X31: =IF(21<=Assumptions!$D$54,-Assumptions!$D$64/Assumptions!$D$54,0) -> -128960 | Y31: =IF(22<=Assumptions!$D$54,-Assumptions!$D$64/Assumptions!$D$54,0) -> -128960 | Z31: =IF(23<=Assumptions!$D$54,-Assumptions!$D$64/Assumptions!$D$54,0) -> -128960 | AA31: =IF(24<=Assumptions!$D$54,-Assumptions!$D$64/Assumptions!$D$54,0) -> -128960 | AB31: =IF(25<=Assumptions!$D$54,-Assumptions!$D$64/Assumptions!$D$54,0) -> -128960 | AC31: =IF(26<=Assumptions!$D$54,-Assumptions!$D$64/Assumptions!$D$54,0) -> 0 | AD31: =IF(27<=Assumptions!$D$54,-Assumptions!$D$64/Assumptions!$D$54,0) -> 0 | AE31: =IF(28<=Assumptions!$D$54,-Assumptions!$D$64/Assumptions!$D$54,0) -> 0 | AF31: =IF(29<=Assumptions!$D$54,-Assumptions!$D$64/Assumptions!$D$54,0) -> 0 | AG31: =IF(30<=Assumptions!$D$54,-Assumptions!$D$64/Assumptions!$D$54,0) -> 0
A32: Debt opening balance | B32: € | C32: =0 -> 0 | D32: =Assumptions!$D$66 -> 1934400 | E32: =D35 -> 1872738.8 | F32: =E35 -> 1808302.8 | G32: =F35 -> 1740967.2 | H32: =G35 -> 1670601.5 | I32: =H35 -> 1597069.4 | J32: =I35 -> 1520228.3 | K32: =J35 -> 1439929.4 | L32: =K35 -> 1356017 | ... AG32: =AF35 -> -6.4028427e-10
A33: Interest expense | B33: € | C33: =0 -> 0 | D33: =-D32*Assumptions!$D$48 -> -87048 | E33: =-E32*Assumptions!$D$48 -> -84273.245 | F33: =-F32*Assumptions!$D$48 -> -81373.627 | G33: =-G32*Assumptions!$D$48 -> -78343.525 | H33: =-H32*Assumptions!$D$48 -> -75177.069 | I33: =-I32*Assumptions!$D$48 -> -71868.123 | J33: =-J32*Assumptions!$D$48 -> -68410.274 | K33: =-K32*Assumptions!$D$48 -> -64796.822 | ... AG33: =-AG32*Assumptions!$D$48 -> 2.8812792e-11
A34: Principal repayment | B34: € | C34: =0 -> 0 | D34: =IF(AND(1<=Assumptions!$D$49,D32>0),-(PMT(Assumptions!$D$48,Assumptions!$D$49,-Assumptions!$D$66)-(-D33)),0) -> -61661.214 | E34: =IF(AND(2<=Assumptions!$D$49,E32>0),-(PMT(Assumptions!$D$48,Assumptions!$D$49,-Assumptions!$D$66)-(-E33)),0) -> -64435.968 | F34: =IF(AND(3<=Assumptions!$D$49,F32>0),-(PMT(Assumptions!$D$48,Assumptions!$D$49,-Assumptions!$D$66)-(-F33)),0) -> -67335.587 | G34: =IF(AND(4<=Assumptions!$D$49,G32>0),-(PMT(Assumptions!$D$48,Assumptions!$D$49,-Assumptions!$D$66)-(-G33)),0) -> -70365.688 | H34: =IF(AND(5<=Assumptions!$D$49,H32>0),-(PMT(Assumptions!$D$48,Assumptions!$D$49,-Assumptions!$D$66)-(-H33)),0) -> -73532.144 | I34: =IF(AND(6<=Assumptions!$D$49,I32>0),-(PMT(Assumptions!$D$48,Assumptions!$D$49,-Assumptions!$D$66)-(-I33)),0) -> -76841.091 | J34: =IF(AND(7<=Assumptions!$D$49,J32>0),-(PMT(Assumptions!$D$48,Assumptions!$D$49,-Assumptions!$D$66)-(-J33)),0) -> -80298.94 | K34: =IF(AND(8<=Assumptions!$D$49,K32>0),-(PMT(Assumptions!$D$48,Assumptions!$D$49,-Assumptions!$D$66)-(-K33)),0) -> -83912.392 | L34: =IF(AND(9<=Assumptions!$D$49,L32>0),-(PMT(Assumptions!$D$48,Assumptions!$D$49,-Assumptions!$D$66)-(-L33)),0) -> -87688.45 | M34: =IF(AND(10<=Assumptions!$D$49,M32>0),-(PMT(Assumptions!$D$48,Assumptions!$D$49,-Assumptions!$D$66)-(-M33)),0) -> -91634.43 | N34: =IF(AND(11<=Assumptions!$D$49,N32>0),-(PMT(Assumptions!$D$48,Assumptions!$D$49,-Assumptions!$D$66)-(-N33)),0) -> -95757.979 | O34: =IF(AND(12<=Assumptions!$D$49,O32>0),-(PMT(Assumptions!$D$48,Assumptions!$D$49,-Assumptions!$D$66)-(-O33)),0) -> -100067.09 | P34: =IF(AND(13<=Assumptions!$D$49,P32>0),-(PMT(Assumptions!$D$48,Assumptions!$D$49,-Assumptions!$D$66)-(-P33)),0) -> -104570.11 | Q34: =IF(AND(14<=Assumptions!$D$49,Q32>0),-(PMT(Assumptions!$D$48,Assumptions!$D$49,-Assumptions!$D$66)-(-Q33)),0) -> -109275.76 | R34: =IF(AND(15<=Assumptions!$D$49,R32>0),-(PMT(Assumptions!$D$48,Assumptions!$D$49,-Assumptions!$D$66)-(-R33)),0) -> -114193.17 | S34: =IF(AND(16<=Assumptions!$D$49,S32>0),-(PMT(Assumptions!$D$48,Assumptions!$D$49,-Assumptions!$D$66)-(-S33)),0) -> -119331.86 | T34: =IF(AND(17<=Assumptions!$D$49,T32>0),-(PMT(Assumptions!$D$48,Assumptions!$D$49,-Assumptions!$D$66)-(-T33)),0) -> -124701.8 | U34: =IF(AND(18<=Assumptions!$D$49,U32>0),-(PMT(Assumptions!$D$48,Assumptions!$D$49,-Assumptions!$D$66)-(-U33)),0) -> -130313.38 | V34: =IF(AND(19<=Assumptions!$D$49,V32>0),-(PMT(Assumptions!$D$48,Assumptions!$D$49,-Assumptions!$D$66)-(-V33)),0) -> -136177.48 | W34: =IF(AND(20<=Assumptions!$D$49,W32>0),-(PMT(Assumptions!$D$48,Assumptions!$D$49,-Assumptions!$D$66)-(-W33)),0) -> -142305.47 | X34: =IF(AND(21<=Assumptions!$D$49,X32>0),-(PMT(Assumptions!$D$48,Assumptions!$D$49,-Assumptions!$D$66)-(-X33)),0) -> 0 | Y34: =IF(AND(22<=Assumptions!$D$49,Y32>0),-(PMT(Assumptions!$D$48,Assumptions!$D$49,-Assumptions!$D$66)-(-Y33)),0) -> 0 | Z34: =IF(AND(23<=Assumptions!$D$49,Z32>0),-(PMT(Assumptions!$D$48,Assumptions!$D$49,-Assumptions!$D$66)-(-Z33)),0) -> 0 | AA34: =IF(AND(24<=Assumptions!$D$49,AA32>0),-(PMT(Assumptions!$D$48,Assumptions!$D$49,-Assumptions!$D$66)-(-AA33)),0) -> 0 | AB34: =IF(AND(25<=Assumptions!$D$49,AB32>0),-(PMT(Assumptions!$D$48,Assumptions!$D$49,-Assumptions!$D$66)-(-AB33)),0) -> 0 | AC34: =IF(AND(26<=Assumptions!$D$49,AC32>0),-(PMT(Assumptions!$D$48,Assumptions!$D$49,-Assumptions!$D$66)-(-AC33)),0) -> 0 | AD34: =IF(AND(27<=Assumptions!$D$49,AD32>0),-(PMT(Assumptions!$D$48,Assumptions!$D$49,-Assumptions!$D$66)-(-AD33)),0) -> 0 | AE34: =IF(AND(28<=Assumptions!$D$49,AE32>0),-(PMT(Assumptions!$D$48,Assumptions!$D$49,-Assumptions!$D$66)-(-AE33)),0) -> 0 | AF34: =IF(AND(29<=Assumptions!$D$49,AF32>0),-(PMT(Assumptions!$D$48,Assumptions!$D$49,-Assumptions!$D$66)-(-AF33)),0) -> 0 | AG34: =IF(AND(30<=Assumptions!$D$49,AG32>0),-(PMT(Assumptions!$D$48,Assumptions!$D$49,-Assumptions!$D$66)-(-AG33)),0) -> 0
A35: Debt closing balance | B35: € | C35: =0 -> 0 | D35: =D32+D34 -> 1872738.8 | E35: =E32+E34 -> 1808302.8 | F35: =F32+F34 -> 1740967.2 | G35: =G32+G34 -> 1670601.5 | H35: =H32+H34 -> 1597069.4 | I35: =I32+I34 -> 1520228.3 | J35: =J32+J34 -> 1439929.4 | K35: =K32+K34 -> 1356017 | ... AG35: =AG32+AG34 -> -6.4028427e-10
A37: EBT (Earnings before tax) | B37: € | C37: =0 -> 0 | D37: =D28+D31+D33 -> 74822 | E37: =E28+E31+E33 -> 81281.245 | F37: =F28+F31+F33 -> 87912.193 | G37: =G28+G31+G33 -> 94720.964 | H37: =H28+H31+H33 -> 101713.93 | I37: =I28+I31+I33 -> 108897.74 | J37: =J28+J31+J33 -> 116279.32 | K37: =K28+K31+K33 -> 123865.87 | ... AG37: =AG28+AG31+AG33 -> 48553.999
A38: Tax (only on positive EBT) | B38: € | C38: =0 -> 0 | D38: =-MAX(0,D37)*Assumptions!$D$55 -> -18705.5 | E38: =-MAX(0,E37)*Assumptions!$D$55 -> -20320.311 | F38: =-MAX(0,F37)*Assumptions!$D$55 -> -21978.048 | G38: =-MAX(0,G37)*Assumptions!$D$55 -> -23680.241 | H38: =-MAX(0,H37)*Assumptions!$D$55 -> -25428.483 | I38: =-MAX(0,I37)*Assumptions!$D$55 -> -27224.436 | J38: =-MAX(0,J37)*Assumptions!$D$55 -> -29069.829 | K38: =-MAX(0,K37)*Assumptions!$D$55 -> -30966.468 | ... AG38: =-MAX(0,AG37)*Assumptions!$D$55 -> -12138.5
A39: Net income | B39: € | C39: =0 -> 0 | D39: =D37+D38 -> 56116.5 | E39: =E37+E38 -> 60960.933 | F39: =F37+F38 -> 65934.145 | G39: =G37+G38 -> 71040.723 | H39: =H37+H38 -> 76285.45 | I39: =I37+I38 -> 81673.307 | J39: =J37+J38 -> 87209.488 | K39: =K37+K38 -> 92899.404 | ... AG39: =AG37+AG38 -> 36415.499
A41: CASHFLOW SUMMARY
A42: CFADS (after-tax, pre-debt) | B42: € | C42: =0 -> 0 | D42: =D28+D38 -> 272124.5 | E42: =E28+E38 -> 274194.18 | F42: =F28+F38 -> 276267.77 | G42: =G28+G38 -> 278344.25 | H42: =H28+H38 -> 280422.52 | I42: =I28+I38 -> 282501.43 | J42: =J28+J38 -> 284579.76 | K42: =K28+K38 -> 286656.23 | ... AG42: =AG28+AG38 -> 36415.499
A43: DSCR (CFADS / debt service) | B43: x | C43: =0 -> 0 | D43: =IFERROR(IF((D33+D34)=0,0,D42/(-(D33+D34))),0) -> 1.8299102 | E43: =IFERROR(IF((E33+E34)=0,0,E42/(-(E33+E34))),0) -> 1.8438278 | F43: =IFERROR(IF((F33+F34)=0,0,F42/(-(F33+F34))),0) -> 1.8577717 | G43: =IFERROR(IF((G33+G34)=0,0,G42/(-(G33+G34))),0) -> 1.8717351 | H43: =IFERROR(IF((H33+H34)=0,0,H42/(-(H33+H34))),0) -> 1.8857105 | I43: =IFERROR(IF((I33+I34)=0,0,I42/(-(I33+I34))),0) -> 1.8996902 | J43: =IFERROR(IF((J33+J34)=0,0,J42/(-(J33+J34))),0) -> 1.913666 | K43: =IFERROR(IF((K33+K34)=0,0,K42/(-(K33+K34))),0) -> 1.9276292 | ... AG43: =IFERROR(IF((AG33+AG34)=0,0,AG42/(-(AG33+AG34))),0) -> -1.2638657e+15
A45: CAPEX | B45: € | C45: =-Assumptions!$D$64 -> -3224000 | D45: =0 -> 0 | E45: =0 -> 0 | F45: =0 -> 0 | G45: =0 -> 0 | H45: =0 -> 0 | I45: =0 -> 0 | J45: =0 -> 0 | K45: =0 -> 0 | ... AG45: =0 -> 0
A46: Project FCF (unlevered, post-tax) | B46: € | C46: =C45 -> -3224000 | D46: =D28-MAX(0,D28+D31)*Assumptions!$D$55 -> 250362.5 | E46: =E28-MAX(0,E28+E31)*Assumptions!$D$55 -> 253125.87 | F46: =F28-MAX(0,F28+F31)*Assumptions!$D$55 -> 255924.36 | G46: =G28-MAX(0,G28+G31)*Assumptions!$D$55 -> 258758.37 | H46: =H28-MAX(0,H28+H31)*Assumptions!$D$55 -> 261628.25 | I46: =I28-MAX(0,I28+I31)*Assumptions!$D$55 -> 264534.4 | J46: =J28-MAX(0,J28+J31)*Assumptions!$D$55 -> 267477.19 | K46: =K28-MAX(0,K28+K31)*Assumptions!$D$55 -> 270457.02 | ... AG46: =AG28-MAX(0,AG28+AG31)*Assumptions!$D$55 -> 36415.499
A47: Equity FCF (levered, post-tax) | B47: € | C47: =-(Assumptions!$D$67+Assumptions!$D$68) -> -1289600 | D47: =D39-D31+D34 -> 123415.29 | E47: =E39-E31+E34 -> 125484.97 | F47: =F39-F31+F34 -> 127558.56 | G47: =G39-G31+G34 -> 129635.03 | H47: =H39-H31+H34 -> 131713.31 | I47: =I39-I31+I34 -> 133792.22 | J47: =J39-J31+J34 -> 135870.55 | K47: =K39-K31+K34 -> 137947.01 | ... AG47: =AG39-AG31+AG34 -> 36415.499
A48: Cumulative project FCF | B48: € | C48: =C46 -> -3224000 | D48: =C48+D46 -> -2973637.5 | E48: =D48+E46 -> -2720511.6 | F48: =E48+F46 -> -2464587.3 | G48: =F48+G46 -> -2205828.9 | H48: =G48+H46 -> -1944200.6 | I48: =H48+I46 -> -1679666.2 | J48: =I48+J46 -> -1412189.1 | K48: =J48+K46 -> -1141732 | ... AG48: =AF48+AG46 -> 3200716.3
A49: Cumulative discounted FCF (@ disc_mid) | B49: € | C49: =C46 -> -3224000 | D49: =C49+D46/(1+Assumptions!$D$59)^1 -> -2992182.9 | E49: =D49+E46/(1+Assumptions!$D$59)^2 -> -2775168.2 | F49: =E49+F46/(1+Assumptions!$D$59)^3 -> -2572007.2 | G49: =F49+G46/(1+Assumptions!$D$59)^4 -> -2381812.1 | H49: =G49+H46/(1+Assumptions!$D$59)^5 -> -2203752.3 | I49: =H49+I46/(1+Assumptions!$D$59)^6 -> -2037050.8 | J49: =I49+J46/(1+Assumptions!$D$59)^7 -> -1880980.4 | K49: =J49+K46/(1+Assumptions!$D$59)^8 -> -1734860.9 | L49: =K49+L46/(1+Assumptions!$D$59)^9 -> -1598055.7 | M49: =L49+M46/(1+Assumptions!$D$59)^10 -> -1469969.1 | N49: =M49+N46/(1+Assumptions!$D$59)^11 -> -1350043.7 | O49: =N49+O46/(1+Assumptions!$D$59)^12 -> -1237758.1 | P49: =O49+P46/(1+Assumptions!$D$59)^13 -> -1132623.9 | Q49: =P49+Q46/(1+Assumptions!$D$59)^14 -> -1034184.5 | R49: =Q49+R46/(1+Assumptions!$D$59)^15 -> -942012.33 | S49: =R49+S46/(1+Assumptions!$D$59)^16 -> -855707.32 | T49: =S49+T46/(1+Assumptions!$D$59)^17 -> -774895.04 | U49: =T49+U46/(1+Assumptions!$D$59)^18 -> -699225.02 | V49: =U49+V46/(1+Assumptions!$D$59)^19 -> -628369.27 | W49: =V49+W46/(1+Assumptions!$D$59)^20 -> -562020.76 | X49: =W49+X46/(1+Assumptions!$D$59)^21 -> -538721.62 | Y49: =X49+Y46/(1+Assumptions!$D$59)^22 -> -517901.89 | Z49: =Y49+Z46/(1+Assumptions!$D$59)^23 -> -499330.43 | AA49: =Z49+AA46/(1+Assumptions!$D$59)^24 -> -482796.28 | AB49: =AA49+AB46/(1+Assumptions!$D$59)^25 -> -468107.01 | AC49: =AB49+AC46/(1+Assumptions!$D$59)^26 -> -458342.08 | AD49: =AC49+AD46/(1+Assumptions!$D$59)^27 -> -449709.17 | AE49: =AD49+AE46/(1+Assumptions!$D$59)^28 -> -442098.93 | AF49: =AE49+AF46/(1+Assumptions!$D$59)^29 -> -435411.73 | AG49: =AF49+AG46/(1+Assumptions!$D$59)^30 -> -431792.86

Sheet CF_Future
A1: Cashflow — Future (2030) scenario
A2: All values link to Assumptions sheet column E. Edit Assumptions to change scenario.
A4: Line item | B4: Unit | C4: Y0 | D4: Y1 | E4: Y2 | F4: Y3 | G4: Y4 | H4: Y5 | I4: Y6 | J4: Y7 | K4: Y8 | L4: Y9 | M4: Y10 | N4: Y11 | O4: Y12 | P4: Y13 | Q4: Y14 | R4: Y15 | S4: Y16 | T4: Y17 | U4: Y18 | V4: Y19 | W4: Y20 | X4: Y21 | Y4: Y22 | Z4: Y23 | AA4: Y24 | AB4: Y25 | AC4: Y26 | AD4: Y27 | AE4: Y28 | AF4: Y29 | AG4: Y30
A5: GENERATION
A6: Generation | B6: MWh | C6: =0 -> 0 | D6: =Assumptions!$E$65*(1-Assumptions!$E$7)^(1-1) -> 5900 | E6: =Assumptions!$E$65*(1-Assumptions!$E$7)^(2-1) -> 5870.5 | F6: =Assumptions!$E$65*(1-Assumptions!$E$7)^(3-1) -> 5841.1475 | G6: =Assumptions!$E$65*(1-Assumptions!$E$7)^(4-1) -> 5811.9418 | H6: =Assumptions!$E$65*(1-Assumptions!$E$7)^(5-1) -> 5782.8821 | I6: =Assumptions!$E$65*(1-Assumptions!$E$7)^(6-1) -> 5753.9676 | J6: =Assumptions!$E$65*(1-Assumptions!$E$7)^(7-1) -> 5725.1978 | K6: =Assumptions!$E$65*(1-Assumptions!$E$7)^(8-1) -> 5696.5718 | L6: =Assumptions!$E$65*(1-Assumptions!$E$7)^(9-1) -> 5668.089 | M6: =Assumptions!$E$65*(1-Assumptions!$E$7)^(10-1) -> 5639.7485 | N6: =Assumptions!$E$65*(1-Assumptions!$E$7)^(11-1) -> 5611.5498 | O6: =Assumptions!$E$65*(1-Assumptions!$E$7)^(12-1) -> 5583.492 | P6: =Assumptions!$E$65*(1-Assumptions!$E$7)^(13-1) -> 5555.5746 | Q6: =Assumptions!$E$65*(1-Assumptions!$E$7)^(14-1) -> 5527.7967 | R6: =Assumptions!$E$65*(1-Assumptions!$E$7)^(15-1) -> 5500.1577 | S6: =Assumptions!$E$65*(1-Assumptions!$E$7)^(16-1) -> 5472.6569 | T6: =Assumptions!$E$65*(1-Assumptions!$E$7)^(17-1) -> 5445.2936 | U6: =Assumptions!$E$65*(1-Assumptions!$E$7)^(18-1) -> 5418.0672 | V6: =Assumptions!$E$65*(1-Assumptions!$E$7)^(19-1) -> 5390.9768 | W6: =Assumptions!$E$65*(1-Assumptions!$E$7)^(20-1) -> 5364.0219 | X6: =Assumptions!$E$65*(1-Assumptions!$E$7)^(21-1) -> 5337.2018 | Y6: =Assumptions!$E$65*(1-Assumptions!$E$7)^(22-1) -> 5310.5158 | Z6: =Assumptions!$E$65*(1-Assumptions!$E$7)^(23-1) -> 5283.9632 | AA6: =Assumptions!$E$65*(1-Assumptions!$E$7)^(24-1) -> 5257.5434 | AB6: =Assumptions!$E$65*(1-Assumptions!$E$7)^(25-1) -> 5231.2557 | AC6: =Assumptions!$E$65*(1-Assumptions!$E$7)^(26-1) -> 5205.0994 | AD6: =Assumptions!$E$65*(1-Assumptions!$E$7)^(27-1) -> 5179.0739 | AE6: =Assumptions!$E$65*(1-Assumptions!$E$7)^(28-1) -> 5153.1786 | AF6: =Assumptions!$E$65*(1-Assumptions!$E$7)^(29-1) -> 5127.4127 | AG6: =Assumptions!$E$65*(1-Assumptions!$E$7)^(30-1) -> 5101.7756
A8: REVENUE
A9: PPA energy revenue | B9: € | C9: =0 -> 0 | D9: =IF(1<=Assumptions!$E$23,D6*Assumptions!$E$21*(1+Assumptions!$E$22)^(1-1),D6*Assumptions!$E$24) -> 389400 | E9: =IF(2<=Assumptions!$E$23,E6*Assumptions!$E$21*(1+Assumptions!$E$22)^(2-1),E6*Assumptions!$E$24) -> 395202.06 | F9: =IF(3<=Assumptions!$E$23,F6*Assumptions!$E$21*(1+Assumptions!$E$22)^(3-1),F6*Assumptions!$E$24) -> 401090.57 | G9: =IF(4<=Assumptions!$E$23,G6*Assumptions!$E$21*(1+Assumptions!$E$22)^(4-1),G6*Assumptions!$E$24) -> 407066.82 | H9: =IF(5<=Assumptions!$E$23,H6*Assumptions!$E$21*(1+Assumptions!$E$22)^(5-1),H6*Assumptions!$E$24) -> 413132.12 | I9: =IF(6<=Assumptions!$E$23,I6*Assumptions!$E$21*(1+Assumptions!$E$22)^(6-1),I6*Assumptions!$E$24) -> 419287.78 | J9: =IF(7<=Assumptions!$E$23,J6*Assumptions!$E$21*(1+Assumptions!$E$22)^(7-1),J6*Assumptions!$E$24) -> 425535.17 | K9: =IF(8<=Assumptions!$E$23,K6*Assumptions!$E$21*(1+Assumptions!$E$22)^(8-1),K6*Assumptions!$E$24) -> 431875.65 | L9: =IF(9<=Assumptions!$E$23,L6*Assumptions!$E$21*(1+Assumptions!$E$22)^(9-1),L6*Assumptions!$E$24) -> 438310.59 | M9: =IF(10<=Assumptions!$E$23,M6*Assumptions!$E$21*(1+Assumptions!$E$22)^(10-1),M6*Assumptions!$E$24) -> 444841.42 | N9: =IF(11<=Assumptions!$E$23,N6*Assumptions!$E$21*(1+Assumptions!$E$22)^(11-1),N6*Assumptions!$E$24) -> 451469.56 | O9: =IF(12<=Assumptions!$E$23,O6*Assumptions!$E$21*(1+Assumptions!$E$22)^(12-1),O6*Assumptions!$E$24) -> 458196.45 | P9: =IF(13<=Assumptions!$E$23,P6*Assumptions!$E$21*(1+Assumptions!$E$22)^(13-1),P6*Assumptions!$E$24) -> 465023.58 | Q9: =IF(14<=Assumptions!$E$23,Q6*Assumptions!$E$21*(1+Assumptions!$E$22)^(14-1),Q6*Assumptions!$E$24) -> 471952.43 | R9: =IF(15<=Assumptions!$E$23,R6*Assumptions!$E$21*(1+Assumptions!$E$22)^(15-1),R6*Assumptions!$E$24) -> 478984.52 | S9: =IF(16<=Assumptions!$E$23,S6*Assumptions!$E$21*(1+Assumptions!$E$22)^(16-1),S6*Assumptions!$E$24) -> 486121.39 | T9: =IF(17<=Assumptions!$E$23,T6*Assumptions!$E$21*(1+Assumptions!$E$22)^(17-1),T6*Assumptions!$E$24) -> 493364.6 | U9: =IF(18<=Assumptions!$E$23,U6*Assumptions!$E$21*(1+Assumptions!$E$22)^(18-1),U6*Assumptions!$E$24) -> 500715.74 | V9: =IF(19<=Assumptions!$E$23,V6*Assumptions!$E$21*(1+Assumptions!$E$22)^(19-1),V6*Assumptions!$E$24) -> 508176.4 | W9: =IF(20<=Assumptions!$E$23,W6*Assumptions!$E$21*(1+Assumptions!$E$22)^(20-1),W6*Assumptions!$E$24) -> 515748.23 | X9: =IF(21<=Assumptions!$E$23,X6*Assumptions!$E$21*(1+Assumptions!$E$22)^(21-1),X6*Assumptions!$E$24) -> 523432.88 | Y9: =IF(22<=Assumptions!$E$23,Y6*Assumptions!$E$21*(1+Assumptions!$E$22)^(22-1),Y6*Assumptions!$E$24) -> 531232.03 | Z9: =IF(23<=Assumptions!$E$23,Z6*Assumptions!$E$21*(1+Assumptions!$E$22)^(23-1),Z6*Assumptions!$E$24) -> 290617.98 | AA9: =IF(24<=Assumptions!$E$23,AA6*Assumptions!$E$21*(1+Assumptions!$E$22)^(24-1),AA6*Assumptions!$E$24) -> 289164.89 | AB9: =IF(25<=Assumptions!$E$23,AB6*Assumptions!$E$21*(1+Assumptions!$E$22)^(25-1),AB6*Assumptions!$E$24) -> 287719.06 | AC9: =IF(26<=Assumptions!$E$23,AC6*Assumptions!$E$21*(1+Assumptions!$E$22)^(26-1),AC6*Assumptions!$E$24) -> 286280.47 | AD9: =IF(27<=Assumptions!$E$23,AD6*Assumptions!$E$21*(1+Assumptions!$E$22)^(27-1),AD6*Assumptions!$E$24) -> 284849.07 | AE9: =IF(28<=Assumptions!$E$23,AE6*Assumptions!$E$21*(1+Assumptions!$E$22)^(28-1),AE6*Assumptions!$E$24) -> 283424.82 | AF9: =IF(29<=Assumptions!$E$23,AF6*Assumptions!$E$21*(1+Assumptions!$E$22)^(29-1),AF6*Assumptions!$E$24) -> 282007.7 | AG9: =IF(30<=Assumptions!$E$23,AG6*Assumptions!$E$21*(1+Assumptions!$E$22)^(30-1),AG6*Assumptions!$E$24) -> 280597.66
A10: Low-carbon attribute premium | B10: € | C10: =0 -> 0 | D10: =IF(1<=Assumptions!$E$23,D6*Assumptions!$E$27,0) -> 23600 | E10: =IF(2<=Assumptions!$E$23,E6*Assumptions!$E$27,0) -> 23482 | F10: =IF(3<=Assumptions!$E$23,F6*Assumptions!$E$27,0) -> 23364.59 | G10: =IF(4<=Assumptions!$E$23,G6*Assumptions!$E$27,0) -> 23247.767 | H10: =IF(5<=Assumptions!$E$23,H6*Assumptions!$E$27,0) -> 23131.528 | I10: =IF(6<=Assumptions!$E$23,I6*Assumptions!$E$27,0) -> 23015.871 | J10: =IF(7<=Assumptions!$E$23,J6*Assumptions!$E$27,0) -> 22900.791 | K10: =IF(8<=Assumptions!$E$23,K6*Assumptions!$E$27,0) -> 22786.287 | L10: =IF(9<=Assumptions!$E$23,L6*Assumptions!$E$27,0) -> 22672.356 | M10: =IF(10<=Assumptions!$E$23,M6*Assumptions!$E$27,0) -> 22558.994 | N10: =IF(11<=Assumptions!$E$23,N6*Assumptions!$E$27,0) -> 22446.199 | O10: =IF(12<=Assumptions!$E$23,O6*Assumptions!$E$27,0) -> 22333.968 | P10: =IF(13<=Assumptions!$E$23,P6*Assumptions!$E$27,0) -> 22222.298 | Q10: =IF(14<=Assumptions!$E$23,Q6*Assumptions!$E$27,0) -> 22111.187 | R10: =IF(15<=Assumptions!$E$23,R6*Assumptions!$E$27,0) -> 22000.631 | S10: =IF(16<=Assumptions!$E$23,S6*Assumptions!$E$27,0) -> 21890.628 | T10: =IF(17<=Assumptions!$E$23,T6*Assumptions!$E$27,0) -> 21781.175 | U10: =IF(18<=Assumptions!$E$23,U6*Assumptions!$E$27,0) -> 21672.269 | V10: =IF(19<=Assumptions!$E$23,V6*Assumptions!$E$27,0) -> 21563.907 | W10: =IF(20<=Assumptions!$E$23,W6*Assumptions!$E$27,0) -> 21456.088 | X10: =IF(21<=Assumptions!$E$23,X6*Assumptions!$E$27,0) -> 21348.807 | Y10: =IF(22<=Assumptions!$E$23,Y6*Assumptions!$E$27,0) -> 21242.063 | Z10: =IF(23<=Assumptions!$E$23,Z6*Assumptions!$E$27,0) -> 0 | AA10: =IF(24<=Assumptions!$E$23,AA6*Assumptions!$E$27,0) -> 0 | AB10: =IF(25<=Assumptions!$E$23,AB6*Assumptions!$E$27,0) -> 0 | AC10: =IF(26<=Assumptions!$E$23,AC6*Assumptions!$E$27,0) -> 0 | AD10: =IF(27<=Assumptions!$E$23,AD6*Assumptions!$E$27,0) -> 0 | AE10: =IF(28<=Assumptions!$E$23,AE6*Assumptions!$E$27,0) -> 0 | AF10: =IF(29<=Assumptions!$E$23,AF6*Assumptions!$E$27,0) -> 0 | AG10: =IF(30<=Assumptions!$E$23,AG6*Assumptions!$E$27,0) -> 0
A11: Agrivoltaic co-revenue / premium | B11: € | C11: =0 -> 0 | D11: =D6*Assumptions!$E$28 -> 11800 | E11: =E6*Assumptions!$E$28 -> 11741 | F11: =F6*Assumptions!$E$28 -> 11682.295 | G11: =G6*Assumptions!$E$28 -> 11623.884 | H11: =H6*Assumptions!$E$28 -> 11565.764 | I11: =I6*Assumptions!$E$28 -> 11507.935 | J11: =J6*Assumptions!$E$28 -> 11450.396 | K11: =K6*Assumptions!$E$28 -> 11393.144 | ... AG11: =AG6*Assumptions!$E$28 -> 10203.551
A12: Biodiversity credit revenue | B12: € | C12: =0 -> 0 | D12: =D6*Assumptions!$E$29 -> 4720 | E12: =E6*Assumptions!$E$29 -> 4696.4 | F12: =F6*Assumptions!$E$29 -> 4672.918 | G12: =G6*Assumptions!$E$29 -> 4649.5534 | H12: =H6*Assumptions!$E$29 -> 4626.3056 | I12: =I6*Assumptions!$E$29 -> 4603.1741 | J12: =J6*Assumptions!$E$29 -> 4580.1582 | K12: =K6*Assumptions!$E$29 -> 4557.2575 | ... AG12: =AG6*Assumptions!$E$29 -> 4081.4205
A13: DPP / data licensing | B13: € | C13: =0 -> 0 | D13: =D6*Assumptions!$E$30 -> 2950 | E13: =E6*Assumptions!$E$30 -> 2935.25 | F13: =F6*Assumptions!$E$30 -> 2920.5738 | G13: =G6*Assumptions!$E$30 -> 2905.9709 | H13: =H6*Assumptions!$E$30 -> 2891.441 | I13: =I6*Assumptions!$E$30 -> 2876.9838 | J13: =J6*Assumptions!$E$30 -> 2862.5989 | K13: =K6*Assumptions!$E$30 -> 2848.2859 | ... AG13: =AG6*Assumptions!$E$30 -> 2550.8878
A14: Community / energy-access grant | B14: € | C14: =0 -> 0 | D14: =Assumptions!$E$31 -> 12000 | E14: =Assumptions!$E$31 -> 12000 | F14: =Assumptions!$E$31 -> 12000 | G14: =Assumptions!$E$31 -> 12000 | H14: =Assumptions!$E$31 -> 12000 | I14: =Assumptions!$E$31 -> 12000 | J14: =Assumptions!$E$31 -> 12000 | K14: =Assumptions!$E$31 -> 12000 | ... AG14: =Assumptions!$E$31 -> 12000
A15: EOL material recovery (Year 30) | B15: € | C15: =0 -> 0 | D15: =0 -> 0 | E15: =0 -> 0 | F15: =0 -> 0 | G15: =0 -> 0 | H15: =0 -> 0 | I15: =0 -> 0 | J15: =0 -> 0 | ... AF15: =0 -> 0 | AG15: =Assumptions!$E$34*Assumptions!$E$5 -> 100000
A16: Total revenue | B16: € | C16: =SUM(C9:C15) -> 0 | D16: =SUM(D9:D15) -> 444470 | E16: =SUM(E9:E15) -> 450056.71 | F16: =SUM(F9:F15) -> 455730.95 | G16: =SUM(G9:G15) -> 461494 | H16: =SUM(H9:H15) -> 467347.15 | I16: =SUM(I9:I15) -> 473291.75 | J16: =SUM(J9:J15) -> 479329.12 | ... AG16: =SUM(AG9:AG15) -> 409433.52
A18: OPERATING COSTS
A19: O&M | B19: € | C19: =0 -> 0 | D19: =-Assumptions!$E$38*Assumptions!$E$5*(1+Assumptions!$E$39)^(1-1) -> -65000 | E19: =-Assumptions!$E$38*Assumptions!$E$5*(1+Assumptions!$E$39)^(2-1) -> -66300 | F19: =-Assumptions!$E$38*Assumptions!$E$5*(1+Assumptions!$E$39)^(3-1) -> -67626 | G19: =-Assumptions!$E$38*Assumptions!$E$5*(1+Assumptions!$E$39)^(4-1) -> -68978.52 | H19: =-Assumptions!$E$38*Assumptions!$E$5*(1+Assumptions!$E$39)^(5-1) -> -70358.09 | I19: =-Assumptions!$E$38*Assumptions!$E$5*(1+Assumptions!$E$39)^(6-1) -> -71765.252 | J19: =-Assumptions!$E$38*Assumptions!$E$5*(1+Assumptions!$E$39)^(7-1) -> -73200.557 | K19: =-Assumptions!$E$38*Assumptions!$E$5*(1+Assumptions!$E$39)^(8-1) -> -74664.568 | L19: =-Assumptions!$E$38*Assumptions!$E$5*(1+Assumptions!$E$39)^(9-1) -> -76157.86 | M19: =-Assumptions!$E$38*Assumptions!$E$5*(1+Assumptions!$E$39)^(10-1) -> -77681.017 | N19: =-Assumptions!$E$38*Assumptions!$E$5*(1+Assumptions!$E$39)^(11-1) -> -79234.637 | O19: =-Assumptions!$E$38*Assumptions!$E$5*(1+Assumptions!$E$39)^(12-1) -> -80819.33 | P19: =-Assumptions!$E$38*Assumptions!$E$5*(1+Assumptions!$E$39)^(13-1) -> -82435.717 | Q19: =-Assumptions!$E$38*Assumptions!$E$5*(1+Assumptions!$E$39)^(14-1) -> -84084.431 | R19: =-Assumptions!$E$38*Assumptions!$E$5*(1+Assumptions!$E$39)^(15-1) -> -85766.12 | S19: =-Assumptions!$E$38*Assumptions!$E$5*(1+Assumptions!$E$39)^(16-1) -> -87481.442 | T19: =-Assumptions!$E$38*Assumptions!$E$5*(1+Assumptions!$E$39)^(17-1) -> -89231.071 | U19: =-Assumptions!$E$38*Assumptions!$E$5*(1+Assumptions!$E$39)^(18-1) -> -91015.692 | V19: =-Assumptions!$E$38*Assumptions!$E$5*(1+Assumptions!$E$39)^(19-1) -> -92836.006 | W19: =-Assumptions!$E$38*Assumptions!$E$5*(1+Assumptions!$E$39)^(20-1) -> -94692.726 | X19: =-Assumptions!$E$38*Assumptions!$E$5*(1+Assumptions!$E$39)^(21-1) -> -96586.581 | Y19: =-Assumptions!$E$38*Assumptions!$E$5*(1+Assumptions!$E$39)^(22-1) -> -98518.312 | Z19: =-Assumptions!$E$38*Assumptions!$E$5*(1+Assumptions!$E$39)^(23-1) -> -100488.68 | AA19: =-Assumptions!$E$38*Assumptions!$E$5*(1+Assumptions!$E$39)^(24-1) -> -102498.45 | AB19: =-Assumptions!$E$38*Assumptions!$E$5*(1+Assumptions!$E$39)^(25-1) -> -104548.42 | AC19: =-Assumptions!$E$38*Assumptions!$E$5*(1+Assumptions!$E$39)^(26-1) -> -106639.39 | AD19: =-Assumptions!$E$38*Assumptions!$E$5*(1+Assumptions!$E$39)^(27-1) -> -108772.18 | AE19: =-Assumptions!$E$38*Assumptions!$E$5*(1+Assumptions!$E$39)^(28-1) -> -110947.62 | AF19: =-Assumptions!$E$38*Assumptions!$E$5*(1+Assumptions!$E$39)^(29-1) -> -113166.57 | AG19: =-Assumptions!$E$38*Assumptions!$E$5*(1+Assumptions!$E$39)^(30-1) -> -115429.9
A20: Land lease (net of agri uplift) | B20: € | C20: =0 -> 0 | D20: =-Assumptions!$E$40*Assumptions!$E$9*(1+Assumptions!$E$39)^(1-1) -> -12000 | E20: =-Assumptions!$E$40*Assumptions!$E$9*(1+Assumptions!$E$39)^(2-1) -> -12240 | F20: =-Assumptions!$E$40*Assumptions!$E$9*(1+Assumptions!$E$39)^(3-1) -> -12484.8 | G20: =-Assumptions!$E$40*Assumptions!$E$9*(1+Assumptions!$E$39)^(4-1) -> -12734.496 | H20: =-Assumptions!$E$40*Assumptions!$E$9*(1+Assumptions!$E$39)^(5-1) -> -12989.186 | I20: =-Assumptions!$E$40*Assumptions!$E$9*(1+Assumptions!$E$39)^(6-1) -> -13248.97 | J20: =-Assumptions!$E$40*Assumptions!$E$9*(1+Assumptions!$E$39)^(7-1) -> -13513.949 | K20: =-Assumptions!$E$40*Assumptions!$E$9*(1+Assumptions!$E$39)^(8-1) -> -13784.228 | L20: =-Assumptions!$E$40*Assumptions!$E$9*(1+Assumptions!$E$39)^(9-1) -> -14059.913 | M20: =-Assumptions!$E$40*Assumptions!$E$9*(1+Assumptions!$E$39)^(10-1) -> -14341.111 | N20: =-Assumptions!$E$40*Assumptions!$E$9*(1+Assumptions!$E$39)^(11-1) -> -14627.933 | O20: =-Assumptions!$E$40*Assumptions!$E$9*(1+Assumptions!$E$39)^(12-1) -> -14920.492 | P20: =-Assumptions!$E$40*Assumptions!$E$9*(1+Assumptions!$E$39)^(13-1) -> -15218.902 | Q20: =-Assumptions!$E$40*Assumptions!$E$9*(1+Assumptions!$E$39)^(14-1) -> -15523.28 | R20: =-Assumptions!$E$40*Assumptions!$E$9*(1+Assumptions!$E$39)^(15-1) -> -15833.745 | S20: =-Assumptions!$E$40*Assumptions!$E$9*(1+Assumptions!$E$39)^(16-1) -> -16150.42 | T20: =-Assumptions!$E$40*Assumptions!$E$9*(1+Assumptions!$E$39)^(17-1) -> -16473.428 | U20: =-Assumptions!$E$40*Assumptions!$E$9*(1+Assumptions!$E$39)^(18-1) -> -16802.897 | V20: =-Assumptions!$E$40*Assumptions!$E$9*(1+Assumptions!$E$39)^(19-1) -> -17138.955 | W20: =-Assumptions!$E$40*Assumptions!$E$9*(1+Assumptions!$E$39)^(20-1) -> -17481.734 | X20: =-Assumptions!$E$40*Assumptions!$E$9*(1+Assumptions!$E$39)^(21-1) -> -17831.369 | Y20: =-Assumptions!$E$40*Assumptions!$E$9*(1+Assumptions!$E$39)^(22-1) -> -18187.996 | Z20: =-Assumptions!$E$40*Assumptions!$E$9*(1+Assumptions!$E$39)^(23-1) -> -18551.756 | AA20: =-Assumptions!$E$40*Assumptions!$E$9*(1+Assumptions!$E$39)^(24-1) -> -18922.791 | AB20: =-Assumptions!$E$40*Assumptions!$E$9*(1+Assumptions!$E$39)^(25-1) -> -19301.247 | AC20: =-Assumptions!$E$40*Assumptions!$E$9*(1+Assumptions!$E$39)^(26-1) -> -19687.272 | AD20: =-Assumptions!$E$40*Assumptions!$E$9*(1+Assumptions!$E$39)^(27-1) -> -20081.017 | AE20: =-Assumptions!$E$40*Assumptions!$E$9*(1+Assumptions!$E$39)^(28-1) -> -20482.638 | AF20: =-Assumptions!$E$40*Assumptions!$E$9*(1+Assumptions!$E$39)^(29-1) -> -20892.29 | AG20: =-Assumptions!$E$40*Assumptions!$E$9*(1+Assumptions!$E$39)^(30-1) -> -21310.136
A21: Insurance | B21: € | C21: =0 -> 0 | D21: =-Assumptions!$E$41*Assumptions!$E$64 -> -16120 | E21: =-Assumptions!$E$41*Assumptions!$E$64 -> -16120 | F21: =-Assumptions!$E$41*Assumptions!$E$64 -> -16120 | G21: =-Assumptions!$E$41*Assumptions!$E$64 -> -16120 | H21: =-Assumptions!$E$41*Assumptions!$E$64 -> -16120 | I21: =-Assumptions!$E$41*Assumptions!$E$64 -> -16120 | J21: =-Assumptions!$E$41*Assumptions!$E$64 -> -16120 | K21: =-Assumptions!$E$41*Assumptions!$E$64 -> -16120 | ... AG21: =-Assumptions!$E$41*Assumptions!$E$64 -> -16120
A22: CSRD + DPP compliance | B22: € | C22: =0 -> 0 | D22: =-Assumptions!$E$42*(1+Assumptions!$E$39)^(1-1) -> -8000 | E22: =-Assumptions!$E$42*(1+Assumptions!$E$39)^(2-1) -> -8160 | F22: =-Assumptions!$E$42*(1+Assumptions!$E$39)^(3-1) -> -8323.2 | G22: =-Assumptions!$E$42*(1+Assumptions!$E$39)^(4-1) -> -8489.664 | H22: =-Assumptions!$E$42*(1+Assumptions!$E$39)^(5-1) -> -8659.4573 | I22: =-Assumptions!$E$42*(1+Assumptions!$E$39)^(6-1) -> -8832.6464 | J22: =-Assumptions!$E$42*(1+Assumptions!$E$39)^(7-1) -> -9009.2994 | K22: =-Assumptions!$E$42*(1+Assumptions!$E$39)^(8-1) -> -9189.4853 | L22: =-Assumptions!$E$42*(1+Assumptions!$E$39)^(9-1) -> -9373.275 | M22: =-Assumptions!$E$42*(1+Assumptions!$E$39)^(10-1) -> -9560.7405 | N22: =-Assumptions!$E$42*(1+Assumptions!$E$39)^(11-1) -> -9751.9554 | O22: =-Assumptions!$E$42*(1+Assumptions!$E$39)^(12-1) -> -9946.9945 | P22: =-Assumptions!$E$42*(1+Assumptions!$E$39)^(13-1) -> -10145.934 | Q22: =-Assumptions!$E$42*(1+Assumptions!$E$39)^(14-1) -> -10348.853 | R22: =-Assumptions!$E$42*(1+Assumptions!$E$39)^(15-1) -> -10555.83 | S22: =-Assumptions!$E$42*(1+Assumptions!$E$39)^(16-1) -> -10766.947 | T22: =-Assumptions!$E$42*(1+Assumptions!$E$39)^(17-1) -> -10982.286 | U22: =-Assumptions!$E$42*(1+Assumptions!$E$39)^(18-1) -> -11201.931 | V22: =-Assumptions!$E$42*(1+Assumptions!$E$39)^(19-1) -> -11425.97 | W22: =-Assumptions!$E$42*(1+Assumptions!$E$39)^(20-1) -> -11654.489 | X22: =-Assumptions!$E$42*(1+Assumptions!$E$39)^(21-1) -> -11887.579 | Y22: =-Assumptions!$E$42*(1+Assumptions!$E$39)^(22-1) -> -12125.331 | Z22: =-Assumptions!$E$42*(1+Assumptions!$E$39)^(23-1) -> -12367.837 | AA22: =-Assumptions!$E$42*(1+Assumptions!$E$39)^(24-1) -> -12615.194 | AB22: =-Assumptions!$E$42*(1+Assumptions!$E$39)^(25-1) -> -12867.498 | AC22: =-Assumptions!$E$42*(1+Assumptions!$E$39)^(26-1) -> -13124.848 | AD22: =-Assumptions!$E$42*(1+Assumptions!$E$39)^(27-1) -> -13387.345 | AE22: =-Assumptions!$E$42*(1+Assumptions!$E$39)^(28-1) -> -13655.092 | AF22: =-Assumptions!$E$42*(1+Assumptions!$E$39)^(29-1) -> -13928.194 | AG22: =-Assumptions!$E$42*(1+Assumptions!$E$39)^(30-1) -> -14206.758
A23: Community governance | B23: € | C23: =0 -> 0 | D23: =-Assumptions!$E$43*(1+Assumptions!$E$39)^(1-1) -> -6000 | E23: =-Assumptions!$E$43*(1+Assumptions!$E$39)^(2-1) -> -6120 | F23: =-Assumptions!$E$43*(1+Assumptions!$E$39)^(3-1) -> -6242.4 | G23: =-Assumptions!$E$43*(1+Assumptions!$E$39)^(4-1) -> -6367.248 | H23: =-Assumptions!$E$43*(1+Assumptions!$E$39)^(5-1) -> -6494.593 | I23: =-Assumptions!$E$43*(1+Assumptions!$E$39)^(6-1) -> -6624.4848 | J23: =-Assumptions!$E$43*(1+Assumptions!$E$39)^(7-1) -> -6756.9745 | K23: =-Assumptions!$E$43*(1+Assumptions!$E$39)^(8-1) -> -6892.114 | L23: =-Assumptions!$E$43*(1+Assumptions!$E$39)^(9-1) -> -7029.9563 | M23: =-Assumptions!$E$43*(1+Assumptions!$E$39)^(10-1) -> -7170.5554 | N23: =-Assumptions!$E$43*(1+Assumptions!$E$39)^(11-1) -> -7313.9665 | O23: =-Assumptions!$E$43*(1+Assumptions!$E$39)^(12-1) -> -7460.2459 | P23: =-Assumptions!$E$43*(1+Assumptions!$E$39)^(13-1) -> -7609.4508 | Q23: =-Assumptions!$E$43*(1+Assumptions!$E$39)^(14-1) -> -7761.6398 | R23: =-Assumptions!$E$43*(1+Assumptions!$E$39)^(15-1) -> -7916.8726 | S23: =-Assumptions!$E$43*(1+Assumptions!$E$39)^(16-1) -> -8075.21 | T23: =-Assumptions!$E$43*(1+Assumptions!$E$39)^(17-1) -> -8236.7142 | U23: =-Assumptions!$E$43*(1+Assumptions!$E$39)^(18-1) -> -8401.4485 | V23: =-Assumptions!$E$43*(1+Assumptions!$E$39)^(19-1) -> -8569.4775 | W23: =-Assumptions!$E$43*(1+Assumptions!$E$39)^(20-1) -> -8740.867 | X23: =-Assumptions!$E$43*(1+Assumptions!$E$39)^(21-1) -> -8915.6844 | Y23: =-Assumptions!$E$43*(1+Assumptions!$E$39)^(22-1) -> -9093.9981 | Z23: =-Assumptions!$E$43*(1+Assumptions!$E$39)^(23-1) -> -9275.878 | AA23: =-Assumptions!$E$43*(1+Assumptions!$E$39)^(24-1) -> -9461.3956 | AB23: =-Assumptions!$E$43*(1+Assumptions!$E$39)^(25-1) -> -9650.6235 | AC23: =-Assumptions!$E$43*(1+Assumptions!$E$39)^(26-1) -> -9843.636 | AD23: =-Assumptions!$E$43*(1+Assumptions!$E$39)^(27-1) -> -10040.509 | AE23: =-Assumptions!$E$43*(1+Assumptions!$E$39)^(28-1) -> -10241.319 | AF23: =-Assumptions!$E$43*(1+Assumptions!$E$39)^(29-1) -> -10446.145 | AG23: =-Assumptions!$E$43*(1+Assumptions!$E$39)^(30-1) -> -10655.068
A24: EOL reserve contribution | B24: € | C24: =0 -> 0 | D24: =-D6*Assumptions!$E$44 -> -11800 | E24: =-E6*Assumptions!$E$44 -> -11741 | F24: =-F6*Assumptions!$E$44 -> -11682.295 | G24: =-G6*Assumptions!$E$44 -> -11623.884 | H24: =-H6*Assumptions!$E$44 -> -11565.764 | I24: =-I6*Assumptions!$E$44 -> -11507.935 | J24: =-J6*Assumptions!$E$44 -> -11450.396 | K24: =-K6*Assumptions!$E$44 -> -11393.144 | ... AG24: =-AG6*Assumptions!$E$44 -> -10203.551
A25: Decommissioning (Year 30) | B25: € | C25: =0 -> 0 | D25: =0 -> 0 | E25: =0 -> 0 | F25: =0 -> 0 | G25: =0 -> 0 | H25: =0 -> 0 | I25: =0 -> 0 | J25: =0 -> 0 | ... AF25: =0 -> 0 | AG25: =-Assumptions!$E$35*Assumptions!$E$5 -> -90000
A26: Total operating costs | B26: € | C26: =SUM(C19:C25) -> 0 | D26: =SUM(D19:D25) -> -118920 | E26: =SUM(E19:E25) -> -120681 | F26: =SUM(F19:F25) -> -122478.7 | G26: =SUM(G19:G25) -> -124313.81 | H26: =SUM(H19:H25) -> -126187.09 | I26: =SUM(I19:I25) -> -128099.29 | J26: =SUM(J19:J25) -> -130051.18 | ... AG26: =SUM(AG19:AG25) -> -277925.42
A28: EBITDA | B28: € | C28: =C16+C26 -> 0 | D28: =D16+D26 -> 325550 | E28: =E16+E26 -> 329375.71 | F28: =F16+F26 -> 333252.25 | G28: =G16+G26 -> 337180.18 | H28: =H16+H26 -> 341160.06 | I28: =I16+I26 -> 345192.46 | J28: =J16+J26 -> 349277.94 | ... AG28: =AG16+AG26 -> 131508.1
A30: DEPRECIATION, INTEREST, TAX
A31: Depreciation (straight-line) | B31: € | C31: =0 -> 0 | D31: =IF(1<=Assumptions!$E$54,-Assumptions!$E$64/Assumptions!$E$54,0) -> -128960 | E31: =IF(2<=Assumptions!$E$54,-Assumptions!$E$64/Assumptions!$E$54,0) -> -128960 | F31: =IF(3<=Assumptions!$E$54,-Assumptions!$E$64/Assumptions!$E$54,0) -> -128960 | G31: =IF(4<=Assumptions!$E$54,-Assumptions!$E$64/Assumptions!$E$54,0) -> -128960 | H31: =IF(5<=Assumptions!$E$54,-Assumptions!$E$64/Assumptions!$E$54,0) -> -128960 | I31: =IF(6<=Assumptions!$E$54,-Assumptions!$E$64/Assumptions!$E$54,0) -> -128960 | J31: =IF(7<=Assumptions!$E$54,-Assumptions!$E$64/Assumptions!$E$54,0) -> -128960 | K31: =IF(8<=Assumptions!$E$54,-Assumptions!$E$64/Assumptions!$E$54,0) -> -128960 | L31: =IF(9<=Assumptions!$E$54,-Assumptions!$E$64/Assumptions!$E$54,0) -> -128960 | M31: =IF(10<=Assumptions!$E$54,-Assumptions!$E$64/Assumptions!$E$54,0) -> -128960 | N31: =IF(11<=Assumptions!$E$54,-Assumptions!$E$64/Assumptions!$E$54,0) -> -128960 | O31: =IF(12<=Assumptions!$E$54,-Assumptions!$E$64/Assumptions!$E$54,0) -> -128960 | P31: =IF(13<=Assumptions!$E$54,-Assumptions!$E$64/Assumptions!$E$54,0) -> -128960 | Q31: =IF(14<=Assumptions!$E$54,-Assumptions!$E$64/Assumptions!$E$54,0) -> -128960 | R31: =IF(15<=Assumptions!$E$54,-Assumptions!$E$64/Assumptions!$E$54,0) -> -128960 | S31: =IF(16<=Assumptions!$E$54,-Assumptions!$E$64/Assumptions!$E$54,0) -> -128960 | T31: =IF(17<=Assumptions!$E$54,-Assumptions!$E$64/Assumptions!$E$54,0) -> -128960 | U31: =IF(18<=Assumptions!$E$54,-Assumptions!$E$64/Assumptions!$E$54,0) -> -128960 | V31: =IF(19<=Assumptions!$E$54,-Assumptions!$E$64/Assumptions!$E$54,0) -> -128960 | W31: =IF(20<=Assumptions!$E$54,-Assumptions!$E$64/Assumptions!$E$54,0) -> -128960 | X31: =IF(21<=Assumptions!$E$54,-Assumptions!$E$64/Assumptions!$E$54,0) -> -128960 | Y31: =IF(22<=Assumptions!$E$54,-Assumptions!$E$64/Assumptions!$E$54,0) -> -128960 | Z31: =IF(23<=Assumptions!$E$54,-Assumptions!$E$64/Assumptions!$E$54,0) -> -128960 | AA31: =IF(24<=Assumptions!$E$54,-Assumptions!$E$64/Assumptions!$E$54,0) -> -128960 | AB31: =IF(25<=Assumptions!$E$54,-Assumptions!$E$64/Assumptions!$E$54,0) -> -128960 | AC31: =IF(26<=Assumptions!$E$54,-Assumptions!$E$64/Assumptions!$E$54,0) -> 0 | AD31: =IF(27<=Assumptions!$E$54,-Assumptions!$E$64/Assumptions!$E$54,0) -> 0 | AE31: =IF(28<=Assumptions!$E$54,-Assumptions!$E$64/Assumptions!$E$54,0) -> 0 | AF31: =IF(29<=Assumptions!$E$54,-Assumptions!$E$64/Assumptions!$E$54,0) -> 0 | AG31: =IF(30<=Assumptions!$E$54,-Assumptions!$E$64/Assumptions!$E$54,0) -> 0
A32: Debt opening balance | B32: € | C32: =0 -> 0 | D32: =Assumptions!$E$66 -> 2095600 | E32: =D35 -> 2037875.3 | F32: =E35 -> 1977553.1 | G32: =F35 -> 1914516.3 | H32: =G35 -> 1848642.9 | I32: =H35 -> 1779805.2 | J32: =I35 -> 1707869.7 | K32: =J35 -> 1632697.2 | L32: =K35 -> 1554141.9 | ... AG32: =AF35 -> 6.1118044e-10
A33: Interest expense | B33: € | C33: =0 -> 0 | D33: =-D32*Assumptions!$E$48 -> -94302 | E33: =-E32*Assumptions!$E$48 -> -91704.39 | F33: =-F32*Assumptions!$E$48 -> -88989.889 | G33: =-G32*Assumptions!$E$48 -> -86153.234 | H33: =-H32*Assumptions!$E$48 -> -83188.93 | I33: =-I32*Assumptions!$E$48 -> -80091.232 | J33: =-J32*Assumptions!$E$48 -> -76854.138 | K33: =-K32*Assumptions!$E$48 -> -73471.375 | ... AG33: =-AG32*Assumptions!$E$48 -> -2.750312e-11
A34: Principal repayment | B34: € | C34: =0 -> 0 | D34: =IF(AND(1<=Assumptions!$E$49,D32>0),-(PMT(Assumptions!$E$48,Assumptions!$E$49,-Assumptions!$E$66)-(-D33)),0) -> -57724.656 | E34: =IF(AND(2<=Assumptions!$E$49,E32>0),-(PMT(Assumptions!$E$48,Assumptions!$E$49,-Assumptions!$E$66)-(-E33)),0) -> -60322.265 | F34: =IF(AND(3<=Assumptions!$E$49,F32>0),-(PMT(Assumptions!$E$48,Assumptions!$E$49,-Assumptions!$E$66)-(-F33)),0) -> -63036.767 | G34: =IF(AND(4<=Assumptions!$E$49,G32>0),-(PMT(Assumptions!$E$48,Assumptions!$E$49,-Assumptions!$E$66)-(-G33)),0) -> -65873.422 | H34: =IF(AND(5<=Assumptions!$E$49,H32>0),-(PMT(Assumptions!$E$48,Assumptions!$E$49,-Assumptions!$E$66)-(-H33)),0) -> -68837.726 | I34: =IF(AND(6<=Assumptions!$E$49,I32>0),-(PMT(Assumptions!$E$48,Assumptions!$E$49,-Assumptions!$E$66)-(-I33)),0) -> -71935.424 | J34: =IF(AND(7<=Assumptions!$E$49,J32>0),-(PMT(Assumptions!$E$48,Assumptions!$E$49,-Assumptions!$E$66)-(-J33)),0) -> -75172.518 | K34: =IF(AND(8<=Assumptions!$E$49,K32>0),-(PMT(Assumptions!$E$48,Assumptions!$E$49,-Assumptions!$E$66)-(-K33)),0) -> -78555.281 | L34: =IF(AND(9<=Assumptions!$E$49,L32>0),-(PMT(Assumptions!$E$48,Assumptions!$E$49,-Assumptions!$E$66)-(-L33)),0) -> -82090.269 | M34: =IF(AND(10<=Assumptions!$E$49,M32>0),-(PMT(Assumptions!$E$48,Assumptions!$E$49,-Assumptions!$E$66)-(-M33)),0) -> -85784.331 | N34: =IF(AND(11<=Assumptions!$E$49,N32>0),-(PMT(Assumptions!$E$48,Assumptions!$E$49,-Assumptions!$E$66)-(-N33)),0) -> -89644.625 | O34: =IF(AND(12<=Assumptions!$E$49,O32>0),-(PMT(Assumptions!$E$48,Assumptions!$E$49,-Assumptions!$E$66)-(-O33)),0) -> -93678.634 | P34: =IF(AND(13<=Assumptions!$E$49,P32>0),-(PMT(Assumptions!$E$48,Assumptions!$E$49,-Assumptions!$E$66)-(-P33)),0) -> -97894.172 | Q34: =IF(AND(14<=Assumptions!$E$49,Q32>0),-(PMT(Assumptions!$E$48,Assumptions!$E$49,-Assumptions!$E$66)-(-Q33)),0) -> -102299.41 | R34: =IF(AND(15<=Assumptions!$E$49,R32>0),-(PMT(Assumptions!$E$48,Assumptions!$E$49,-Assumptions!$E$66)-(-R33)),0) -> -106902.88 | S34: =IF(AND(16<=Assumptions!$E$49,S32>0),-(PMT(Assumptions!$E$48,Assumptions!$E$49,-Assumptions!$E$66)-(-S33)),0) -> -111713.51 | T34: =IF(AND(17<=Assumptions!$E$49,T32>0),-(PMT(Assumptions!$E$48,Assumptions!$E$49,-Assumptions!$E$66)-(-T33)),0) -> -116740.62 | U34: =IF(AND(18<=Assumptions!$E$49,U32>0),-(PMT(Assumptions!$E$48,Assumptions!$E$49,-Assumptions!$E$66)-(-U33)),0) -> -121993.95 | V34: =IF(AND(19<=Assumptions!$E$49,V32>0),-(PMT(Assumptions!$E$48,Assumptions!$E$49,-Assumptions!$E$66)-(-V33)),0) -> -127483.68 | W34: =IF(AND(20<=Assumptions!$E$49,W32>0),-(PMT(Assumptions!$E$48,Assumptions!$E$49,-Assumptions!$E$66)-(-W33)),0) -> -133220.44 | X34: =IF(AND(21<=Assumptions!$E$49,X32>0),-(PMT(Assumptions!$E$48,Assumptions!$E$49,-Assumptions!$E$66)-(-X33)),0) -> -139215.36 | Y34: =IF(AND(22<=Assumptions!$E$49,Y32>0),-(PMT(Assumptions!$E$48,Assumptions!$E$49,-Assumptions!$E$66)-(-Y33)),0) -> -145480.05 | Z34: =IF(AND(23<=Assumptions!$E$49,Z32>0),-(PMT(Assumptions!$E$48,Assumptions!$E$49,-Assumptions!$E$66)-(-Z33)),0) -> 0 | AA34: =IF(AND(24<=Assumptions!$E$49,AA32>0),-(PMT(Assumptions!$E$48,Assumptions!$E$49,-Assumptions!$E$66)-(-AA33)),0) -> 0 | AB34: =IF(AND(25<=Assumptions!$E$49,AB32>0),-(PMT(Assumptions!$E$48,Assumptions!$E$49,-Assumptions!$E$66)-(-AB33)),0) -> 0 | AC34: =IF(AND(26<=Assumptions!$E$49,AC32>0),-(PMT(Assumptions!$E$48,Assumptions!$E$49,-Assumptions!$E$66)-(-AC33)),0) -> 0 | AD34: =IF(AND(27<=Assumptions!$E$49,AD32>0),-(PMT(Assumptions!$E$48,Assumptions!$E$49,-Assumptions!$E$66)-(-AD33)),0) -> 0 | AE34: =IF(AND(28<=Assumptions!$E$49,AE32>0),-(PMT(Assumptions!$E$48,Assumptions!$E$49,-Assumptions!$E$66)-(-AE33)),0) -> 0 | AF34: =IF(AND(29<=Assumptions!$E$49,AF32>0),-(PMT(Assumptions!$E$48,Assumptions!$E$49,-Assumptions!$E$66)-(-AF33)),0) -> 0 | AG34: =IF(AND(30<=Assumptions!$E$49,AG32>0),-(PMT(Assumptions!$E$48,Assumptions!$E$49,-Assumptions!$E$66)-(-AG33)),0) -> 0
A35: Debt closing balance | B35: € | C35: =0 -> 0 | D35: =D32+D34 -> 2037875.3 | E35: =E32+E34 -> 1977553.1 | F35: =F32+F34 -> 1914516.3 | G35: =G32+G34 -> 1848642.9 | H35: =H32+H34 -> 1779805.2 | I35: =I32+I34 -> 1707869.7 | J35: =J32+J34 -> 1632697.2 | K35: =K32+K34 -> 1554141.9 | ... AG35: =AG32+AG34 -> 6.1118044e-10
A37: EBT (Earnings before tax) | B37: € | C37: =0 -> 0 | D37: =D28+D31+D33 -> 102288 | E37: =E28+E31+E33 -> 108711.32 | F37: =F28+F31+F33 -> 115302.36 | G37: =G28+G31+G33 -> 122066.95 | H37: =H28+H31+H33 -> 129011.13 | I37: =I28+I31+I33 -> 136141.23 | J37: =J28+J31+J33 -> 143463.8 | K37: =K28+K31+K33 -> 150985.71 | ... AG37: =AG28+AG31+AG33 -> 131508.1
A38: Tax (only on positive EBT) | B38: € | C38: =0 -> 0 | D38: =-MAX(0,D37)*Assumptions!$E$55 -> -25572 | E38: =-MAX(0,E37)*Assumptions!$E$55 -> -27177.83 | F38: =-MAX(0,F37)*Assumptions!$E$55 -> -28825.591 | G38: =-MAX(0,G37)*Assumptions!$E$55 -> -30516.737 | H38: =-MAX(0,H37)*Assumptions!$E$55 -> -32252.784 | I38: =-MAX(0,I37)*Assumptions!$E$55 -> -34035.307 | J38: =-MAX(0,J37)*Assumptions!$E$55 -> -35865.951 | K38: =-MAX(0,K37)*Assumptions!$E$55 -> -37746.427 | ... AG38: =-MAX(0,AG37)*Assumptions!$E$55 -> -32877.025
A39: Net income | B39: € | C39: =0 -> 0 | D39: =D37+D38 -> 76716 | E39: =E37+E38 -> 81533.49 | F39: =F37+F38 -> 86476.773 | G39: =G37+G38 -> 91550.212 | H39: =H37+H38 -> 96758.351 | I39: =I37+I38 -> 102105.92 | J39: =J37+J38 -> 107597.85 | K39: =K37+K38 -> 113239.28 | ... AG39: =AG37+AG38 -> 98631.075
A41: CASHFLOW SUMMARY
A42: CFADS (after-tax, pre-debt) | B42: € | C42: =0 -> 0 | D42: =D28+D38 -> 299978 | E42: =E28+E38 -> 302197.88 | F42: =F28+F38 -> 304426.66 | G42: =G28+G38 -> 306663.45 | H42: =H28+H38 -> 308907.28 | I42: =I28+I38 -> 311157.15 | J42: =J28+J38 -> 313411.99 | K42: =K28+K38 -> 315670.65 | ... AG42: =AG28+AG38 -> 98631.075
A43: DSCR (CFADS / debt service) | B43: x | C43: =0 -> 0 | D43: =IFERROR(IF((D33+D34)=0,0,D42/(-(D33+D34))),0) -> 1.9731934 | E43: =IFERROR(IF((E33+E34)=0,0,E42/(-(E33+E34))),0) -> 1.9877954 | F43: =IFERROR(IF((F33+F34)=0,0,F42/(-(F33+F34))),0) -> 2.0024558 | G43: =IFERROR(IF((G33+G34)=0,0,G42/(-(G33+G34))),0) -> 2.0171689 | H43: =IFERROR(IF((H33+H34)=0,0,H42/(-(H33+H34))),0) -> 2.0319284 | I43: =IFERROR(IF((I33+I34)=0,0,I42/(-(I33+I34))),0) -> 2.0467276 | J43: =IFERROR(IF((J33+J34)=0,0,J42/(-(J33+J34))),0) -> 2.0615595 | K43: =IFERROR(IF((K33+K34)=0,0,K42/(-(K33+K34))),0) -> 2.0764165 | ... AG43: =IFERROR(IF((AG33+AG34)=0,0,AG42/(-(AG33+AG34))),0) -> 3.5861777e+15
A45: CAPEX | B45: € | C45: =-Assumptions!$E$64 -> -3224000 | D45: =0 -> 0 | E45: =0 -> 0 | F45: =0 -> 0 | G45: =0 -> 0 | H45: =0 -> 0 | I45: =0 -> 0 | J45: =0 -> 0 | K45: =0 -> 0 | ... AG45: =0 -> 0
A46: Project FCF (unlevered, post-tax) | B46: € | C46: =C45 -> -3224000 | D46: =D28-MAX(0,D28+D31)*Assumptions!$E$55 -> 276402.5 | E46: =E28-MAX(0,E28+E31)*Assumptions!$E$55 -> 279271.78 | F46: =F28-MAX(0,F28+F31)*Assumptions!$E$55 -> 282179.19 | G46: =G28-MAX(0,G28+G31)*Assumptions!$E$55 -> 285125.14 | H46: =H28-MAX(0,H28+H31)*Assumptions!$E$55 -> 288110.05 | I46: =I28-MAX(0,I28+I31)*Assumptions!$E$55 -> 291134.34 | J46: =J28-MAX(0,J28+J31)*Assumptions!$E$55 -> 294198.46 | K46: =K28-MAX(0,K28+K31)*Assumptions!$E$55 -> 297302.81 | ... AG46: =AG28-MAX(0,AG28+AG31)*Assumptions!$E$55 -> 98631.075
A47: Equity FCF (levered, post-tax) | B47: € | C47: =-(Assumptions!$E$67+Assumptions!$E$68) -> -1128400 | D47: =D39-D31+D34 -> 147951.34 | E47: =E39-E31+E34 -> 150171.22 | F47: =F39-F31+F34 -> 152400.01 | G47: =G39-G31+G34 -> 154636.79 | H47: =H39-H31+H34 -> 156880.62 | I47: =I39-I31+I34 -> 159130.5 | J47: =J39-J31+J34 -> 161385.33 | K47: =K39-K31+K34 -> 163644 | ... AG47: =AG39-AG31+AG34 -> 98631.075
A48: Cumulative project FCF | B48: € | C48: =C46 -> -3224000 | D48: =C48+D46 -> -2947597.5 | E48: =D48+E46 -> -2668325.7 | F48: =E48+F46 -> -2386146.5 | G48: =F48+G46 -> -2101021.4 | H48: =G48+H46 -> -1812911.3 | I48: =H48+I46 -> -1521777 | J48: =I48+J46 -> -1227578.5 | K48: =J48+K46 -> -930275.73 | ... AG48: =AF48+AG46 -> 4509394.9
A49: Cumulative discounted FCF (@ disc_mid) | B49: € | C49: =C46 -> -3224000 | D49: =C49+D46/(1+Assumptions!$E$59)^1 -> -2968071.8 | E49: =D49+E46/(1+Assumptions!$E$59)^2 -> -2728641.2 | F49: =E49+F46/(1+Assumptions!$E$59)^3 -> -2504638.3 | G49: =F49+G46/(1+Assumptions!$E$59)^4 -> -2295062.8 | H49: =G49+H46/(1+Assumptions!$E$59)^5 -> -2098979.9 | I49: =H49+I46/(1+Assumptions!$E$59)^6 -> -1915515.9 | J49: =I49+J46/(1+Assumptions!$E$59)^7 -> -1743853.9 | K49: =J49+K46/(1+Assumptions!$E$59)^8 -> -1583230.5 | L49: =K49+L46/(1+Assumptions!$E$59)^9 -> -1432931.8 | M49: =L49+M46/(1+Assumptions!$E$59)^10 -> -1292290.5 | N49: =M49+N46/(1+Assumptions!$E$59)^11 -> -1160682.7 | O49: =N49+O46/(1+Assumptions!$E$59)^12 -> -1037525.3 | P49: =O49+P46/(1+Assumptions!$E$59)^13 -> -922272.72 | Q49: =P49+Q46/(1+Assumptions!$E$59)^14 -> -814415.12 | R49: =Q49+R46/(1+Assumptions!$E$59)^15 -> -713475.64 | S49: =R49+S46/(1+Assumptions!$E$59)^16 -> -619008.4 | T49: =S49+T46/(1+Assumptions!$E$59)^17 -> -530596.44 | U49: =T49+U46/(1+Assumptions!$E$59)^18 -> -447849.81 | V49: =U49+V46/(1+Assumptions!$E$59)^19 -> -370403.85 | W49: =V49+W46/(1+Assumptions!$E$59)^20 -> -297917.49 | X49: =W49+X46/(1+Assumptions!$E$59)^21 -> -230071.76 | Y49: =X49+Y46/(1+Assumptions!$E$59)^22 -> -166568.31 | Z49: =Y49+Z46/(1+Assumptions!$E$59)^23 -> -141574.16 | AA49: =Z49+AA46/(1+Assumptions!$E$59)^24 -> -118940.14 | AB49: =AA49+AB46/(1+Assumptions!$E$59)^25 -> -98459.095 | AC49: =AB49+AC46/(1+Assumptions!$E$59)^26 -> -84300.23 | AD49: =AC49+AD46/(1+Assumptions!$E$59)^27 -> -71608.088 | AE49: =AD49+AE46/(1+Assumptions!$E$59)^28 -> -60247.621 | AF49: =AE49+AF46/(1+Assumptions!$E$59)^29 -> -50095.5 | AG49: =AF49+AG46/(1+Assumptions!$E$59)^30 -> -40293.807

Sheet KPIs
A1: Key Performance Indicators — all three scenarios
A3: KPI | B3: Unit | C3: Conventional | D3: Regenerative | E3: Future | F3: Target / Comment
A4: PROFITABILITY METRICS
A5: Equity IRR | B5: % | C5: =IRR(CF_Conv!C47:AG47) -> 0.12116041 | D5: =IRR(CF_Regen!C47:AG47) -> 0.096126531 | E5: =IRR(CF_Future!C47:AG47) -> 0.13858309 | F5: Target ≥ 8% for parity; ≥ 10% premium
A6: Project IRR (unlevered, post-tax) | B6: % | C6: =IRR(CF_Conv!C46:AG46) -> 0.079082299 | D6: =IRR(CF_Regen!C46:AG46) -> 0.06364231 | E6: =IRR(CF_Future!C46:AG46) -> 0.078588175 | F6: Reflects asset-level economics
A7: NPV — Project FCF
A8: NPV at 5% | B8: € | C8: =NPV(Assumptions!$C$58,CF_Conv!D46:AG46)+CF_Conv!C46 -> 803711.26 | D8: =NPV(Assumptions!$D$58,CF_Regen!D46:AG46)+CF_Regen!C46 -> 445545.77 | E8: =NPV(Assumptions!$E$58,CF_Future!D46:AG46)+CF_Future!C46 -> 1026316.1 | F8: EU taxonomy / sovereign discount
A9: NPV at 8% | B9: € | C9: =NPV(Assumptions!$C$59,CF_Conv!D46:AG46)+CF_Conv!C46 -> -20553.815 | D9: =NPV(Assumptions!$D$59,CF_Regen!D46:AG46)+CF_Regen!C46 -> -431792.86 | E9: =NPV(Assumptions!$E$59,CF_Future!D46:AG46)+CF_Future!C46 -> -40293.807 | F9: Conventional project hurdle
A10: NPV at 10% | B10: € | C10: =NPV(Assumptions!$C$60,CF_Conv!D46:AG46)+CF_Conv!C46 -> -413792.93 | D10: =NPV(Assumptions!$D$60,CF_Regen!D46:AG46)+CF_Regen!C46 -> -845731.09 | E10: =NPV(Assumptions!$E$60,CF_Future!D46:AG46)+CF_Future!C46 -> -533658.62 | F10: Sponsor / stress view
A12: UNIT ECONOMICS
A13: LCOE (energy-only, real) | B13: €/MWh | C13: =(-CF_Conv!C45-NPV(Assumptions!$C$59,CF_Conv!D26:AG26))/NPV(Assumptions!$C$59,CF_Conv!D6:AG6) -> 61.538466 | D13: =(-CF_Regen!C45-NPV(Assumptions!$D$59,CF_Regen!D26:AG26))/NPV(Assumptions!$D$59,CF_Regen!D6:AG6) -> 75.898934 | E13: =(-CF_Future!C45-NPV(Assumptions!$E$59,CF_Future!D26:AG26))/NPV(Assumptions!$E$59,CF_Future!D6:AG6) -> 75.382216 | F13: Conventional benchmark
A14: LVOE (all revenue streams, real) | B14: €/MWh | C14: =(NPV(Assumptions!$C$59,CF_Conv!D16:AG16)+CF_Conv!C16)/NPV(Assumptions!$C$59,CF_Conv!D6:AG6) -> 69.326184 | D14: =(NPV(Assumptions!$D$59,CF_Regen!D16:AG16)+CF_Regen!C16)/NPV(Assumptions!$D$59,CF_Regen!D6:AG6) -> 76.61713 | E14: =(NPV(Assumptions!$E$59,CF_Future!D16:AG16)+CF_Future!C16)/NPV(Assumptions!$E$59,CF_Future!D6:AG6) -> 84.236914 | F14: Should exceed LCOE
A15: LVOE – LCOE spread (margin per MWh) | B15: €/MWh | C15: =C14-C13 -> 7.7877181 | D15: =D14-D13 -> 0.71819607 | E15: =E14-E13 -> 8.8546982 | F15: Positive = project creates value above cost
A17: LIQUIDITY & RISK
A18: Simple payback (project) | B18: yr | C18: =IFERROR(MATCH(TRUE(),CF_Conv!D48:AG48>0,0),"") -> 10 | D18: =IFERROR(MATCH(TRUE(),CF_Regen!D48:AG48>0,0),"") -> 13 | E18: =IFERROR(MATCH(TRUE(),CF_Future!D48:AG48>0,0),"") -> 12 | F18: Years until cumulative FCF > 0
A19: Discounted payback (@ 8%) | B19: yr | C19: =IFERROR(MATCH(TRUE(),CF_Conv!D49:AG49>0,0),"") | D19: =IFERROR(MATCH(TRUE(),CF_Regen!D49:AG49>0,0),"") | E19: =IFERROR(MATCH(TRUE(),CF_Future!D49:AG49>0,0),"") | F19: Years until cumulative discounted FCF > 0
A20: Min DSCR (financeable years only) | B20: x | C20: =SMALL(CF_Conv!D43:AG43,COUNTIF(CF_Conv!D43:AG43,"<=0")+1) -> 0.98850087 | D20: =SMALL(CF_Regen!D43:AG43,COUNTIF(CF_Regen!D43:AG43,"<=0")+1) -> 1.8299102 | E20: =SMALL(CF_Future!D43:AG43,COUNTIF(CF_Future!D43:AG43,"<=0")+1) -> 1.9731934 | F20: Bank covenant ≥ 1.30
A21: Avg DSCR | B21: x | C21: =AVERAGEIF(CF_Conv!D43:AG43,">0") -> 1.8751425 | D21: =AVERAGEIF(CF_Regen!D43:AG43,">0") -> 1.9615943 | E21: =AVERAGEIF(CF_Future!D43:AG43,">0") -> 1.124577e+15 | F21: Target ≥ 1.40
A23: VALUE FLOWS (30-YEAR NPV @ 8%)
A24: NPV total revenue | B24: € | C24: =NPV(Assumptions!$C$59,CF_Conv!D16:AG16)+CF_Conv!C16 -> 4572158.5 | D24: =NPV(Assumptions!$D$59,CF_Regen!D16:AG16)+CF_Regen!C16 -> 4863415.8 | E24: =NPV(Assumptions!$E$59,CF_Future!D16:AG16)+CF_Future!C16 -> 5347095.8 | F24: Total value created (gross)
A25: NPV total OPEX | B25: € | C25: =NPV(Assumptions!$C$59,CF_Conv!D26:AG26)+CF_Conv!C26 -> -1226047.6 | D25: =NPV(Assumptions!$D$59,CF_Regen!D26:AG26)+CF_Regen!C26 -> -1593826.9 | E25: =NPV(Assumptions!$E$59,CF_Future!D26:AG26)+CF_Future!C26 -> -1561027.3 | F25: Negative = costs
A26: Total CAPEX | B26: € | C26: =Assumptions!C64 -> 2832500 | D26: =Assumptions!D64 -> 3224000 | E26: =Assumptions!E64 -> 3224000 | F26: Year 0
A28: VERDICT
A29: Equity IRR ≥ 8% threshold? | C29: =IF(C5>=0.08,"YES","NO") -> YES | D29: =IF(D5>=0.08,"YES","NO") -> YES | E29: =IF(E5>=0.08,"YES","NO") -> YES | F29: Investment-committee benchmark
A30: NPV @ 5% (≈ WACC) positive? | C30: =IF(C8>0,"YES","NO") -> YES | D30: =IF(D8>0,"YES","NO") -> YES | E30: =IF(E8>0,"YES","NO") -> YES | F30: Project creates value at WACC discount
A31: Min DSCR ≥ 1.30? | C31: =IF(C20>=1.3,"YES","NO") -> NO | D31: =IF(D20>=1.3,"YES","NO") -> YES | E31: =IF(E20>=1.3,"YES","NO") -> YES | F31: Bank-financeable
A33: OVERALL VERDICT (Regenerative) | C33: =IF(AND(D29="YES",D30="YES",D31="YES"),"PROFITABLE — equity IRR target met, NPV positive, bank-financeable",IF(D29="YES","CONDITIONALLY VIABLE — IRR target met but check DSCR/NPV","BELOW TARGET — review assumptions or accept lower hurdle")) -> PROFITABLE — equity IRR target met, NPV positive, bank-financeable

Sheet Sensitivity
A1: Sensitivity Analysis — Regenerative Scenario Equity IRR
A2: How equity IRR responds to ±20% perturbation of each input. Variables ranked by impact magnitude.
A4: Manual sensitivity (recommended)
A5: To test any single assumption: go to Assumptions sheet, change the Regenerative column value (column D), and observe KPIs!D5 (equity IRR).
A6: The pre-computed table below shows ±20% perturbations of the most material drivers, computed via shadow cashflows.
A7: Shadow cashflows replicate the full 30-year CF_Regen logic with one input perturbed. They are stored in rows 30+ for inspection.
A10: Tornado: ±20% perturbation of key drivers
A11: Driver | B11: Base value | C11: -20% value | D11: +20% value | E11: IRR @ -20% | F11: IRR base | G11: IRR @ +20% | H11: Range (pp)
A12: Capacity factor (yield) | B12: 1180 | C12: 944 | D12: 1416 | E12: 0.030749927 | F12: 0.096126531 | G12: 0.14908728 | H12: 0.11833735
A13: PPA price (Y1) | B13: 64 | C13: 51.2 | D13: 76.8 | E13: 0.044257842 | F13: 0.096126531 | G13: 0.14574459 | H13: 0.10148675
A14: CAPEX (€/Wp total) | B14: 0.6448 | C14: 0.51584 | D14: 0.77376 | E14: 0.14675262 | F14: 0.096126531 | G14: 0.059102976 | H14: 0.08764964
A15: Debt LTV share | B15: 0.6 | C15: 0.48 | D15: 0.72 | E15: 0.11752917 | F15: 0.096126531 | G15: 0.074476144 | H15: 0.043053026
A16: O&M cost | B16: 13 | C16: 10.4 | D16: 15.6 | E16: 0.10657002 | F16: 0.096126531 | G16: 0.084943263 | H16: 0.021626756
A17: Cost of senior debt | B17: 0.045 | C17: 0.036 | D17: 0.054 | E17: 0.1025611 | F17: 0.096126531 | G17: 0.089345669 | H17: 0.013215432
A18: Land lease (net) | B18: 1800 | C18: 1440 | D18: 2160 | E18: 0.098501137 | F18: 0.096126531 | G18: 0.093717572 | H18: 0.0047835654
A19: Low-carbon premium | B19: 3 | C19: 2.4 | D19: 3.6 | E19: 0.09404255 | F19: 0.096126531 | G19: 0.098210936 | H19: 0.0041683855
A20: Agrivoltaic premium | B20: 1.5 | C20: 1.2 | D20: 1.8 | E20: 0.094950641 | F20: 0.096126531 | G20: 0.097297792 | H20: 0.0023471501
A25: Interpretation
A26: The 'Range (pp)' column shows the spread between -20% and +20% IRR outcomes in percentage points.
A27: Larger range = more impactful driver. Top variables in this list are where the model is most exposed to assumption error.
A28: Note: sensitivities computed via Python simulation that mirrors the Excel cashflow logic exactly.
A29: To verify any single sensitivity manually: edit the relevant cell in Assumptions (column D, Regenerative), then read IRR from KPIs!D5.
A30: Two-factor stress tests (e.g. low PPA × high cost of debt) should be done by toggling two assumptions simultaneously.
